Workbook
Name current_price: [1]Summary!$C$8
Name Scenario: Segment!$B$3

Sheet BCLO
E2: Model Summary
E3: Bausch + Lomb (BCLO) | F3: 45064 | G3: =EOMONTH(F3,3) -> 45169 | H3: =EOMONTH(G3,3) -> 45260 | I3: =EOMONTH(H3,3) -> 45351 | J3: =EOMONTH(I3,3) -> 45443 | K3: =J3 -> 45443 | L3: =EOMONTH(K3,3) -> 45535 | M3: =EOMONTH(L3,3) -> 45626 | N3: =EOMONTH(M3,3) -> 45716 | O3: =EOMONTH(N3,3) -> 45808 | P3: =O3 -> 45808 | Q3: =EOMONTH(P3,3) -> 45900 | R3: =EOMONTH(Q3,3) -> 45991 | S3: =EOMONTH(R3,3) -> 46081 | T3: =EOMONTH(S3,3) -> 46173 | U3: =T3 -> 46173 | V3: =EOMONTH(U3,3) -> 46265 | W3: =EOMONTH(V3,3) -> 46356 | X3: =EOMONTH(W3,3) -> 46446 | Y3: =EOMONTH(X3,3) -> 46538 | Z3: =Y3 -> 46538 | AA3: =EOMONTH(Z3,3) -> 46630 | AB3: =EOMONTH(AA3,3) -> 46721 | AC3: =EOMONTH(AB3,3) -> 46812 | AD3: =EOMONTH(AC3,3) -> 46904 | AE3: =AD3 -> 46904 | AF3: =EOMONTH(AE3,3) -> 46996 | AG3: =EOMONTH(AF3,3) -> 47087 | AH3: =EOMONTH(AG3,3) -> 47177 | AI3: =EOMONTH(AH3,3) -> 47269 | AJ3: =AI3 -> 47269 | AK3: =EOMONTH(AJ3,3) -> 47361 | AL3: =EOMONTH(AK3,3) -> 47452 | AM3: =EOMONTH(AL3,3) -> 47542 | AN3: =EOMONTH(AM3,3) -> 47634 | AO3: =AN3 -> 47634 | AP3: 47999 | AQ3: 48335 | AR3: 48335
E4: $ Million | F4: =YEAR(F3)-1&"A" -> 2022A | G4: ="Q1 "& YEAR(G3) -> Q1 2023 | H4: ="Q2 "& YEAR(H3) -> Q2 2023 | I4: ="Q3 "& YEAR(I3) -> Q3 2024 | J4: ="Q4 "& YEAR(J3)-1 -> Q4 2023 | K4: =YEAR(K3)-1&"A" -> 2023A | L4: ="Q1 "& YEAR(L3) -> Q1 2024 | M4: ="Q2 "& YEAR(M3) -> Q2 2024 | N4: ="Q3 "& YEAR(N3) -> Q3 2025 | O4: ="Q4 "& YEAR(O3)-1 -> Q4 2024 | P4: =YEAR(P3)-1&"A" -> 2024A | Q4: ="Q1 "& YEAR(Q3) -> Q1 2025 | R4: ="Q2 "& YEAR(R3) -> Q2 2025 | S4: ="Q3 "& YEAR(S3) -> Q3 2026 | T4: ="Q4 "& YEAR(T3)-1 -> Q4 2025 | U4: =YEAR(U3)-1&"A" -> 2025A | V4: ="Q1 "& YEAR(V3) -> Q1 2026 | W4: ="Q2 "& YEAR(W3) -> Q2 2026 | X4: ="Q3 "& YEAR(X3) -> Q3 2027 | Y4: ="Q4 "& YEAR(Y3)-1 -> Q4 2026 | Z4: =YEAR(Z3)-1&"A" -> 2026A | AA4: ="Q1 "& YEAR(AA3) -> Q1 2027 | AB4: ="Q2 "& YEAR(AB3) -> Q2 2027 | AC4: ="Q3 "& YEAR(AC3) -> Q3 2028 | AD4: ="Q4 "& YEAR(AD3)-1 -> Q4 2027 | AE4: =YEAR(AE3)-1&"A" -> 2027A | AF4: ="Q1 "& YEAR(AF3) -> Q1 2028 | AG4: ="Q2 "& YEAR(AG3) -> Q2 2028 | AH4: ="Q3 "& YEAR(AH3) -> Q3 2029 | AI4: ="Q4 "& YEAR(AI3)-1 -> Q4 2028 | AJ4: =YEAR(AJ3)-1&"E" -> 2028E | AK4: ="Q1 "& YEAR(AK3) -> Q1 2029 | AL4: ="Q2 "& YEAR(AL3) -> Q2 2029 | AM4: ="Q3 "& YEAR(AM3) -> Q3 2030 | AN4: ="Q4 "& YEAR(AN3)-1 -> Q4 2029 | AO4: =YEAR(AO3)-1&"E" -> 2029E | AP4: =YEAR(AP3)-1&"E" -> 2030E | AQ4: =YEAR(AQ3)-1&"E" -> 2031E | AR4: =YEAR(AR3)-1&"E" -> 2031E
A5: Bausch + Lomb | E5: Key Perfomormance Indicators
A6: Author | D6: Owen Purnomo | E6: Vision Care Revenue | F6: =Segment!F8 -> 2369 | G6: =Segment!G8 -> 0 | H6: =Segment!H8 -> 0 | I6: =Segment!I8 -> 0 | J6: =Segment!J8 -> 0 | K6: =Segment!K8 -> 2543 | L6: =Segment!L8 -> 0 | M6: =Segment!M8 -> 0 | ... AR6: =Segment!AR8 -> 3965.8181
A7: Ticker | D7: BCLO | E7: Comp YoY | F7: - | K7: =Segment!K9 -> 0.073448713 | L7: =Segment!L9 -> #DIV/0! | M7: =Segment!M9 -> #DIV/0! | N7: =Segment!N9 -> #DIV/0! | O7: =Segment!O9 -> #DIV/0! | P7: =Segment!P9 -> 0.077074322 | Q7: =Segment!Q9 -> #DIV/0! | R7: =Segment!R9 -> #DIV/0! | ... AR7: =Segment!AR9 -> 0.03
A8: Current Price | D8: 16.82 | E8: Pharmaceutial Revenue | F8: =Segment!F13 -> 681 | G8: =Segment!G13 -> 0 | H8: =Segment!H13 -> 0 | I8: =Segment!I13 -> 0 | J8: =Segment!J13 -> 0 | K8: =Segment!K13 -> 836 | L8: =Segment!L13 -> 0 | M8: =Segment!M13 -> 0 | ... AR8: =Segment!AR13 -> 1624.6934
E9: Comp YoY | F9: =Segment!F9 -> - | G9: =Segment!G9 -> 0 | H9: =Segment!H9 -> 0 | I9: =Segment!I9 -> 0 | J9: =Segment!J9 -> 0 | K9: =Segment!K9 -> 0.073448713 | L9: =Segment!L9 -> #DIV/0! | M9: =Segment!M9 -> #DIV/0! | ... AR9: =Segment!AR9 -> 0.03
E10: Surgical Revenue | F10: =Segment!F18 -> 718 | G10: =Segment!G18 -> 0 | H10: =Segment!H18 -> 0 | I10: =Segment!I18 -> 0 | J10: =Segment!J18 -> 0 | K10: =Segment!K18 -> 767 | L10: =Segment!L18 -> 0 | M10: =Segment!M18 -> 0 | ... AR10: =Segment!AR18 -> 1288.6786
E11: Comp YoY | F11: =Segment!F19 -> - | G11: =Segment!G19 -> 0 | H11: =Segment!H19 -> 0 | I11: =Segment!I19 -> 0 | J11: =Segment!J19 -> 0 | K11: =Segment!K19 -> 0.068245125 | L11: =Segment!L19 -> #DIV/0! | M11: =Segment!M19 -> #DIV/0! | ... AR11: =Segment!AR19 -> 0.04
E12: Income Statement
E13: Revenues | F13: =Segment!F6 -> 3768 | G13: =Segment!G6 -> 0 | H13: =Segment!H6 -> 0 | I13: =Segment!I6 -> 0 | J13: =Segment!J6 -> 0 | K13: =Segment!K6 -> 4146 | L13: =Segment!L6 -> 0 | M13: =Segment!M6 -> 0 | ... AR13: =Segment!AR6 -> 6879.1902
E14: YoY Growth | F14: - | K14: =K13/F13-1 -> 0.10031847 | L14: =L13/G13-1 -> #DIV/0! | M14: =M13/H13-1 -> #DIV/0! | N14: =N13/I13-1 -> #DIV/0! | O14: =O13/J13-1 -> #DIV/0! | P14: =P13/K13-1 -> 0.15557164 | Q14: =Q13/L13-1 -> #DIV/0! | R14: =R13/M13-1 -> #DIV/0! | ... AO14: =AO13/AJ13-1 -> 0.049348819 | AP14: =AP13/AO13-1 -> 0.029388899 | AQ14: =AQ13/AP13-1 -> 0.02942977 | AR14: =AR13/AQ13-1 -> 0.029470654
E15: Cost of Sales | F15: =Segment!F26+8 -> 1519 | G15: =Segment!G26 -> 0 | H15: =Segment!H26 -> 0 | I15: =Segment!I26 -> 0 | J15: =Segment!J26 -> 0 | K15: =Segment!K26+2 -> 1642 | L15: =Segment!L26 -> 0 | M15: =Segment!M26 -> 0 | N15: =Segment!N26 -> 0 | O15: =Segment!O26 -> 0 | P15: =Segment!P26+2 -> 1870 | Q15: =Segment!Q26 -> 0 | R15: =Segment!R26 -> 0 | S15: =Segment!S26 -> 0 | T15: =Segment!T26 -> 0 | U15: =Segment!U26+5 -> 2050 | V15: =Segment!V26 -> 0 | W15: =Segment!W26 -> 0 | X15: =Segment!X26 -> 0 | Y15: =Segment!Y26 -> 0 | Z15: =Segment!Z26 -> 2183.2187 | AA15: =Segment!AA26 -> 0 | AB15: =Segment!AB26 -> 0 | AC15: =Segment!AC26 -> 0 | ... AR15: =Segment!AR26 -> 2751.6761
E16: Gross Profit | F16: =F13-F15 -> 2249 | G16: =G13-G15 -> 0 | H16: =H13-H15 -> 0 | I16: =I13-I15 -> 0 | J16: =J13-J15 -> 0 | K16: =K13-K15 -> 2504 | L16: =L13-L15 -> 0 | M16: =M13-M15 -> 0 | ... AR16: =AR13-AR15 -> 4127.5141
E17: Gross Margin % | F17: =F16/F13 -> 0.59686837 | G17: =G16/G13 -> #DIV/0! | H17: =H16/H13 -> #DIV/0! | I17: =I16/I13 -> #DIV/0! | J17: =J16/J13 -> #DIV/0! | K17: =K16/K13 -> 0.60395562 | L17: =L16/L13 -> #DIV/0! | M17: =M16/M13 -> #DIV/0! | ... AR17: =AR16/AR13 -> 0.6
E18: SG&A | F18: 1478 | K18: 1736 | P18: 2082 | U18: 2234 | Z18: =Z13*Z19 -> 2297.1357 | AA18: =AA13*AA19 -> #DIV/0! | AB18: =AB13*AB19 -> #DIV/0! | AC18: =AC13*AC19 -> #DIV/0! | AD18: =AD13*AD19 -> #DIV/0! | AE18: =AE13*AE19 -> 2451.2901 | AF18: =AF13*AF19 -> #DIV/0! | AG18: =AG13*AG19 -> #DIV/0! | ... AR18: =AR13*AR19 -> 2953.2455
E19: As % of Sales | F19: =F18/F13 -> 0.39225053 | G19: =G18/G13 -> #DIV/0! | H19: =H18/H13 -> #DIV/0! | I19: =I18/I13 -> #DIV/0! | J19: =J18/J13 -> #DIV/0! | K19: =K18/K13 -> 0.41871684 | L19: =L18/L13 -> #DIV/0! | M19: =M18/M13 -> #DIV/0! | ... Y19: =Y18/Y13 -> #DIV/0! | Z19: =AVERAGE(F19,K19,P19,U19) -> 0.42087138 | AA19: =AVERAGE(G19,L19,Q19,V19) -> #DIV/0! | AB19: =AVERAGE(H19,M19,R19,W19) -> #DIV/0! | AC19: =AVERAGE(I19,N19,S19,X19) -> #DIV/0! | AD19: =AVERAGE(J19,O19,T19,Y19) -> #DIV/0! | AE19: =AVERAGE(K19,P19,U19,Z19) -> 0.42802659 | AF19: =AVERAGE(L19,Q19,V19,AA19) -> #DIV/0! | AG19: =AVERAGE(M19,R19,W19,AB19) -> #DIV/0! | ... AO19: =AVERAGE(U19,Z19,AE19,AJ19) -> 0.42930134 | AP19: =AVERAGE(U19,Z19,AE19,AJ19,AO19) -> 0.42930134 | AQ19: =AP19 -> 0.42930134 | AR19: =AQ19 -> 0.42930134
E20: R&D Expense | F20: 307 | K20: 324 | P20: 343 | U20: 371 | Z20: =Z13*Z21 -> 414.73869 | AE20: =AE13*AE21 -> 435.17233 | AF20: =AF13*AF21 -> 0 | AG20: =AG13*AG21 -> 0 | AH20: =AH13*AH21 -> 0 | AI20: =AI13*AI21 -> 0 | AJ20: =AJ13*AJ21 -> 456.63013 | AK20: =AK13*AK21 -> 0 | AL20: =AL13*AL21 -> 0 | ... AR20: =AR13*AR21 -> 522.72662
E21: As % of Sales | F21: =F20/F13 -> 0.081475584 | G21: =G20/G13 -> #DIV/0! | H21: =H20/H13 -> #DIV/0! | I21: =I20/I13 -> #DIV/0! | J21: =J20/J13 -> #DIV/0! | K21: =K20/K13 -> 0.078147612 | L21: =L20/L13 -> #DIV/0! | M21: =M20/M13 -> #DIV/0! | ... Y21: =Y20/Y13 -> #DIV/0! | Z21: =AVERAGE(F21,K21,P21,U21) -> 0.075986651 | AA21: =AVERAGE(G21,L21,Q21,V21) -> #DIV/0! | AB21: =AVERAGE(H21,M21,R21,W21) -> #DIV/0! | AC21: =AVERAGE(I21,N21,S21,X21) -> #DIV/0! | AD21: =AVERAGE(J21,O21,T21,Y21) -> #DIV/0! | AE21: =$Z$21 -> 0.075986651 | AF21: =$Z$21 -> 0.075986651 | AG21: =$Z$21 -> 0.075986651 | AH21: =$Z$21 -> 0.075986651 | AI21: =$Z$21 -> 0.075986651 | AJ21: =$Z$21 -> 0.075986651 | AK21: =$Z$21 -> 0.075986651 | AL21: =$Z$21 -> 0.075986651 | ... AR21: =$Z$21 -> 0.075986651
E22: Other Expenses | F22: 13 | K22: 74 | P22: 44 | U22: 75 | Z22: =AVERAGE(F22:U22) -> 51.5 | AA22: =AVERAGE(G22:V22) -> 64.333333 | AB22: =AVERAGE(H22:W22) -> 64.333333 | AC22: =AVERAGE(I22:X22) -> 64.333333 | AD22: =AVERAGE(J22:Y22) -> 64.333333 | AE22: =AVERAGE(K22:Z22) -> 61.125 | AF22: =AVERAGE(L22:AA22) -> 58.708333 | AG22: =AVERAGE(M22:AB22) -> 59.833333 | ... AO22: =AVERAGE(U22:AJ22) -> 62.193514 | AP22: =AO22 -> 62.193514 | AQ22: =AP22 -> 62.193514 | AR22: =AQ22 -> 62.193514
E23: EBITDA | F23: =F16-F18-F20-F22 -> 451 | G23: =G16-G18-G20-G22 -> 0 | H23: =H16-H18-H20-H22 -> 0 | I23: =I16-I18-I20-I22 -> 0 | J23: =J16-J18-J20-J22 -> 0 | K23: =K16-K18-K20-K22 -> 370 | L23: =L16-L18-L20-L22 -> 0 | M23: =M16-M18-M20-M22 -> 0 | ... AR23: =AR16-AR18-AR20-AR22 -> 589.34844
E24: Margin % | F24: =F23/F13 -> 0.11969214 | G24: =G23/G13 -> #DIV/0! | H24: =H23/H13 -> #DIV/0! | I24: =I23/I13 -> #DIV/0! | J24: =J23/J13 -> #DIV/0! | K24: =K23/K13 -> 0.089242644 | L24: =L23/L13 -> #DIV/0! | M24: =M23/M13 -> #DIV/0! | ... AR24: =AR23/AR13 -> 0.085671194
E25: Asset Impairments | F25: 15 | K25: 54 | P25: 29 | U25: 20
E26: Goodwill Impairments | F26: 824 | K26: 493 | P26: 0 | U26: 0
E27: Restructuring | F27: 63 | K27: 62 | P27: 32 | U27: 30
E28: Other Adjustments (Non-Recurring) | F28: 0 | K28: 0 | P28: 207 | U28: 60
E29: Total Add-backs | F29: =SUM(F25:F28) -> 902 | G29: =SUM(G25:G28) -> 0 | H29: =SUM(H25:H28) -> 0 | I29: =SUM(I25:I28) -> 0 | J29: =SUM(J25:J28) -> 0 | K29: =SUM(K25:K28) -> 609 | L29: =SUM(L25:L28) -> 0 | M29: =SUM(M25:M28) -> 0 | ... U29: =SUM(U25:U28) -> 110
E30: Adjusted EBITDA | F30: =F23+F29 -> 1353 | G30: =G23+G29 -> 0 | H30: =H23+H29 -> 0 | I30: =I23+I29 -> 0 | J30: =J23+J29 -> 0 | K30: =K23+K29 -> 979 | L30: =L23+L29 -> 0 | M30: =M23+M29 -> 0 | ... AR30: =AR23+AR29 -> 589.34844
E31: Margin % | F31: =F30/F13 -> 0.35907643 | G31: =G30/G13 -> #DIV/0! | H31: =H30/H13 -> #DIV/0! | I31: =I30/I13 -> #DIV/0! | J31: =J30/J13 -> #DIV/0! | K31: =K30/K13 -> 0.23613121 | L31: =L30/L13 -> #DIV/0! | M31: =M30/M13 -> #DIV/0! | ... AR31: =AR30/AR13 -> 0.085671194
E32: Depreciation & Amortization | F32: 387 | K32: 412 | P32: 456 | U32: 439 | Z32: =AVERAGE(F32,K32,P32,U32) -> 423.5 | AE32: =AVERAGE(F32:Z32) -> 423.5 | AF32: =AVERAGE(G32:AA32) -> 432.625 | AG32: =AVERAGE(H32:AB32) -> 432.625 | AH32: =AVERAGE(I32:AC32) -> 432.625 | AI32: =AVERAGE(J32:AD32) -> 432.625 | AJ32: =AVERAGE(F32:AE32) -> 423.5 | AO32: =AVERAGE(F32:AJ32) -> 426.81818 | AP32: =AVERAGE(G32:AK32) -> 430.8 | AQ32: =AVERAGE(H32:AL32) -> 430.8 | AR32: =AVERAGE(I32:AM32) -> 430.8
E33: EBIT | F33: =F23-F32 -> 64 | G33: =G23-G32 -> 0 | H33: =H23-H32 -> 0 | I33: =I23-I32 -> 0 | J33: =J23-J32 -> 0 | K33: =K23-K32 -> -42 | L33: =L23-L32 -> 0 | M33: =M23-M32 -> 0 | ... Y33: =Y23-Y32 -> 0 | Z33: =Z30-Z32 -> 87.953692 | AA33: =AA30-AA32 -> #DIV/0! | AB33: =AB30-AB32 -> #DIV/0! | AC33: =AC30-AC32 -> #DIV/0! | AD33: =AD30-AD32 -> #DIV/0! | AE33: =AE30-AE32 -> 65.087092 | AF33: =AF30-AF32 -> #DIV/0! | AG33: =AG30-AG32 -> #DIV/0! | ... AR33: =AR30-AR32 -> 158.54844
E34: Margin % | F34: =F33/F13 -> 0.016985138 | G34: =G33/G13 -> #DIV/0! | H34: =H33/H13 -> #DIV/0! | I34: =I33/I13 -> #DIV/0! | J34: =J33/J13 -> #DIV/0! | K34: =K33/K13 -> -0.010130246 | L34: =L33/L13 -> #DIV/0! | M34: =M33/M13 -> #DIV/0! | ... AR34: =AR33/AR13 -> 0.023047544
E35: Adjusted EBIT | F35: =F30-F32 -> 966 | G35: =G30-G32 -> 0 | H35: =H30-H32 -> 0 | I35: =I30-I32 -> 0 | J35: =J30-J32 -> 0 | K35: =K30-K32 -> 567 | L35: =L30-L32 -> 0 | M35: =M30-M32 -> 0 | ... AR35: =AR30-AR32 -> 158.54844
E36: Margin % | F36: =F35/F13 -> 0.25636943 | G36: =G35/G13 -> #DIV/0! | H36: =H35/H13 -> #DIV/0! | I36: =I35/I13 -> #DIV/0! | J36: =J35/J13 -> #DIV/0! | K36: =K35/K13 -> 0.13675832 | L36: =L35/L13 -> #DIV/0! | M36: =M35/M13 -> #DIV/0! | ... AR36: =AR35/AR13 -> 0.023047544
E37: Interest Expense, net | F37: =146-6-6 -> 134 | K37: =283-15+28 -> 296 | P37: =399-15+12 -> 396 | U37: =421-12+6+15 -> 430 | Z37: 365 | AE37: 314 | AJ37: 235 | AO37: 75 | AP37: 75 | AQ37: 75 | AR37: 75
E38: As % of Beg Cash
E39: Earnings Before Tax | F39: =F35-F37 -> 832 | G39: =G35-G37 -> 0 | H39: =H35-H37 -> 0 | I39: =I35-I37 -> 0 | J39: =J35-J37 -> 0 | K39: =K35-K37 -> 271 | L39: =L35-L37 -> 0 | M39: =M35-M37 -> 0 | ... AR39: =AR35-AR37 -> 83.548439
E40: Income Tax | F40: 58 | K40: 82 | P40: 71 | U40: 35 | Z40: =Z39*0.2 -> -55.409262 | AA40: =AA39*0.2 -> #DIV/0! | AB40: =AB39*0.2 -> #DIV/0! | AC40: =AC39*0.2 -> #DIV/0! | AD40: =AD39*0.2 -> #DIV/0! | AE40: =AE39*0.2 -> -49.782582 | AF40: =AF39*0.2 -> #DIV/0! | AG40: =AG39*0.2 -> #DIV/0! | ... AR40: =AR39*0.2 -> 16.709688
E41: Tax Rate % | F41: =F40/F39 -> 0.069711538 | G41: =G40/G39 -> #DIV/0! | H41: =H40/H39 -> #DIV/0! | I41: =I40/I39 -> #DIV/0! | J41: =J40/J39 -> #DIV/0! | K41: =K40/K39 -> 0.30258303 | L41: =L40/L39 -> #DIV/0! | M41: =M40/M39 -> #DIV/0! | ... AR41: =AR40/AR39 -> 0.2
E42: Net Income/Loss | F42: =F39-F40 -> 774 | G42: =G39-G40 -> 0 | H42: =H39-H40 -> 0 | I42: =I39-I40 -> 0 | J42: =J39-J40 -> 0 | K42: =K39-K40 -> 189 | L42: =L39-L40 -> 0 | M42: =M39-M40 -> 0 | ... AR42: =AR39-AR40 -> 66.838751
E43: Net Margin % | F43: =F42/F13 -> 0.20541401 | G43: =G42/G13 -> #DIV/0! | H43: =H42/H13 -> #DIV/0! | I43: =I42/I13 -> #DIV/0! | J43: =J42/J13 -> #DIV/0! | K43: =K42/K13 -> 0.045586107 | L43: =L42/L13 -> #DIV/0! | M43: =M42/M13 -> #DIV/0! | ... AR43: =AR42/AR13 -> 0.0097160784
E44: Diluted Shares Outstanding | F44: 350.2 | K44: 350.5 | P44: 351.8 | U44: 353.8 | Z44: =U44 -> 353.8 | AA44: =V44 -> 0 | AB44: =W44 -> 0 | AC44: =X44 -> 0 | AD44: =Y44 -> 0 | AE44: =Z44 -> 353.8 | AF44: =AA44 -> 0 | AG44: =AB44 -> 0 | ... AO44: =AJ44 -> 353.8 | AP44: =AO44 -> 353.8 | AQ44: =AP44 -> 353.8 | AR44: =AQ44 -> 353.8
E46: EPS - Diluted | F46: =F42/F44 -> 2.2101656 | G46: =G42/G44 -> #DIV/0! | H46: =H42/H44 -> #DIV/0! | I46: =I42/I44 -> #DIV/0! | J46: =J42/J44 -> #DIV/0! | K46: =K42/K44 -> 0.53922967 | L46: =L42/L44 -> #DIV/0! | M46: =M42/M44 -> #DIV/0! | ... AR46: =AR42/AR44 -> 0.18891676
E47: YoY Growth | F47: - | K47: =(K46-F46)/F46 -> -0.75602296 | L47: =(L46-G46)/G46 -> #DIV/0! | M47: =(M46-H46)/H46 -> #DIV/0! | N47: =(N46-I46)/I46 -> #DIV/0! | O47: =(O46-J46)/J46 -> #DIV/0! | P47: =(P46-K46)/K46 -> -2.0701051 | Q47: =(Q46-L46)/L46 -> #DIV/0! | R47: =(R46-M46)/M46 -> #DIV/0! | ... AO47: =(AO46-AJ46)/AJ46 -> -1.2119599 | AP47: =(AP46-AO46)/AO46 -> 0.40834693 | AQ47: =(AQ46-AP46)/AP46 -> 0.38658145 | AR47: =(AR46-AQ46)/AQ46 -> 0.28740562
E49: Cash Flow Statement
E50: Net Income | F50: =F42 -> 774 | G50: =G42 -> 0 | H50: =H42 -> 0 | I50: =I42 -> 0 | J50: =J42 -> 0 | K50: =K42 -> 189 | L50: =L42 -> 0 | M50: =M42 -> 0 | ... AR50: =AR42 -> 66.838751
E51: Depreciation & Amortization | F51: =F32 -> 387 | G51: =G32 -> 0 | H51: =H32 -> 0 | I51: =I32 -> 0 | J51: =J32 -> 0 | K51: =K32 -> 412 | L51: =L32 -> 0 | M51: =M32 -> 0 | ... AR51: =AR32 -> 430.8
E52: Stock Based Compensation | F52: 62 | K52: 74 | P52: 92 | U52: 149 | Z52: =Z13*Z53 -> 109.16093 | AA52: =AA13*AA53 -> 0 | AB52: =AB13*AB53 -> 0 | AC52: =AC13*AC53 -> 0 | AD52: =AD13*AD53 -> 0 | AE52: =AE13*AE53 -> 114.53915 | AF52: =AF13*AF53 -> 0 | AG52: =AG13*AG53 -> 0 | ... AR52: =AR13*AR53 -> 137.5838
E53: As % of Sales | F53: =F52/F13 -> 0.016454352 | G53: =G52/G13 -> #DIV/0! | H53: =H52/H13 -> #DIV/0! | I53: =I52/I13 -> #DIV/0! | J53: =J52/J13 -> #DIV/0! | K53: =K52/K13 -> 0.017848529 | L53: =L52/L13 -> #DIV/0! | M53: =M52/M13 -> #DIV/0! | ... U53: =U52/U13 -> 0.029209959 | Z53: 0.02 | AA53: 0.02 | AB53: 0.02 | AC53: 0.02 | AD53: 0.02 | AE53: 0.02 | AF53: 0.02 | AG53: 0.02 | AH53: 0.02 | AI53: 0.02 | AJ53: 0.02 | AK53: 0.02 | AL53: 0.02 | AM53: 0.02 | AN53: 0.02 | AO53: 0.02 | AP53: 0.02 | AQ53: 0.02 | AR53: 0.02
E54: Δ Working Capital | F54: -19 | K54: -287 | P54: -87 | U54: -97 | Z54: -60 | AE54: -55 | AJ54: -45 | AO54: -40 | AP54: -35 | AQ54: -30 | AR54: -25
E55: Other | F55: -38 | K55: 106 | P55: 87 | U55: 143 | Z55: 50 | AE55: 50 | AJ55: 50 | AO55: 50 | AP55: 50 | AQ55: 50 | AR55: 50
E56: Cash Flow from Operations (CFO) | F56: =SUM(F50,F51,F52,F54,F55) -> 1166 | G56: =SUM(G50,G51,G52,G54,G55) -> 0 | H56: =SUM(H50,H51,H52,H54,H55) -> 0 | I56: =SUM(I50,I51,I52,I54,I55) -> 0 | J56: =SUM(J50,J51,J52,J54,J55) -> 0 | K56: =SUM(K50,K51,K52,K54,K55) -> 494 | L56: =SUM(L50,L51,L52,L54,L55) -> 0 | M56: =SUM(M50,M51,M52,M54,M55) -> 0 | ... AR56: =SUM(AR50,AR51,AR52,AR54,AR55) -> 660.22255
E57: Capital Expenditures | F57: 175 | K57: 181 | P57: 291 | U57: 349 | Z57: 285 | AE57: 288 | AJ57: 287 | AO57: 290 | AP57: 290 | AQ57: 290 | AR57: 290
E58: Free Cash Flow (FCF) | F58: =F56-F57 -> 991 | G58: =G56-G57 -> 0 | H58: =H56-H57 -> 0 | I58: =I56-I57 -> 0 | J58: =J56-J57 -> 0 | K58: =K56-K57 -> 313 | L58: =L56-L57 -> 0 | M58: =M56-M57 -> 0 | ... AR58: =AR56-AR57 -> 370.22255
E59: Conversion % | F59: =F58/F42 -> 1.2803618 | G59: =G58/G42 -> #DIV/0! | H59: =H58/H42 -> #DIV/0! | I59: =I58/I42 -> #DIV/0! | J59: =J58/J42 -> #DIV/0! | K59: =K58/K42 -> 1.6560847 | L59: =L58/L42 -> #DIV/0! | M59: =M58/M42 -> #DIV/0! | ... AR59: =AR58/AR42 -> 5.5390406
E60: Stock Issuance/(Repurchases) | F60: 0 | K60: 0 | P60: -12 | U60: -15 | Z60: 0 | AE60: 0 | AJ60: 0 | AO60: 0 | AP60: 0 | AQ60: 0 | AR60: 0
E61: Dividends Paid | F61: 0 | G61: 0 | H61: 0 | I61: 0 | J61: 0 | K61: 0 | L61: 0 | M61: 0 | N61: 0 | O61: 0 | P61: 0 | Q61: 0 | R61: 0 | S61: 0 | T61: 0 | U61: 0 | V61: 0 | W61: 0 | X61: 0 | Y61: 0 | Z61: 0 | AA61: 0 | AB61: 0 | AC61: 0 | AD61: 0 | AE61: 0 | AF61: 0 | AG61: 0 | AH61: 0 | AI61: 0 | AJ61: 0 | AK61: 0 | AL61: 0 | AM61: 0 | AN61: 0 | AO61: 0 | AP61: 0 | AQ61: 0 | AR61: 0
E62: Other Financing Activities | F62: -2377 | K62: -37 | P62: -11 | U62: -21 | Z62: -25 | AE62: -10 | AJ62: -15 | AO62: -10 | AP62: 0
E63: Foreign Exchange | F63: -8 | K63: -2 | P63: -16 | U63: 10 | Z63: 0 | AE63: 0 | AJ63: 0 | AO63: 0 | AP63: 0 | AQ63: 0 | AR63: 0
E64: Net Change in Cash | F64: =SUM(F58,F60:F63) -> -1394 | G64: =SUM(G58,G60:G63) -> 0 | H64: =SUM(H58,H60:H63) -> 0 | I64: =SUM(I58,I60:I63) -> 0 | J64: =SUM(J58,J60:J63) -> 0 | K64: =SUM(K58,K60:K63) -> 274 | L64: =SUM(L58,L60:L63) -> 0 | M64: =SUM(M58,M60:M63) -> 0 | ... AR64: =SUM(AR58,AR60:AR63) -> 370.22255
E66: FCF per Share | F66: =F58/F44 -> 2.8298115 | G66: =G58/G44 -> #DIV/0! | H66: =H58/H44 -> #DIV/0! | I66: =I58/I44 -> #DIV/0! | J66: =J58/J44 -> #DIV/0! | K66: =K58/K44 -> 0.89300999 | L66: =L58/L44 -> #DIV/0! | M66: =M58/M44 -> #DIV/0! | ... AR66: =AR58/AR44 -> 1.0464176
E67: FCF Yield | F67: =F66/F100 -> 0.16824088 | G67: =G66/G100 -> #DIV/0! | H67: =H66/H100 -> #DIV/0! | I67: =I66/I100 -> #DIV/0! | J67: =J66/J100 -> #DIV/0! | K67: =K66/K100 -> 0.046510937 | L67: =L66/L100 -> #DIV/0! | M67: =M66/M100 -> #DIV/0! | ... AR67: =AR66/AR100 -> 0.061553978
E69: Balance Sheet
E70: Cash & Equivalents | F70: 354 | K70: 331 | P70: 305 | U70: 383 | Z70: =U70+Z64 -> 374.02389 | AA70: =V70+AA64 -> #DIV/0! | AB70: =W70+AB64 -> #DIV/0! | AC70: =X70+AC64 -> #DIV/0! | AD70: =Y70+AD64 -> #DIV/0! | AE70: =Z70+AE64 -> 409.93271 | AF70: =AA70+AF64 -> #DIV/0! | AG70: =AB70+AG64 -> #DIV/0! | ... AO70: =AJ70+AO64 -> 820.71137 | AP70: =AO70+AP64 -> 1143.7786 | AQ70: =AP70+AQ64 -> 1490.1412 | AR70: =AQ70+AR64 -> 1860.3637
E71: Restricted Cash | F71: 26 | K71: 3 | P71: 11 | U71: 14 | Z71: 0 | AE71: 0 | AJ71: 0 | AO71: 0 | AP71: 0 | AQ71: 0 | AR71: 0
E72: Receivables | F72: 724 | K72: 839 | P72: 1026 | U72: 1221 | Z72: 1250 | AE72: 1300 | AJ72: 1350 | AO72: 1400 | AP72: 1450 | AQ72: 1500 | AR72: 1550
E73: Inventory | F73: 628 | K73: 1028 | P73: 1036 | U73: 976 | Z73: 1100 | AE73: 1150 | AJ73: 1200 | AO73: 1250 | AP73: 1300 | AQ73: 1350 | AR73: =1400 -> 1400
E74: Prepaid & Other Assets | F74: 405 | K74: 541 | P74: 410 | U74: 383 | Z74: =AVERAGE(F74:U74) -> 434.75 | AA74: =AVERAGE(G74:V74) -> 444.66667 | AB74: =AVERAGE(H74:W74) -> 444.66667 | AC74: =AVERAGE(I74:X74) -> 444.66667 | AD74: =AVERAGE(J74:Y74) -> 444.66667 | AE74: =AVERAGE(K74:Z74) -> 442.1875 | AF74: =AVERAGE(L74:AA74) -> 418.10417 | AG74: =AVERAGE(M74:AB74) -> 423.41667 | ... AR74: =AVERAGE(X74:AM74) -> 434.18349
E75: Current Assets | F75: =SUM(F70:F74) -> 2137 | G75: =SUM(G70:G74) -> 0 | H75: =SUM(H70:H74) -> 0 | I75: =SUM(I70:I74) -> 0 | J75: =SUM(J70:J74) -> 0 | K75: =SUM(K70:K74) -> 2742 | L75: =SUM(L70:L74) -> 0 | M75: =SUM(M70:M74) -> 0 | ... AR75: =SUM(AR70:AR74) -> 5244.5472
E76: Property, Plant, Equipment | F76: 1300 | K76: 1390 | P76: 1485 | U76: 1762 | Z76: =U76-P76+U76 -> 2039 | AA76: =V76-Q76+V76 -> 0 | AB76: =W76-R76+W76 -> 0 | AC76: =X76-S76+X76 -> 0 | AD76: =Y76-T76+Y76 -> 0 | AE76: =Z76-U76+Z76 -> 2316 | AF76: =AA76-V76+AA76 -> 0 | AG76: =AB76-W76+AB76 -> 0 | ... AO76: =AJ76-AE76+AJ76 -> 2870 | AP76: =AO76+AJ76-AO76 -> 2593 | AQ76: =AP76-AO76+AP76 -> 2316 | AR76: =AQ76-AP76+AQ76 -> 2039
E77: Intangible Assets | F77: 2058 | K77: 3589 | P77: 3494 | U77: 3281 | Z77: =AVERAGE(F77:U77) -> 3105.5 | AA77: =AVERAGE(G77:V77) -> 3454.6667 | AB77: =AVERAGE(H77:W77) -> 3454.6667 | AC77: =AVERAGE(I77:X77) -> 3454.6667 | AD77: =AVERAGE(J77:Y77) -> 3454.6667 | AE77: =AVERAGE(K77:Z77) -> 3367.375 | AF77: =AVERAGE(L77:AA77) -> 3333.7917 | AG77: =AVERAGE(M77:AB77) -> 3357.9667 | ... AR77: =AVERAGE(X77:AM77) -> 3372.5804
E78: Goodwil | F78: 4507 | K78: 4575 | P78: 4523 | U78: 4758 | Z78: =AVERAGE(F78:U78) -> 4590.75 | AA78: =V78 -> 0 | AB78: =W78 -> 0 | AC78: =X78 -> 0 | AD78: =Y78 -> 0 | AE78: =Z78 -> 4590.75 | AF78: =AA78 -> 0 | AG78: =AB78 -> 0 | AH78: =AC78 -> 0 | ... AO78: =AJ78 -> 4590.75 | AP78: =AO78 -> 4590.75 | AQ78: =AP78 -> 4590.75 | AR78: =AQ78 -> 4590.75
E79: Deffered Tax Assets | F79: 927 | K79: 921 | P79: 885 | U79: 934 | Z79: 900 | AE79: 870 | AJ79: 850 | AO79: 840 | AP79: 830 | AQ79: 820 | AR79: 810
E80: Non Current Assets | F80: 215 | K80: 225 | P80: 294 | U80: 310 | Z80: 290 | AE80: 280 | AJ80: 270 | AO80: 260 | AP80: 250 | AQ80: 240 | AR80: 230
E81: Total Assets | F81: =SUM(F75:J80) -> 11144 | G81: =SUM(G75:K80) -> 13442 | H81: =SUM(H75:L80) -> 13442 | I81: =SUM(I75:M80) -> 13442 | J81: =SUM(J75:N80) -> 13442 | K81: =SUM(K75:O80) -> 13442 | L81: =SUM(L75:P80) -> 13469 | M81: =SUM(M75:Q80) -> 13469 | ... Y81: =SUM(Y75:AC80) -> #DIV/0! | Z81: =SUM(Z75:Z80) -> 14084.024 | AA81: =SUM(AA75:AA80) -> #DIV/0! | AB81: =SUM(AB75:AB80) -> #DIV/0! | AC81: =SUM(AC75:AC80) -> #DIV/0! | AD81: =SUM(AD75:AD80) -> #DIV/0! | AE81: =SUM(AE75:AE80) -> 14726.245 | AF81: =SUM(AF75:AF80) -> #DIV/0! | AG81: =SUM(AG75:AG80) -> #DIV/0! | ... AR81: =SUM(AR75:AR80) -> 16286.878
E82: Accounts Payable | F82: 370 | K82: 522 | P82: 389 | U82: 388 | Z82: 400 | AE82: 420 | AJ82: 440 | AO82: 460 | AP82: 480 | AQ82: 500 | AR82: 520
E83: Accrued Liabilities | F83: 901 | K83: 1027 | P83: 1309 | U83: 1493 | Z83: =1490 -> 1490 | AA83: =1490 -> 1490 | AB83: =1490 -> 1490 | AC83: =1490 -> 1490 | AD83: =1490 -> 1490 | AE83: =1490 -> 1490 | AF83: =1490 -> 1490 | AG83: =1490 -> 1490 | ... AR83: =1490 -> 1490
E84: Other Current Liabilities | F84: 25 | K84: 30 | P84: 40 | U84: 39 | Z84: 40 | AE84: 40 | AJ84: 40 | AO84: 40 | AP84: 40 | AQ84: 40 | AR84: 40
E85: Current Liabilities | F85: =SUM(F82:F84) -> 1296 | G85: =SUM(G82:G84) -> 0 | H85: =SUM(H82:H84) -> 0 | I85: =SUM(I82:I84) -> 0 | J85: =SUM(J82:J84) -> 0 | K85: =SUM(K82:K84) -> 1579 | L85: =SUM(L82:L84) -> 0 | M85: =SUM(M82:M84) -> 0 | ... AR85: =SUM(AR82:AR84) -> 2050
E86: Deffered Taxes & Other Liabilities | F86: =7+329 -> 336 | K86: =14+397 -> 411 | P86: =13+430 -> 443 | U86: =19+521 -> 540 | Z86: =AVERAGE(F86:U86) -> 432.5 | AA86: =AVERAGE(G86:V86) -> 464.66667 | AB86: =AVERAGE(H86:W86) -> 464.66667 | AC86: =AVERAGE(I86:X86) -> 464.66667 | AD86: =AVERAGE(J86:Y86) -> 464.66667 | AE86: =AVERAGE(K86:Z86) -> 456.625 | AF86: =AVERAGE(L86:AA86) -> 470.04167 | AG86: =AVERAGE(M86:AB86) -> 468.96667 | ... AR86: =AVERAGE(X86:AM86) -> 464.14398
E87: Long Term Liabilities | F87: 2411 | K87: 4532 | P87: 4744 | U87: 5043 | Z87: 5202.423 | AE87: 5800.62 | AJ87: 6243.983 | AO87: 6851.27 | AP87: 6974 | AQ87: 7102 | AR87: 7200
E88: Total Liabilities | F88: =SUM(F85:F87) -> 4043 | G88: =SUM(G85:G87) -> 0 | H88: =SUM(H85:H87) -> 0 | I88: =SUM(I85:I87) -> 0 | J88: =SUM(J85:J87) -> 0 | K88: =SUM(K85:K87) -> 6522 | L88: =SUM(L85:L87) -> 0 | M88: =SUM(M85:M87) -> 0 | ... AQ88: =SUM(AQ85:AQ87) -> 9595.7316 | AR88: 9768
E89: Total Equity | F89: 7101 | G89: =SUM(#REF!) -> #REF! | H89: =SUM(#REF!) -> #REF! | I89: =SUM(#REF!) -> #REF! | J89: =SUM(#REF!) -> #REF! | K89: 6920 | L89: =SUM(#REF!) -> #REF! | M89: =SUM(#REF!) -> #REF! | N89: =SUM(#REF!) -> #REF! | O89: =SUM(#REF!) -> #REF! | P89: 6544 | Q89: =SUM(#REF!) -> #REF! | R89: =SUM(#REF!) -> #REF! | S89: =SUM(#REF!) -> #REF! | T89: =SUM(#REF!) -> #REF! | U89: 6519 | V89: =SUM(#REF!) -> #REF! | W89: =SUM(#REF!) -> #REF! | X89: =SUM(#REF!) -> #REF! | Y89: =SUM(#REF!) -> #REF! | Z89: =U89 -> 6519 | AA89: =V89 -> #REF! | AB89: =W89 -> #REF! | AC89: =X89 -> #REF! | AD89: =Y89 -> #REF! | AE89: =Z89 -> 6519 | AF89: =AA89 -> #REF! | AG89: =AB89 -> #REF! | ... AO89: =AJ89 -> 6519 | AP89: =AO89 -> 6519 | AQ89: =AP89 -> 6519 | AR89: =AQ89 -> 6519
E90: Balance Check | F90: =F81-F88-F89 -> 0 | G90: =G81-G88-G89 -> #REF! | H90: =H81-H88-H89 -> #REF! | I90: =I81-I88-I89 -> #REF! | J90: =J81-J88-J89 -> #REF! | K90: =K81-K88-K89 -> 0 | L90: =L81-L88-L89 -> #REF! | M90: =M81-M88-M89 -> #REF! | ... AR90: =AR81-AR88-AR89 -> -0.1223256
E91: Valuation
E92: P/E | F92: =F100/F46 -> 7.6102894 | G92: =G100/G46 -> #DIV/0! | H92: =H100/H46 -> #DIV/0! | I92: =I100/I46 -> #DIV/0! | J92: =J100/J46 -> #DIV/0! | K92: =K100/K46 -> 35.606349 | L92: =L100/L46 -> #DIV/0! | M92: =M100/M46 -> #DIV/0! | ... AR92: =AR100/AR46 -> 89.98672
E93: EV/ Adjusted EBITDA | F93: =F103/F30 -> 5.8731441 | G93: =G103/G30 -> #DIV/0! | H93: =H103/H30 -> #DIV/0! | I93: =I103/I30 -> #DIV/0! | J93: =J103/J30 -> #DIV/0! | K93: =K103/K30 -> 11.192646 | L93: =L103/L30 -> #DIV/0! | M93: =M103/M30 -> #DIV/0! | ... AR93: =AR103/AR30 -> 19.333616
E94: FCF Yield % | F94: =F67 -> 0.16824088 | G94: =G67 -> #DIV/0! | H94: =H67 -> #DIV/0! | I94: =I67 -> #DIV/0! | J94: =J67 -> #DIV/0! | K94: =K67 -> 0.046510937 | L94: =L67 -> #DIV/0! | M94: =M67 -> #DIV/0! | ... AR94: =AR67 -> 0.061553978
E95: Net Debt/EBITDA | F95: =F102/F30 -> 1.5195861 | G95: =G102/G30 -> #DIV/0! | H95: =H102/H30 -> #DIV/0! | I95: =I102/I30 -> #DIV/0! | J95: =J102/J30 -> #DIV/0! | K95: =K102/K30 -> 4.3186925 | L95: =L102/L30 -> #DIV/0! | M95: =M102/M30 -> #DIV/0! | ... AR95: =AR102/AR30 -> 9.1281081
E96: EV/Revenue | F96: =F103/F13 -> 2.1089076 | G96: =G103/G13 -> #DIV/0! | H96: =H103/H13 -> #DIV/0! | I96: =I103/I13 -> #DIV/0! | J96: =J103/J13 -> #DIV/0! | K96: =K103/K13 -> 2.6429329 | L96: =L103/L13 -> #DIV/0! | M96: =M103/M13 -> #DIV/0! | ... AR96: =AR103/AR13 -> 1.6563339
E97: ROIC | F97: =F107/F109 -> 0.0088585719 | G97: =G107/G109 -> #DIV/0! | H97: =H107/H109 -> #DIV/0! | I97: =I107/I109 -> #DIV/0! | J97: =J107/J109 -> #DIV/0! | K97: =K107/K109 -> -0.0044475422 | L97: =L107/L109 -> #DIV/0! | M97: =M107/M109 -> #DIV/0! | ... AR97: =AR107/AR109 -> 0.026916128
E98: ROE | F98: =F42/F89 -> 0.10899873 | G98: =G42/G89 -> #REF! | H98: =H42/H89 -> #REF! | I98: =I42/I89 -> #REF! | J98: =J42/J89 -> #REF! | K98: =K42/K89 -> 0.027312139 | L98: =L42/L89 -> #REF! | M98: =M42/M89 -> #REF! | ... AR98: =AR42/AR89 -> 0.010252915
E99: ROA | F99: =F42/F81 -> 0.069454415 | G99: =G42/G81 -> 0 | H99: =H42/H81 -> 0 | I99: =I42/I81 -> 0 | J99: =J42/J81 -> 0 | K99: =K42/K81 -> 0.014060408 | L99: =L42/L81 -> 0 | M99: =M42/M81 -> 0 | ... AR99: =AR42/AR81 -> 0.0041038407
E100: Closing Price | F100: =Data!F2 -> 16.82 | K100: =Data!F14 -> 19.2 | P100: =Data!F38 -> 12.8 | U100: =Data!F49 -> 16.82 | Z100: =Data!A3 -> 16.691875 | AA100: 16.8 | AB100: 16.8 | AC100: 16.8 | AD100: 16.8 | AE100: =Z100 -> 16.691875 | AF100: 16.8 | AG100: 16.8 | AH100: 16.8 | AI100: 16.8 | AJ100: =Z100 -> 16.691875 | AK100: 16.8 | AL100: 16.8 | AM100: 16.8 | AN100: 16.8 | AO100: =Z100 -> 16.691875 | AP100: =17 -> 17 | AQ100: =AP100 -> 17 | AR100: =AQ100 -> 17
E101: Market Cap | F101: =F100*F44 -> 5890.364 | G101: =G100*G44 -> 0 | H101: =H100*H44 -> 0 | I101: =I100*I44 -> 0 | J101: =J100*J44 -> 0 | K101: =K100*K44 -> 6729.6 | L101: =L100*L44 -> 0 | M101: =M100*M44 -> 0 | ... AR101: =AR100*AR44 -> 6014.6
E102: Net Debt | F102: =F87+F84-F70-F71 -> 2056 | G102: =G87+G84-G70-G71 -> 0 | H102: =H87+H84-H70-H71 -> 0 | I102: =I87+I84-I70-I71 -> 0 | J102: =J87+J84-J70-J71 -> 0 | K102: =K87+K84-K70-K71 -> 4228 | L102: =L87+L84-L70-L71 -> 0 | M102: =M87+M84-M70-M71 -> 0 | ... AR102: =AR87+AR84-AR70-AR71 -> 5379.6363
E103: Enterprise Value | F103: =F101+F102 -> 7946.364 | G103: =G101+G102 -> 0 | H103: =H101+H102 -> 0 | I103: =I101+I102 -> 0 | J103: =J101+J102 -> 0 | K103: =K101+K102 -> 10957.6 | L103: =L101+L102 -> 0 | M103: =M101+M102 -> 0 | ... AR103: =AR101+AR102 -> 11394.236
E106: Supplementals
E107: NOPAT | F107: =F33*(1-F41) -> 59.538462 | G107: =G33*(1-G41) -> #DIV/0! | H107: =H33*(1-H41) -> #DIV/0! | I107: =I33*(1-I41) -> #DIV/0! | J107: =J33*(1-J41) -> #DIV/0! | K107: =K33*(1-K41) -> -29.291513 | L107: =L33*(1-L41) -> #DIV/0! | M107: =M33*(1-M41) -> #DIV/0! | ... AR107: =AR33*(1-AR41) -> 126.83875
...

Sheet Segment
B2: Scenario | E2: Revenue & Operations
B3: 1 | E3: Bausch + Lomb (BCLO) | F3: 44979 | G3: =EOMONTH(F3,3) -> 45077 | H3: =EOMONTH(G3,3) -> 45169 | I3: =EOMONTH(H3,3) -> 45260 | J3: =EOMONTH(I3,3) -> 45351 | K3: =J3 -> 45351 | L3: =EOMONTH(K3,3) -> 45443 | M3: =EOMONTH(L3,3) -> 45535 | N3: =EOMONTH(M3,3) -> 45626 | O3: =EOMONTH(N3,3) -> 45716 | P3: =O3 -> 45716 | Q3: =EOMONTH(P3,3) -> 45808 | R3: =EOMONTH(Q3,3) -> 45900 | S3: =EOMONTH(R3,3) -> 45991 | T3: =EOMONTH(S3,3) -> 46081 | U3: =T3 -> 46081 | V3: =EOMONTH(U3,3) -> 46173 | W3: =EOMONTH(V3,3) -> 46265 | X3: =EOMONTH(W3,3) -> 46356 | Y3: =EOMONTH(X3,3) -> 46446 | Z3: =Y3 -> 46446 | AA3: =EOMONTH(Z3,3) -> 46538 | AB3: =EOMONTH(AA3,3) -> 46630 | AC3: =EOMONTH(AB3,3) -> 46721 | AD3: =EOMONTH(AC3,3) -> 46812 | AE3: =AD3 -> 46812 | AF3: =EOMONTH(AE3,3) -> 46904 | AG3: =EOMONTH(AF3,3) -> 46996 | AH3: =EOMONTH(AG3,3) -> 47087 | AI3: =EOMONTH(AH3,3) -> 47177 | AJ3: =AI3 -> 47177 | AK3: =EOMONTH(AJ3,3) -> 47269 | AL3: =EOMONTH(AK3,3) -> 47361 | AM3: =EOMONTH(AL3,3) -> 47452 | AN3: =EOMONTH(AM3,3) -> 47542 | AO3: =AN3 -> 47542 | AP3: 47999 | AQ3: 48335 | AR3: 48335
E4: $millions | F4: =YEAR(F3)-1&"A" -> 2022A | G4: ="Q1 "& YEAR(G3) -> Q1 2023 | H4: ="Q2 "& YEAR(H3) -> Q2 2023 | I4: ="Q3 "& YEAR(I3) -> Q3 2023 | J4: ="Q4 "& YEAR(J3)-1 -> Q4 2023 | K4: =YEAR(K3)-1&"A" -> 2023A | L4: ="Q1 "& YEAR(L3) -> Q1 2024 | M4: ="Q2 "& YEAR(M3) -> Q2 2024 | N4: ="Q3 "& YEAR(N3) -> Q3 2024 | O4: ="Q4 "& YEAR(O3)-1 -> Q4 2024 | P4: =YEAR(P3)-1&"A" -> 2024A | Q4: ="Q1 "& YEAR(Q3) -> Q1 2025 | R4: ="Q2 "& YEAR(R3) -> Q2 2025 | S4: ="Q3 "& YEAR(S3) -> Q3 2025 | T4: ="Q4 "& YEAR(T3)-1 -> Q4 2025 | U4: =YEAR(U3)-1&"A" -> 2025A | V4: ="Q1 "& YEAR(V3) -> Q1 2026 | W4: ="Q2 "& YEAR(W3) -> Q2 2026 | X4: ="Q3 "& YEAR(X3) -> Q3 2026 | Y4: ="Q4 "& YEAR(Y3)-1 -> Q4 2026 | Z4: =YEAR(Z3)-1&"A" -> 2026A | AA4: ="Q1 "& YEAR(AA3) -> Q1 2027 | AB4: ="Q2 "& YEAR(AB3) -> Q2 2027 | AC4: ="Q3 "& YEAR(AC3) -> Q3 2027 | AD4: ="Q4 "& YEAR(AD3)-1 -> Q4 2027 | AE4: =YEAR(AE3)-1&"A" -> 2027A | AF4: ="Q1 "& YEAR(AF3) -> Q1 2028 | AG4: ="Q2 "& YEAR(AG3) -> Q2 2028 | AH4: ="Q3 "& YEAR(AH3) -> Q3 2028 | AI4: ="Q4 "& YEAR(AI3)-1 -> Q4 2028 | AJ4: =YEAR(AJ3)-1&"E" -> 2028E | AK4: ="Q1 "& YEAR(AK3) -> Q1 2029 | AL4: ="Q2 "& YEAR(AL3) -> Q2 2029 | AM4: ="Q3 "& YEAR(AM3) -> Q3 2029 | AN4: ="Q4 "& YEAR(AN3)-1 -> Q4 2029 | AO4: =YEAR(AO3)-1&"E" -> 2029E | AP4: =YEAR(AP3)-1&"E" -> 2030E | AQ4: =YEAR(AQ3)-1&"E" -> 2031E | AR4: =YEAR(AR3)-1&"E" -> 2031E
E5: Revenue Build
B6: 1 = Base | E6: Total Revenues | F6: =SUM(F8,F13,F18) -> 3768 | G6: =SUM(G8,G13,G18) -> 0 | H6: =SUM(H8,H13,H18) -> 0 | I6: =SUM(I8,I13,I18) -> 0 | J6: =SUM(J8,J13,J18) -> 0 | K6: =SUM(K8,K13,K18) -> 4146 | L6: =SUM(L8,L13,L18) -> 0 | M6: =SUM(M8,M13,M18) -> 0 | ... AR6: =SUM(AR8,AR13,AR18) -> 6879.1902
B7: 2 = Bear | E7: Total Comp YoY | F7: - | K7: =K6/F6-1 -> 0.10031847 | L7: =L6/G6-1 -> #DIV/0! | M7: =M6/H6-1 -> #DIV/0! | N7: =N6/I6-1 -> #DIV/0! | O7: =O6/J6-1 -> #DIV/0! | P7: =P6/K6-1 -> 0.15557164 | Q7: =Q6/L6-1 -> #DIV/0! | R7: =R6/M6-1 -> #DIV/0! | ... AO7: =AO6/AJ6-1 -> 0.049348819 | AP7: =AP6/AO6-1 -> 0.029388899 | AQ7: =AQ6/AP6-1 -> 0.02942977 | AR7: =AR6/AQ6-1 -> 0.029470654
B8: 3 = Bull | E8: Vision Care Revenue | F8: 2369 | K8: 2543 | P8: 2739 | U8: 2923 | Z8: =U8*(1+Z9) -> 3135.1132 | AA8: =V8*(1+AA9) -> 0 | AB8: =W8*(1+AB9) -> 0 | AC8: =X8*(1+AC9) -> 0 | AD8: =Y8*(1+AD9) -> 0 | AE8: =Z8*(1+AE9) -> 3291.8688 | AF8: =AA8*(1+AF9) -> 0 | AG8: =AB8*(1+AG9) -> 0 | ... AO8: =AJ8*(1+AO9) -> 3629.2854 | AP8: =AO8*(1+AP9) -> 3738.164 | AQ8: =AP8*(1+AQ9) -> 3850.3089 | AR8: =AQ8*(1+AR9) -> 3965.8181
E9: Comp YoY | F9: - | K9: =K8/F8-1 -> 0.073448713 | L9: =L8/G8-1 -> #DIV/0! | M9: =M8/H8-1 -> #DIV/0! | N9: =N8/I8-1 -> #DIV/0! | O9: =O8/J8-1 -> #DIV/0! | P9: =P8/K8-1 -> 0.077074322 | Q9: =Q8/L8-1 -> #DIV/0! | R9: =R8/M8-1 -> #DIV/0! | ... Y9: =Y8/T8-1 -> #DIV/0! | Z9: =CHOOSE(Scenario,Z10,Z11,Z12) -> 0.072566945 | AA9: =CHOOSE(Scenario,AA10,AA11,AA12) -> 0 | AB9: =CHOOSE(Scenario,AB10,AB11,AB12) -> 0 | AC9: =CHOOSE(Scenario,AC10,AC11,AC12) -> 0 | AD9: =CHOOSE(Scenario,AD10,AD11,AD12) -> 0 | AE9: =CHOOSE(Scenario,AE10,AE11,AE12) -> 0.05 | AF9: =CHOOSE(Scenario,AF10,AF11,AF12) -> 0 | AG9: =CHOOSE(Scenario,AG10,AG11,AG12) -> 0 | ... AR9: =CHOOSE(Scenario,AR10,AR11,AR12) -> 0.03
E10: Base Case | Z10: =AVERAGE(K9,P9,U9) -> 0.072566945 | AE10: 0.05 | AJ10: 0.05 | AO10: 0.05 | AP10: 0.03 | AQ10: 0.03 | AR10: 0.03
E11: Bear Case | Z11: -0.035 | AE11: -0.025 | AF11: -0.025 | AG11: -0.025 | AH11: -0.025 | AI11: -0.025 | AJ11: -0.025 | AK11: -0.025 | AL11: -0.025 | AM11: -0.025 | AN11: -0.025 | AO11: -0.025 | AP11: -0.015 | AQ11: -0.015 | AR11: -0.015
E12: Bull Case | Z12: 0.09 | AE12: 0.07 | AF12: 0.07 | AG12: 0.07 | AH12: 0.07 | AI12: 0.07 | AJ12: 0.07 | AK12: 0.07 | AL12: 0.07 | AM12: 0.07 | AN12: 0.07 | AO12: 0.07 | AP12: 0.04 | AQ12: 0.04 | AR12: 0.04
E13: Pharmaceutial Revenue | F13: 681 | K13: 836 | P13: 1209 | U13: 1284 | Z13: =U13*(1+Z14) -> 1361.04 | AA13: =V13*(1+AA14) -> 0 | AB13: =W13*(1+AB14) -> 0 | AC13: =X13*(1+AC14) -> 0 | AD13: =Y13*(1+AD14) -> 0 | AE13: =Z13*(1+AE14) -> 1415.4816 | AF13: =AA13*(1+AF14) -> 0 | AG13: =AB13*(1+AG14) -> 0 | ... AO13: =AJ13*(1+AO14) -> 1530.9849 | AP13: =AO13*(1+AP14) -> 1561.6046 | AQ13: =AP13*(1+AQ14) -> 1592.8367 | AR13: =AQ13*(1+AR14) -> 1624.6934
E14: Comp YoY | F14: - | K14: =K13/F13-1 -> 0.22760646 | L14: =L13/G13-1 -> #DIV/0! | M14: =M13/H13-1 -> #DIV/0! | N14: =N13/I13-1 -> #DIV/0! | O14: =O13/J13-1 -> #DIV/0! | P14: =P13/K13-1 -> 0.44617225 | Q14: =Q13/L13-1 -> #DIV/0! | R14: =R13/M13-1 -> #DIV/0! | ... Y14: =Y13/T13-1 -> #DIV/0! | Z14: =CHOOSE(Scenario,Z15,Z16,Z17) -> 0.06 | AA14: =CHOOSE(Scenario,AA15,AA16,AA17) -> 0 | AB14: =CHOOSE(Scenario,AB15,AB16,AB17) -> 0 | AC14: =CHOOSE(Scenario,AC15,AC16,AC17) -> 0 | AD14: =CHOOSE(Scenario,AD15,AD16,AD17) -> 0 | AE14: =CHOOSE(Scenario,AE15,AE16,AE17) -> 0.04 | AF14: =CHOOSE(Scenario,AF15,AF16,AF17) -> 0.04 | AG14: =CHOOSE(Scenario,AG15,AG16,AG17) -> 0.04 | ... AR14: =CHOOSE(Scenario,AR15,AR16,AR17) -> 0.02
E15: Base Case | Z15: 0.06 | AE15: 0.04 | AF15: 0.04 | AG15: 0.04 | AH15: 0.04 | AI15: 0.04 | AJ15: 0.04 | AK15: 0.04 | AL15: 0.04 | AM15: 0.04 | AN15: 0.04 | AO15: 0.04 | AP15: 0.02 | AQ15: 0.02 | AR15: 0.02
E16: Bear Case | Z16: -0.03 | AE16: -0.02 | AF16: -0.02 | AG16: -0.02 | AH16: -0.02 | AI16: -0.02 | AJ16: -0.02 | AK16: -0.02 | AL16: -0.02 | AM16: -0.02 | AN16: -0.02 | AO16: -0.02 | AP16: -0.01 | AQ16: -0.01 | AR16: -0.01
E17: Bull Case | Z17: 0.08 | AE17: 0.06 | AF17: 0.06 | AG17: 0.06 | AH17: 0.06 | AI17: 0.06 | AJ17: 0.06 | AK17: 0.06 | AL17: 0.06 | AM17: 0.06 | AN17: 0.06 | AO17: 0.06 | AP17: 0.04 | AQ17: 0.04 | AR17: 0.04
E18: Surgical Revenue | F18: 718 | K18: 767 | P18: 843 | U18: 894 | Z18: =U18*(1+Z19) -> 961.89355 | AA18: =V18*(1+AA19) -> 0 | AB18: =W18*(1+AB19) -> 0 | AC18: =X18*(1+AC19) -> 0 | AD18: =Y18*(1+AD19) -> 0 | AE18: =Z18*(1+AE19) -> 1019.6072 | AF18: =AA18*(1+AF19) -> 0 | AG18: =AB18*(1+AG19) -> 0 | ... AO18: =AJ18*(1+AO19) -> 1145.6306 | AP18: =AO18*(1+AP19) -> 1191.4558 | AQ18: =AP18*(1+AQ19) -> 1239.1141 | AR18: =AQ18*(1+AR19) -> 1288.6786
E19: Comp YoY | F19: - | K19: =K18/F18-1 -> 0.068245125 | L19: =L18/G18-1 -> #DIV/0! | M19: =M18/H18-1 -> #DIV/0! | N19: =N18/I18-1 -> #DIV/0! | O19: =O18/J18-1 -> #DIV/0! | P19: =P18/K18-1 -> 0.099087353 | Q19: =Q18/L18-1 -> #DIV/0! | R19: =R18/M18-1 -> #DIV/0! | ... Y19: =Y18/T18-1 -> #DIV/0! | Z19: =CHOOSE(Scenario,Z20,Z21,Z22) -> 0.075943566 | AA19: =CHOOSE(Scenario,AA20,AA21,AA22) -> 0 | AB19: =CHOOSE(Scenario,AB20,AB21,AB22) -> 0 | AC19: =CHOOSE(Scenario,AC20,AC21,AC22) -> 0 | AD19: =CHOOSE(Scenario,AD20,AD21,AD22) -> 0 | AE19: =CHOOSE(Scenario,AE20,AE21,AE22) -> 0.06 | AF19: =CHOOSE(Scenario,AF20,AF21,AF22) -> 0.06 | AG19: =CHOOSE(Scenario,AG20,AG21,AG22) -> 0.06 | ... AR19: =CHOOSE(Scenario,AR20,AR21,AR22) -> 0.04
E20: Base Case | Z20: =AVERAGE(K19,P19,U19) -> 0.075943566 | AE20: 0.06 | AF20: 0.06 | AG20: 0.06 | AH20: 0.06 | AI20: 0.06 | AJ20: 0.06 | AK20: 0.06 | AL20: 0.06 | AM20: 0.06 | AN20: 0.06 | AO20: 0.06 | AP20: 0.04 | AQ20: 0.04 | AR20: 0.04
E21: Bear Case | Z21: -0.04 | AE21: -0.03 | AF21: -0.03 | AG21: -0.03 | AH21: -0.03 | AI21: -0.03 | AJ21: -0.03 | AK21: -0.03 | AL21: -0.03 | AM21: -0.03 | AN21: -0.03 | AO21: -0.03 | AP21: -0.03 | AQ21: -0.03 | AR21: -0.03
E22: Bull Case | Z22: 0.1 | AE22: 0.08 | AF22: 0.08 | AG22: 0.08 | AH22: 0.08 | AI22: 0.08 | AJ22: 0.08 | AK22: 0.08 | AL22: 0.08 | AM22: 0.08 | AN22: 0.08 | AO22: 0.08 | AP22: 0.08 | AQ22: 0.08 | AR22: 0.08
E24: COGS Build
E25: Total Cost of Goods Sold | F25: =F26 -> 1511 | G25: =G26 -> 0 | H25: =H26 -> 0 | I25: =I26 -> 0 | J25: =J26 -> 0 | K25: =K26 -> 1640 | L25: =L26 -> 0 | M25: =M26 -> 0 | ... AR25: =AR26 -> 2751.6761
E26: Cost of Good Sold (Operating Cost) | F26: 1511 | K26: 1640 | P26: 1868 | U26: 2045 | Z26: =Z27*Z6 -> 2183.2187 | AA26: =AA27*AA6 -> 0 | AB26: =AB27*AB6 -> 0 | AC26: =AC27*AC6 -> 0 | AD26: =AD27*AD6 -> 0 | AE26: =AE27*AE6 -> 2290.783 | AF26: =AF27*AF6 -> 0 | AG26: =AG27*AG6 -> 0 | ... AR26: =AR27*AR6 -> 2751.6761
E27: Gross Margin % | F27: =F26/F6 -> 0.40100849 | G27: =G26/G6 -> #DIV/0! | H27: =H26/H6 -> #DIV/0! | I27: =I26/I6 -> #DIV/0! | J27: =J26/J6 -> #DIV/0! | K27: =K26/K6 -> 0.39556199 | L27: =L26/L6 -> #DIV/0! | M27: =M26/M6 -> #DIV/0! | ... U27: =U26/U6 -> 0.40090178 | Z27: =CHOOSE(Scenario,Z28,Z29,Z30) -> 0.4 | AA27: =CHOOSE(Scenario,AA28,AA29,AA30) -> 0.4 | AB27: =CHOOSE(Scenario,AB28,AB29,AB30) -> 0.4 | AC27: =CHOOSE(Scenario,AC28,AC29,AC30) -> 0.4 | AD27: =CHOOSE(Scenario,AD28,AD29,AD30) -> 0.4 | AE27: =CHOOSE(Scenario,AE28,AE29,AE30) -> 0.4 | AF27: =CHOOSE(Scenario,AF28,AF29,AF30) -> 0.4 | AG27: =CHOOSE(Scenario,AG28,AG29,AG30) -> 0.4 | ... AR27: =CHOOSE(Scenario,AR28,AR29,AR30) -> 0.4
E28: Base Case | Z28: 0.4 | AA28: 0.4 | AB28: 0.4 | AC28: 0.4 | AD28: 0.4 | AE28: 0.4 | AF28: 0.4 | AG28: 0.4 | AH28: 0.4 | AI28: 0.4 | AJ28: 0.4 | AK28: 0.4 | AL28: 0.4 | AM28: 0.4 | AN28: 0.4 | AO28: 0.4 | AP28: 0.4 | AQ28: 0.4 | AR28: 0.4
E29: Bear Case | Z29: 0.37 | AA29: 0.37 | AB29: 0.37 | AC29: 0.37 | AD29: 0.37 | AE29: 0.37 | AF29: 0.37 | AG29: 0.37 | AH29: 0.37 | AI29: 0.37 | AJ29: 0.37 | AK29: 0.37 | AL29: 0.37 | AM29: 0.37 | AN29: 0.37 | AO29: 0.37 | AP29: 0.37 | AQ29: 0.37 | AR29: 0.37
E30: Bull Case | Z30: 0.42 | AA30: 0.42 | AB30: 0.42 | AC30: 0.42 | AD30: 0.42 | AE30: 0.42 | AF30: 0.42 | AG30: 0.42 | AH30: 0.42 | AI30: 0.42 | AJ30: 0.42 | AK30: 0.42 | AL30: 0.42 | AM30: 0.42 | AN30: 0.42 | AO30: 0.42 | AP30: 0.42 | AQ30: 0.42 | AR30: 0.42

Sheet Industry & Scenario
B2: Industry Comparables
B3: Company Info | G3: Stock Returns | J3: NTM Valuation | L3: Profitability
B4: Name | C4: Ticker | D4: Price | E4: Mcap ($m) | F4: EV ($m) | G4: 6-Month | H4: 1-Year | I4: YTD | J4: EV/EBITDA | K4: P/E | L4: EBITDA Margin | M4: ROIC
B5: Bausch + Lomb | C5: BCLO | D5: =Data!F49 -> 16.82 | E5: =BCLO!Z101 -> 5905.5854 | F5: =BCLO!U103 -> 10635.916 | G5: 0.0086 | H5: 0.0026 | I5: 0.0046 | J5: =BCLO!Z93 -> 21.065415 | K5: =BCLO!Z92 -> -26.645299 | L5: =BCLO!Z31 -> 0.09370636 | M5: =BCLO!Z97 -> 0.011450296
B6: Alcon | C6: ALC | D6: 75 | E6: 37850 | F6: 45000 | G6: 0.0049 | H6: -0.2004 | I6: -0.0244 | J6: 30 | K6: 38 | L6: 0.26 | M6: 0.27
B7: The Cooper Companies | C7: COO | D7: 70 | E7: 14400 | F7: 19000 | G7: -0.1296 | H7: -0.2252 | I7: -0.2252 | J7: 15 | K7: 15 | L7: 0.27 | M7: 0.03
B8: Staar Surgical | C8: STAA | D8: 18 | E8: 900 | F8: 700 | G8: -0.035 | H8: 0.0742 | I8: 0.4178 | J8: -29 | K8: -15 | L8: =-34% -> -0.34 | M8: =-16% -> -0.16
B9: Median | G9: =MEDIAN(G5:G8) -> -0.01505 | H9: =MEDIAN(H5:H8) -> -0.0989 | I9: =MEDIAN(I5:I8) -> -0.0099 | J9: =MEDIAN(J5:J8) -> 18.032708 | K9: =MEDIAN(K5:K8) -> 0 | L9: =MEDIAN(L5:L8) -> 0.17685318 | M9: =MEDIAN(M5:M8) -> 0.020725148
B10: Average | G10: =AVERAGE(G5:G8) -> -0.037775 | H10: =AVERAGE(H5:H8) -> -0.0872 | I10: =AVERAGE(I5:I8) -> 0.0432 | J10: =AVERAGE(J5:J8) -> 9.2663539 | K10: =AVERAGE(K5:K8) -> 2.8386753 | L10: =AVERAGE(L5:L8) -> 0.07092659 | M10: =AVERAGE(M5:M8) -> 0.037862574

Sheet Data
A1: BLCO | B1: Date | C1: Open | D1: High | E1: Low | F1: Close | G1: Volume
A2: Average | B2: 44682 | C2: 18 | D2: 20.4 | E2: 15.9 | F2: 16.82 | G2: 28540000
A3: =AVERAGE(F2:F49) -> 16.691875 | B3: 44713 | C3: 16.7 | D3: 17.1 | E3: 13.5 | F3: 14.21 | G3: 19820000
A4: Median | B4: 44743 | C4: 14.3 | D4: 16.85 | E4: 13.8 | F4: 16.35 | G4: 16450000
A5: =MEDIAN(F2:F49) -> 16.82 | B5: 44774 | C5: 16.5 | D5: 18.1 | E5: 15.6 | F5: 16.9 | G5: 14230000
B6: 44805 | C6: 16.8 | D6: 17.2 | E6: 13.9 | F6: 14.1 | G6: 15670000
B7: 44835 | C7: 14.2 | D7: 16.8 | E7: 13.85 | F7: 16.45 | G7: 13980000
B8: 44866 | C8: 16.5 | D8: 18.2 | E8: 15.9 | F8: 17.85 | G8: 12760000
B9: 44896 | C9: 17.7 | D9: 18.5 | E9: 15.5 | F9: 15.96 | G9: 11340000
B10: 44927 | C10: 16.1 | D10: 18.6 | E10: 15.8 | F10: 18.2 | G10: 14120000
B11: 44958 | C11: 18.1 | D11: 19.4 | E11: 17.2 | F11: 18.65 | G11: 11890000
B12: 44986 | C12: 18.7 | D12: 20.1 | E12: 17.9 | F12: 19.5 | G12: 13450000
B13: 45017 | C13: 19.6 | D13: 20.5 | E13: 18.4 | F13: 19.8 | G13: 10230000
B14: 45047 | C14: 19.9 | D14: 20.8 | E14: 18.2 | F14: 19.2 | G14: 12340000
B15: 45078 | C15: 19.3 | D15: 20.4 | E15: 18.1 | F15: 19.85 | G15: 11780000
B16: 45108 | C16: 19.9 | D16: 21 | E16: 18.5 | F16: 18.9 | G16: 13560000
B17: 45139 | C17: 18.8 | D17: 19.5 | E17: 17.2 | F17: 17.45 | G17: 10890000
... B49: 46113 | C49: 16.07 | D49: 17.12 | E49: 15.89 | F49: 16.82 | G49: 3070000
