Workbook

Sheet 0000000

Sheet Base Revenue Driver
A1: Owen Purnomo
A2: MGM Resorts International
A3: NYSE: MGM
A4: Segment Revenue Driver
A5: Figures in USD mm
A6: Segment | B6: Metrics | C6: 2020 | D6: 2021 | E6: 2022 | F6: 2023 | G6: 2024 | H6: 2025 | I6: 2026 | J6: 2027 | K6: 2028 | L6: 2029 | M6: 2030 | N6: 2031
A7: Las Vegas Strip Resorts | B7: Las Vegas Visitor Growth% | C7: - | D7: - | E7: - | F7: - | G7: - | H7: - | I7: 0 | J7: 0.015 | K7: =$J$7 -> 0.015 | L7: =$J$7 -> 0.015 | M7: =$J$7 -> 0.015 | N7: =$J$7 -> 0.015
B8: Spend per Visitor Growth % | C8: - | D8: - | E8: - | F8: - | G8: - | H8: - | I8: 0.005 | J8: 0.02 | K8: =$J$8 -> 0.02 | L8: =$J$8 -> 0.02 | M8: =$J$8 -> 0.02 | N8: =$J$8 -> 0.02
B9: Event Based Growth% | C9: - | D9: - | E9: - | F9: - | G9: - | H9: - | I9: 0 | J9: 0.005 | K9: 0 | L9: 0.0075 | M9: 0 | N9: 0
B10: Total Growth | C10: - | D10: - | E10: - | F10: - | G10: - | H10: - | I10: =SUM(I7:I9) -> 0.005 | J10: =SUM(J7:J9) -> 0.04 | K10: =SUM(K7:K9) -> 0.035 | L10: =SUM(L7:L9) -> 0.0425 | M10: =SUM(M7:M9) -> 0.035 | N10: =SUM(N7:N9) -> 0.035
A12: Casino
A13: Table Games | B13: Table Drop | C13: 2001 | D13: 3587 | E13: 5804 | F13: 6215 | G13: 6028 | H13: 6127 | I13: =H13*(1+I10) -> 6157.635 | J13: =I13*(1+J10) -> 6403.9404 | K13: =J13*(1+K10) -> 6628.0783 | L13: =K13*(1+L10) -> 6909.7716 | M13: =L13*(1+M10) -> 7151.6136 | N13: =M13*(1+N10) -> 7401.9201
B14: Table Drop Growth% | C14: =(C13-3526)/3526 -> -0.43250142 | D14: =(D13-C13)/C13 -> 0.7926037 | E14: =(E13-D13)/D13 -> 0.61806524 | F14: =(F13-E13)/E13 -> 0.070813232 | G14: =(G13-F13)/F13 -> -0.030088496 | H14: =(H13-G13)/G13 -> 0.016423358 | I14: =(I13-H13)/H13 -> 0.005 | J14: =(J13-I13)/I13 -> 0.04 | K14: =(K13-J13)/J13 -> 0.035 | ... N14: =(N13-M13)/M13 -> 0.035
B15: Table Win% | C15: 0.235 | D15: 0.246 | E15: 0.24 | F15: 0.263 | G15: 0.244 | H15: 0.252 | I15: =AVERAGE(C15:H15) -> 0.24666667 | J15: =$I$15 -> 0.24666667 | K15: =$I$15 -> 0.24666667 | L15: =$I$15 -> 0.24666667 | M15: =$I$15 -> 0.24666667 | N15: =$I$15 -> 0.24666667
B16: Table Win | C16: =C13*C15 -> 470.235 | D16: =D13*D15 -> 882.402 | E16: =E13*E15 -> 1392.96 | F16: =F13*F15 -> 1634.545 | G16: =G13*G15 -> 1470.832 | H16: =H13*H15 -> 1544.004 | I16: =I13*I15 -> 1518.8833 | J16: =J13*J15 -> 1579.6386 | ... N16: =N13*N15 -> 1825.807
A18: Slot Games | B18: Slot Handle | C18: 6904 | D18: 15089 | E18: 22812 | F18: 23920 | G18: 23840 | H18: 24565 | I18: =H18*(1+I10) -> 24687.825 | J18: =I18*(1+J10) -> 25675.338 | K18: =J18*(1+K10) -> 26573.975 | L18: =K18*(1+L10) -> 27703.369 | M18: =L18*(1+M10) -> 28672.987 | N18: =M18*(1+N10) -> 29676.541
B19: Slot Handle Growth% | C19: =(C18-12874)/12874 -> -0.46372534 | D19: =(D18-C18)/C18 -> 1.1855446 | E19: =(E18-D18)/D18 -> 0.51182981 | F19: =(F18-E18)/E18 -> 0.048570928 | G19: =(G18-F18)/F18 -> -0.0033444816 | H19: =(H18-G18)/G18 -> 0.030411074 | I19: =(I18-H18)/H18 -> 0.005 | J19: =(J18-I18)/I18 -> 0.04 | K19: =(K18-J18)/J18 -> 0.035 | ... N19: =(N18-M18)/M18 -> 0.035
B20: Slot Win% | C20: 0.094 | D20: 0.094 | E20: 0.093 | F20: 0.093 | G20: 0.094 | H20: 0.094 | I20: =AVERAGE(C20:H20) -> 0.093666667 | J20: =$I$20 -> 0.093666667 | K20: =$I$20 -> 0.093666667 | L20: =$I$20 -> 0.093666667 | M20: =$I$20 -> 0.093666667 | N20: =$I$20 -> 0.093666667
B21: Slot Win | C21: =C18*C20 -> 648.976 | D21: =D18*D20 -> 1418.366 | E21: =E18*E20 -> 2121.516 | F21: =F18*F20 -> 2224.56 | G21: =G18*G20 -> 2240.96 | H21: =H18*H20 -> 2309.11 | I21: =I18*I20 -> 2312.4263 | J21: =J18*J20 -> 2404.9233 | ... N21: =N18*N20 -> 2779.7027
A23: Gaming Summary | B23: Total Handle | C23: =C13+C18 -> 8905 | D23: =D13+D18 -> 18676 | E23: =E13+E18 -> 28616 | F23: =F13+F18 -> 30135 | G23: =G13+G18 -> 29868 | H23: =H13+H18 -> 30692 | I23: =I13+I18 -> 30845.46 | J23: =J13+J18 -> 32079.278 | ... N23: =N13+N18 -> 37078.461
B24: Gross Gaming Win | C24: =C16+C21 -> 1119.211 | D24: =D16+D21 -> 2300.768 | E24: =E16+E21 -> 3514.476 | F24: =F16+F21 -> 3859.105 | G24: =G16+G21 -> 3711.792 | H24: =H16+H21 -> 3853.114 | I24: =I16+I21 -> 3831.3096 | J24: =J16+J21 -> 3984.562 | ... N24: =N16+N21 -> 4605.5097
B25: Gaming Incentives (SSP Allocation) | C25: 422.421 | D25: 752 | E25: 1410 | F25: 1731 | G25: 1752 | H25: 1839 | I25: =H25*(1+I26) -> 1848.195 | J25: =I25*(1+J26) -> 1922.1228 | K25: =J25*(1+K26) -> 1989.3971 | L25: =K25*(1+L26) -> 2073.9465 | M25: =L25*(1+M26) -> 2146.5346 | N25: =M25*(1+N26) -> 2221.6633
B26: Gaming Incentives Growth% | C26: =(C25-751)/751 -> -0.43752197 | D26: =(D25-C25)/C25 -> 0.78021453 | E26: =(E25-D25)/D25 -> 0.875 | F26: =(F25-E25)/E25 -> 0.22765957 | G26: =(G25-F25)/F25 -> 0.012131716 | H26: =(H25-G25)/G25 -> 0.049657534 | I26: =I10 -> 0.005 | J26: =J10 -> 0.04 | K26: =K10 -> 0.035 | L26: =L10 -> 0.0425 | M26: =M10 -> 0.035 | N26: =N10 -> 0.035
B27: Gaming Incentives (% of Gross Gaming Win) | C27: =C25/C24 -> 0.37742749 | D27: =D25/D24 -> 0.32684738 | E27: =E25/E24 -> 0.40119779 | F27: =F25/F24 -> 0.4485496 | G27: =G25/G24 -> 0.47200921 | H27: =H25/H24 -> 0.4772763 | I27: =I25/I24 -> 0.4823925 | J27: =J25/J24 -> 0.4823925 | ... N27: =N25/N24 -> 0.4823925 | P27: Despite stable hold rates and mix, rising promotional reinvestment has structurally diluted revenue conversion, indicating competitive pressure rather than demand weakness
B28: Casino Revenue | C28: =C24+31-C25 -> 727.79 | D28: =D24-D25 -> 1548.768 | E28: =E24-E25 -> 2104.476 | F28: =F24-F25 -> 2128.105 | G28: =G24-G25 -> 1959.792 | H28: =H24-H25 -> 2014.114 | I28: =I24-I25 -> 1983.1146 | J28: =J24-J25 -> 2062.4392 | K28: =K24-K25 -> 2134.6245 | ... N28: =N24-N25 -> 2383.8463
B29: Casino Revenue Growth% | C29: =(C28-1296)/1296 -> -0.43843364 | D29: =(D28-C28)/C28 -> 1.1280424 | E29: =(E28-D28)/D28 -> 0.35880648 | F29: =(F28-E28)/E28 -> 0.011227973 | G29: =(G28-F28)/F28 -> -0.079090552 | H29: =(H28-G28)/G28 -> 0.027718248 | I29: =(I28-H28)/H28 -> -0.015391098 | J29: =(J28-I28)/I28 -> 0.04 | K29: =(K28-J28)/J28 -> 0.035 | ... N29: =(N28-M28)/M28 -> 0.035
A31: Analytics | B31: Total SSP Allocation | C31: =C25 -> 422.421 | D31: =D25 -> 752 | E31: =E25 -> 1410 | F31: =F25 -> 1731 | G31: =G25 -> 1752 | H31: =H25 -> 1839 | I31: =I25 -> 1848.195 | J31: =J25 -> 1922.1228 | ... N31: =N25 -> 2221.6633 | P31: MGM retains only ~50% of gross gaming win as casino revenue, with the remainder reinvested into customer incentives and reallocated across non-gaming segments, materially distorting segment-level profitability.
B32: Rooms% of LVSR | C32: =C54/C67 -> 0.25778233 | D32: =D54/D67 -> 0.27516371 | E32: =E54/E67 -> 0.30261436 | F32: =F54/F67 -> 0.34174595 | G32: =G54/G67 -> 0.35634358 | H32: =H54/H67 -> 0.33850277 | I32: =I54/I67 -> 0.33741517 | J32: =J54/J67 -> 0.33308774 | ... N32: =N54/N67 -> 0.31867493
B33: SSP Allocation to Rooms | C33: =C31*C32 -> 108.89267 | D33: =D31*D32 -> 206.92311 | E33: =E31*E32 -> 426.68625 | F33: =F31*F32 -> 591.56224 | G33: =G31*G32 -> 624.31394 | H33: =H31*H32 -> 622.5066 | I33: =I31*I32 -> 623.60904 | J33: =J31*J32 -> 640.23555 | ... N33: =N31*N32 -> 707.9884
B34: F&B% of LVSR | C34: =C59/C67 -> 0.22100565 | D34: =D59/D67 -> 0.22075009 | E34: =E59/E67 -> 0.26148227 | F34: =F59/F67 -> 0.26108406 | G34: =G59/G67 -> 0.26817159 | H34: =H59/H67 -> 0.26887645 | I34: =I59/I67 -> 0.27131262 | J34: =J59/J67 -> 0.2730846 | ... N34: =N59/N67 -> 0.2789863
B35: SSP Allocation to Food and Beverage | C35: =C31*C34 -> 93.357426 | D35: =D31*D34 -> 166.00407 | E35: =E31*E34 -> 368.69 | F35: =F31*F34 -> 451.93651 | G35: =G31*G34 -> 469.83662 | H35: =H31*H34 -> 494.4638 | I35: =I31*I34 -> 501.43862 | J35: =J31*J34 -> 524.90213 | ... N35: =N31*N34 -> 619.81362
B36: Entertainmen% of LVSR | C36: =C64/C67 -> 0.17971372 | D36: =D64/D67 -> 0.1672481 | E36: =E64/E67 -> 0.17694659 | F36: =F64/F67 -> 0.15443767 | G36: =G64/G67 -> 0.15241161 | H36: =H64/H67 -> 0.15299784 | I36: =I64/I67 -> 0.15438408 | J36: =J64/J67 -> 0.15539238 | ... N36: =N64/N67 -> 0.15875061
B37: SSP Allocation to Entertainment and Other | C37: =C31*C36 -> 75.91485 | D37: =D31*D36 -> 125.77057 | E37: =E31*E36 -> 249.49469 | F37: =F31*F36 -> 267.3316 | G37: =G31*G36 -> 267.02514 | H37: =H31*H36 -> 281.36303 | I37: =I31*I36 -> 285.33189 | J37: =J31*J36 -> 298.68325 | ... N37: =N31*N36 -> 352.69041
B39: Blend Hold% | C39: =C24/C23 -> 0.12568344 | D39: =D24/D23 -> 0.12319383 | E39: =E24/E23 -> 0.12281507 | F39: =F24/F23 -> 0.12806056 | G39: =G24/G23 -> 0.1242732 | H39: =H24/H23 -> 0.12554131 | I39: =I24/I23 -> 0.12420984 | J39: =J24/J23 -> 0.12420984 | ... N39: =N24/N23 -> 0.12420984
B40: Table Mix% | C40: =C16/C24 -> 0.42014866 | D40: =D16/D24 -> 0.38352498 | E40: =E16/E24 -> 0.39634927 | F40: =F16/F24 -> 0.42355546 | G40: =G16/G24 -> 0.39625927 | H40: =H16/H24 -> 0.40071589 | I40: =I16/I24 -> 0.39643972 | J40: =J16/J24 -> 0.39643972 | ... N40: =N16/N24 -> 0.39643972
B41: Slot Mix% | C41: =C21/C24 -> 0.57985134 | D41: =D21/D24 -> 0.61647502 | E41: =E21/E24 -> 0.60365073 | F41: =F21/F24 -> 0.57644454 | G41: =G21/G24 -> 0.60374073 | H41: =H21/H24 -> 0.59928411 | I41: =I21/I24 -> 0.60356028 | J41: =J21/J24 -> 0.60356028 | ... N41: =N21/N24 -> 0.60356028
B42: Net Monetization | C42: =C28/C24 -> 0.65027059 | D42: =D28/D24 -> 0.67315262 | E42: =E28/E24 -> 0.59880221 | F42: =F28/F24 -> 0.5514504 | G42: =G28/G24 -> 0.52799079 | H42: =H28/H24 -> 0.5227237 | I42: =I28/I24 -> 0.5176075 | J42: =J28/J24 -> 0.5176075 | ... N42: =N28/N24 -> 0.5176075
B43: Promo/SSP Rate | C43: =1-C42 -> 0.34972941 | D43: =1-D42 -> 0.32684738 | E43: =1-E42 -> 0.40119779 | F43: =1-F42 -> 0.4485496 | G43: =1-G42 -> 0.47200921 | H43: =1-H42 -> 0.4772763 | I43: =1-I42 -> 0.4823925 | J43: =1-J42 -> 0.4823925 | ... N43: =1-N42 -> 0.4823925
A45: Rooms | B45: Occupancy% | C45: 0.55 | D45: 0.74 | E45: 0.89 | F45: 0.93 | G45: 0.94 | H45: 0.92 | I45: 0.9 | J45: =$I$45 -> 0.9 | K45: =$I$45 -> 0.9 | L45: =$I$45 -> 0.9 | M45: =$I$45 -> 0.9 | N45: =$I$45 -> 0.9
B46: Occupancy Growth% | C46: =(C45-91%)/91% -> -0.3956044 | D46: =(D45-C45)/C45 -> 0.34545455 | E46: =(E45-D45)/D45 -> 0.2027027 | F46: =(F45-E45)/E45 -> 0.04494382 | G46: =(G45-F45)/F45 -> 0.010752688 | H46: =(H45-G45)/G45 -> -0.021276596 | I46: =(I45-H45)/H45 -> -0.02173913 | J46: =(J45-I45)/I45 -> 0 | K46: =(K45-J45)/J45 -> 0 | ... N46: =(N45-M45)/M45 -> 0
B47: # of Rooms and Suites | C47: 31098 | D47: 36595 | E47: 37293 | F47: 37243 | G47: 37243 | H47: 37000 | I47: =AVERAGE(F47:H47) -> 37162 | J47: =$I$47 -> 37162 | K47: =$I$47 -> 37162 | L47: =$I$47 -> 37162 | M47: =$I$47 -> 37162 | N47: =$I$47 -> 37162
B48: ADR (Average Daily Rate) | C48: 161 | D48: 173 | E48: 229 | F48: 256 | G48: 260 | H48: 249 | I48: =H48*(1+I49) -> 249 | J48: =I48*(1+J49) -> 253.98 | K48: =J48*(1+K49) -> 259.0596 | L48: =K48*(1+L49) -> 264.24079 | M48: =L48*(1+M49) -> 269.52561 | N48: =M48*(1+N49) -> 274.91612
B49: ADR Growth% | C49: =(C48-167)/167 -> -0.035928144 | D49: =(D48-C48)/C48 -> 0.074534161 | E49: =(E48-D48)/D48 -> 0.32369942 | F49: =(F48-E48)/E48 -> 0.11790393 | G49: =(G48-F48)/F48 -> 0.015625 | H49: =(H48-G48)/G48 -> -0.042307692 | I49: =0% -> 0 | J49: =2% -> 0.02 | K49: =$J$49 -> 0.02 | L49: =$J$49 -> 0.02 | M49: =$J$49 -> 0.02 | N49: =$J$49 -> 0.02
B50: RevPar | C50: 88 | D50: 128 | E50: 203 | F50: 237 | G50: 245 | H50: 229 | I50: =I48*I51 -> 231.38472 | J50: =J48*J51 -> 236.01241 | K50: =K48*K51 -> 240.73266 | L50: =L48*L51 -> 245.54731 | M50: =M48*M51 -> 250.45826 | N50: =N48*N51 -> 255.46742
B51: Revpar/ADR | C51: =C50/C48 -> 0.54658385 | D51: =D50/D48 -> 0.73988439 | E51: =E50/E48 -> 0.88646288 | F51: =F50/F48 -> 0.92578125 | G51: =G50/G48 -> 0.94230769 | H51: =H50/H48 -> 0.91967871 | I51: =AVERAGE(F51:H51) -> 0.92925589 | J51: =$I$51 -> 0.92925589 | K51: =$I$51 -> 0.92925589 | L51: =$I$51 -> 0.92925589 | M51: =$I$51 -> 0.92925589 | N51: =$I$51 -> 0.92925589
B52: Rooms Promotion | C52: =C33 -> 108.89267 | D52: =D33 -> 206.92311 | E52: =E33 -> 426.68625 | F52: =F33 -> 591.56224 | G52: =G33 -> 624.31394 | H52: =H33 -> 622.5066 | I52: =I33 -> 623.60904 | J52: =J33 -> 640.23555 | ... N52: =N33 -> 707.9884
B53: Rooms Cash Revenue | C53: =C54-C52 -> 440.4846 | D53: =D54-D52 -> 1058.2685 | E53: =E54-E52 -> 2032.5838 | F53: =F54-F52 -> 2404.6241 | G53: =G54-G52 -> 2506.314 | H53: =H54-H52 -> 2222.7268 | I53: =I54-I52 -> 2201.0701 | J53: =J54-J52 -> 2240.9372 | ... N53: =N54-N52 -> 2410.6856
B54: Rooms Total Revenue | C54: =((C50*C47*365)/1000000)*C45 -> 549.37727 | D54: =((D50*D47*365)/1000000)*D45 -> 1265.1916 | E54: =((E50*E47*365)/1000000)*E45 -> 2459.2701 | F54: =((F50*F47*365)/1000000)*F45 -> 2996.1863 | G54: =((G50*G47*365)/1000000)*G45 -> 3130.628 | H54: =((H50*H47*365)/1000000)*H45 -> 2845.2334 | I54: =((I50*I47*365)/1000000)*I45 -> 2824.6791 | J54: =((J50*J47*365)/1000000)*J45 -> 2881.1727 | ... N54: =((N50*N47*365)/1000000)*N45 -> 3118.674
B55: Rooms Total Cash Revenue Growth% | C55: =(C54-1863)/1863 -> -0.7051115 | D55: =(D53-C53)/C53 -> 1.4025097 | E55: =(E53-D53)/D53 -> 0.92066932 | F55: =(F53-E53)/E53 -> 0.18303807 | G55: =(G53-F53)/F53 -> 0.042289331 | H55: =(H53-G53)/G53 -> -0.11314912 | I55: =(I53-H53)/H53 -> -0.0097433085 | J55: =(J53-I53)/I53 -> 0.018112586 | K55: =(K53-J53)/J53 -> 0.018586417 | ... N55: =(N53-M53)/M53 -> 0.018604597
A57: Food and Beverage | B57: Food and Beverage Promotional Revenue | C57: =C35 -> 93.357426 | D57: =D35 -> 166.00407 | E57: =E35 -> 368.69 | F57: =F35 -> 451.93651 | G57: =G35 -> 469.83662 | H57: =H35 -> 494.4638 | I57: =I35 -> 501.43862 | J57: =J35 -> 524.90213 | ... N57: =N35 -> 619.81362
B58: Food and Beverage Cash Revenue | C58: =C59-C57 -> 377.64257 | D58: =D59-D57 -> 848.99593 | E58: =E59-E57 -> 1756.31 | F58: =F59-F57 -> 1837.0635 | G58: =G59-G57 -> 1886.1634 | H58: =H59-H57 -> 1765.5362 | I58: =I59-I57 -> 1769.8614 | J58: =J59-J57 -> 1837.2499 | ... N58: =N59-N57 -> 2110.4523
B59: Food and Beverage Total Revenue | C59: 471 | D59: 1015 | E59: 2125 | F59: 2289 | G59: 2356 | H59: 2260 | I59: =H59*(1+I10) -> 2271.3 | J59: =I59*(1+J10) -> 2362.152 | K59: =J59*(1+K10) -> 2444.8273 | L59: =K59*(1+L10) -> 2548.7325 | M59: =L59*(1+M10) -> 2637.9381 | N59: =M59*(1+N10) -> 2730.266
B60: Food and Beverage Cash Revenue Growth% | C60: =(C59-1517)/1517 -> -0.68951879 | D60: =(D58-C58)/C58 -> 1.2481468 | E60: =(E58-D58)/D58 -> 1.0686907 | F60: =(F58-E58)/E58 -> 0.045979065 | G60: =(G58-F58)/F58 -> 0.026727376 | H60: =(H58-G58)/G58 -> -0.063953728 | I60: =(I58-H58)/H58 -> 0.0024497808 | J60: =(J58-I58)/I58 -> 0.038075578 | K60: =(K58-J58)/J58 -> 0.033565629 | ... N60: =(N58-M58)/M58 -> 0.033584076
A61: Entertainment, retail and other
B62: Entertianment & other Promotional Revenue | C62: =C37 -> 75.91485 | D62: =D37 -> 125.77057 | E62: =E37 -> 249.49469 | F62: =F37 -> 267.3316 | G62: =G37 -> 267.02514 | H62: =H37 -> 281.36303 | I62: =I37 -> 285.33189 | J62: =J37 -> 298.68325 | ... N62: =N37 -> 352.69041
B63: Entertianment & other Cash Revenue | C63: =C64-C62 -> 307.08515 | D63: =D64-D62 -> 643.22943 | E63: =E64-E62 -> 1188.5053 | F63: =F64-F62 -> 1086.6684 | G63: =G64-G62 -> 1071.9749 | H63: =H64-H62 -> 1004.637 | I63: =I64-I62 -> 1007.0981 | J63: =J64-J62 -> 1045.444 | ... N63: =N64-N62 -> 1200.9034
B64: Entertainment, retail and other | C64: 383 | D64: 769 | E64: 1438 | F64: 1354 | G64: 1339 | H64: 1286 | I64: =H64*(1+I10) -> 1292.43 | J64: =I64*(1+J10) -> 1344.1272 | K64: =J64*(1+K10) -> 1391.1717 | L64: =K64*(1+L10) -> 1450.2964 | M64: =L64*(1+M10) -> 1501.0568 | N64: =M64*(1+N10) -> 1553.5938
B65: Entertainment, retail and other Cash Growth% | C65: =(C64-1153)/1153 -> -0.66782307 | D65: =(D63-C63)/C63 -> 1.0946289 | E65: =(E63-D63)/D63 -> 0.847716 | F65: =(F63-E63)/E63 -> -0.085684858 | G65: =(G63-F63)/F63 -> -0.013521643 | H65: =(H63-G63)/G63 -> -0.062816667 | I65: =(I63-H63)/H63 -> 0.0024497808 | J65: =(J63-I63)/I63 -> 0.038075578 | K65: =(K63-J63)/J63 -> 0.033565629 | ... N65: =(N63-M63)/M63 -> 0.033584076
B67: Segment Revenue (USD mm) | C67: =C28+C54+C59+C64 -> 2131.1673 | D67: =D28+D54+D59+D64 -> 4597.9596 | E67: =E28+E54+E59+E64 -> 8126.7461 | F67: =F28+F54+F59+F64 -> 8767.2913 | G67: =G28+G54+G59+G64 -> 8785.42 | H67: =H28+H54+H59+H64 -> 8405.3474 | I67: =I28+I54+I59+I64 -> 8371.5237 | J67: =J28+J54+J59+J64 -> 8649.8911 | ... N67: =N28+N54+N59+N64 -> 9786.3801
B68: Segment of Total Revenue% | C68: =C67/C198 -> 0.44819112 | D68: =D67/D198 -> 0.50448564 | E68: =E67/E198 -> 0.6516385 | F68: =F67/F198 -> 0.54715702 | G68: =G67/G198 -> 0.5143647 | H68: =H67/H198 -> 0.48603766 | I68: =I67/I198 -> 0.48910318 | J68: =J67/J198 -> 0.47790032 | ... N68: =N67/N198 -> 0.46189501
B69: Segment EBIT Margin% | C69: =C70/C67 -> -0.2950938 | D69: =D70/D67 -> 0.46575562 | E69: =E70/E67 -> -0.043020387 | F69: =F70/F67 -> 0.17182715 | G69: =G70/G67 -> 0.17273975 | H69: =H70/H67 -> 0.15056093 | I69: =AVERAGE(F69:H69) -> 0.16504261 | J69: =$I$69 -> 0.16504261 | K69: =$I$69 -> 0.16504261 | L69: =$I$69 -> 0.16504261 | M69: =$I$69 -> 0.16504261 | N69: =$I$69 -> 0.16504261
B70: Segment EBIT (USD mm) | C70: =232.188-(1210.556*C68)-(710.683*C68) -> -628.89426 | D70: =3142.308-(1150.61*D68)-(833.158*D68) -> 2141.5255 | E70: =3190.486-(3482.05*E68)-(1950.566*E68) -> -349.61576 | F70: =3190.486-(814.128*F68)-(2263.649*F68) -> 1506.4587 | G70: =3106.543-(831.097*G68)-(2258.057*G68) -> 1517.5912 | H70: =2857.873-(1017.794*H68)-(2258.405*H68) -> 1265.5169 | I70: =I67*I69 -> 1381.6581 | J70: =J67*J69 -> 1427.6006 | K70: =K67*K69 -> 1470.4339 | L70: =L67*L69 -> 1522.0142 | M70: =M67*M69 -> 1567.8638 | N70: =N67*N69 -> 1615.1697
A72: Regional Operations | B72: Regional Visitor Growth% | C72: - | D72: - | E72: - | F72: - | G72: - | H72: - | I72: 0.01 | J72: 0.015 | K72: =$J$7 -> 0.015 | L72: =$J$7 -> 0.015 | M72: =$J$7 -> 0.015 | N72: =$J$7 -> 0.015
B73: Spend per Visitor Growth % | C73: - | D73: - | E73: - | F73: - | G73: - | H73: - | I73: 0.01 | J73: 0.015 | K73: =$J$73 -> 0.015 | L73: =$J$73 -> 0.015 | M73: =$J$73 -> 0.015 | N73: =$J$73 -> 0.015
B74: Event Based Growth% | C74: - | D74: - | E74: - | F74: - | G74: - | H74: - | I74: 0 | J74: 0 | K74: 0 | L74: 0 | M74: 0 | N74: 0
B75: Total Growth | C75: - | D75: - | E75: - | F75: - | G75: - | H75: - | I75: =SUM(I72:I74) -> 0.02 | J75: =SUM(J72:J74) -> 0.03 | K75: =SUM(K72:K74) -> 0.03 | L75: =SUM(L72:L74) -> 0.03 | M75: =SUM(M72:M74) -> 0.03 | N75: =SUM(N72:N74) -> 0.03
A77: Casino
A78: Table Games | B78: Table Drop | C78: 2422 | D78: 3980 | E78: 4469 | F78: 3886 | G78: 3909 | H78: 4001 | I78: =H78*(1+I75) -> 4081.02 | J78: =I78*(1+J75) -> 4203.4506 | K78: =J78*(1+K75) -> 4329.5541 | L78: =K78*(1+L75) -> 4459.4407 | M78: =L78*(1+M75) -> 4593.224 | N78: =M78*(1+N75) -> 4731.0207
B79: Table Drop Growth% | C79: =(C78-4226)/4226 -> -0.42688121 | D79: =(D78-C78)/C78 -> 0.64327002 | E79: =(E78-D78)/D78 -> 0.12286432 | F79: =(F78-E78)/E78 -> -0.13045424 | G79: =(G78-F78)/F78 -> 0.0059186824 | H79: =(H78-G78)/G78 -> 0.023535431 | I79: =(I78-H78)/H78 -> 0.02 | J79: =(J78-I78)/I78 -> 0.03 | K79: =(K78-J78)/J78 -> 0.03 | ... N79: =(N78-M78)/M78 -> 0.03
B80: Table Win% | C80: 0.201 | D80: 0.198 | E80: 0.209 | F80: 0.21 | G80: 0.206 | H80: 0.204 | I80: =AVERAGE(C80:H80) -> 0.20466667 | J80: =$I$15 -> 0.24666667 | K80: =$I$15 -> 0.24666667 | L80: =$I$15 -> 0.24666667 | M80: =$I$15 -> 0.24666667 | N80: =$I$15 -> 0.24666667
B81: Table Win | C81: =C78*C80 -> 486.822 | D81: =D78*D80 -> 788.04 | E81: =E78*E80-1 -> 933.021 | F81: =F78*F80-2 -> 814.06 | G81: =G78*G80+2 -> 807.254 | H81: =H78*H80+2 -> 818.204 | I81: =I78*I80 -> 835.24876 | J81: =J78*J80 -> 1036.8511 | K81: =K78*K80 -> 1067.9567 | L81: =L78*L80 -> 1099.9954 | M81: =M78*M80 -> 1132.9952 | N81: =N78*N80 -> 1166.9851
A83: Slot Games | B83: Slot Handle | C83: 14527 | D83: 25566 | E83: 26226 | F83: 26850 | G83: 26894 | H83: 27161 | I83: =H83*(1+I75) -> 27704.22 | J83: =I83*(1+J75) -> 28535.347 | K83: =J83*(1+K75) -> 29391.407 | L83: =K83*(1+L75) -> 30273.149 | M83: =L83*(1+M75) -> 31181.344 | N83: =M83*(1+N75) -> 32116.784
B84: Slot Handle Growth% | C84: =(C83-25031)/25031 -> -0.41963965 | D84: =(D83-C83)/C83 -> 0.75989537 | E84: =(E83-D83)/D83 -> 0.025815536 | F84: =(F83-E83)/E83 -> 0.023793182 | G84: =(G83-F83)/F83 -> 0.0016387337 | H84: =(H83-G83)/G83 -> 0.009927865 | I84: =(I83-H83)/H83 -> 0.02 | J84: =(J83-I83)/I83 -> 0.03 | K84: =(K83-J83)/J83 -> 0.03 | ... N84: =(N83-M83)/M83 -> 0.03
B85: Slot Win% | C85: 0.097 | D85: 0.096 | E85: 0.095 | F85: 0.096 | G85: 0.099 | H85: 0.101 | I85: =AVERAGE(C85:H85) -> 0.097333333 | J85: =$I$20 -> 0.093666667 | K85: =$I$20 -> 0.093666667 | L85: =$I$20 -> 0.093666667 | M85: =$I$20 -> 0.093666667 | N85: =$I$20 -> 0.093666667
B86: Slot Win | C86: =C83*C85 -> 1409.119 | D86: =D83*D85 -> 2454.336 | E86: =E83*E85 -> 2491.47 | F86: =F83*F85 -> 2577.6 | G86: =G83*G85 -> 2662.506 | H86: =H83*H85 -> 2743.261 | I86: =I83*I85 -> 2696.5441 | J86: =J83*J85 -> 2672.8108 | ... N86: =N83*N85 -> 3008.2721
A88: Gaming Summary | B88: Total Handle | C88: =C78+C83 -> 16949 | D88: =D78+D83 -> 29546 | E88: =E78+E83 -> 30695 | F88: =F78+F83 -> 30736 | G88: =G78+G83 -> 30803 | H88: =H78+H83 -> 31162 | I88: =I78+I83 -> 31785.24 | J88: =J78+J83 -> 32738.797 | ... N88: =N78+N83 -> 36847.805
B89: Gross Gaming Win | C89: =C81+C86 -> 1895.941 | D89: =D81+D86 -> 3242.376 | E89: =E81+E86 -> 3424.491 | F89: =F81+F86 -> 3391.66 | G89: =G81+G86 -> 3469.76 | H89: =H81+H86 -> 3561.465 | I89: =I81+I86 -> 3531.7928 | J89: =J81+J86 -> 3709.6619 | ... N89: =N81+N86 -> 4175.2572
B90: Gaming Incentives (SSP Allocation) | C90: =C89-C93+173 -> 499.748 | D90: =D89-D93 -> 520.861 | E90: =E89-E93 -> 523.419 | F90: =F89-F93 -> 679.455 | G90: =G89-G93 -> 731.982 | H90: =H89-H93 -> 788.731 | I90: =H90*(1+I91) -> 804.50562 | J90: =I90*(1+J91) -> 828.64079 | K90: =J90*(1+K91) -> 853.50001 | L90: =K90*(1+L91) -> 879.10501 | M90: =L90*(1+M91) -> 905.47816 | N90: =M90*(1+N91) -> 932.64251
B91: Gaming Incentives Growth% | C91: =(C90-751)/751 -> -0.33455659 | D91: =(D90-C90)/C90 -> 0.042247293 | E91: =(E90-D90)/D90 -> 0.0049110991 | F91: =(F90-E90)/E90 -> 0.29810916 | G91: =(G90-F90)/F90 -> 0.077307548 | H91: =(H90-G90)/G90 -> 0.077527863 | I91: =I75 -> 0.02 | J91: =J75 -> 0.03 | K91: =K75 -> 0.03 | L91: =L75 -> 0.03 | M91: =M75 -> 0.03 | N91: =N75 -> 0.03
B92: Gaming Incentives (% of Gross Gaming Win) | C92: =C90/C89 -> 0.26358837 | D92: =D90/D89 -> 0.16064176 | E92: =E90/E89 -> 0.15284578 | F92: =F90/F89 -> 0.20033111 | G92: =G90/G89 -> 0.21096041 | H92: =H90/H89 -> 0.22146252 | I92: =I90/I89 -> 0.22778958 | J92: =J90/J89 -> 0.22337367 | ... N92: =N90/N89 -> 0.22337367
B93: Casino Revenue | C93: 1569.193 | D93: 2721.515 | E93: 2901.072 | F93: 2712.205 | G93: 2737.778 | H93: 2772.734 | I93: =I89-I90 -> 2727.2872 | J93: =J89-J90 -> 2881.0212 | K93: =K89-K90 -> 2967.4518 | L93: =L89-L90 -> 3056.4753 | M93: =M89-M90 -> 3148.1696 | N93: =N89-N90 -> 3242.6147
B94: Casino Revenue Growth% | C94: =(C93-1296)/1296 -> 0.21079707 | D94: =(D93-C93)/C93 -> 0.73434052 | E94: =(E93-D93)/D93 -> 0.065976855 | F94: =(F93-E93)/E93 -> -0.065102486 | G94: =(G93-F93)/F93 -> 0.0094288595 | H94: =(H93-G93)/G93 -> 0.012768018 | I94: =(I93-H93)/H93 -> -0.016390602 | J94: =(J93-I93)/I93 -> 0.056368811 | K94: =(K93-J93)/J93 -> 0.03 | ... N94: =(N93-M93)/M93 -> 0.03
A96: Analytics | B96: Total SSP Allocation | C96: =C90 -> 499.748 | D96: =D90 -> 520.861 | E96: =E90 -> 523.419 | F96: =F90 -> 679.455 | G96: =G90 -> 731.982 | H96: =H90 -> 788.731 | I96: =I90 -> 804.50562 | J96: =J90 -> 828.64079 | ... N96: =N90 -> 932.64251
B97: Rooms% of Regional Operations | C97: =C112/C125 -> 0.066565133 | D97: =D112/D125 -> 0.066805166 | E97: =E112/E125 -> 0.077423037 | F97: =F112/F125 -> 0.080674406 | G97: =G112/G125 -> 0.081799909 | H97: =H112/H125 -> 0.081636218 | I97: =I112/I125 -> 0.083834639 | J97: =J112/J125 -> 0.082301011 | ... N97: =N112/N125 -> 0.082301011
B98: SSP Allocation to Rooms | C98: =C96*C97 -> 33.265792 | D98: =D96*D97 -> 34.796206 | E98: =E96*E97 -> 40.524688 | F98: =F96*F97 -> 54.814629 | G98: =G96*G97 -> 59.876061 | H98: =H96*H97 -> 64.389016 | I98: =I96*I97 -> 67.445438 | J98: =J96*J97 -> 68.197975 | ... N98: =N96*N97 -> 76.757422
B99: F&B% of Regional Operations | C99: =C117/C125 -> 0.093613112 | D99: =D117/D125 -> 0.066807586 | E99: =E117/E125 -> 0.077423037 | F99: =F117/F125 -> 0.11988146 | G99: =G117/G125 -> 0.12260471 | H99: =H117/H125 -> 0.12235108 | I99: =I117/I125 -> 0.12564593 | J99: =J117/J125 -> 0.12334742 | ... N99: =N117/N125 -> 0.12334742
B100: SSP Allocation to Food and Beverage | C100: =C96*C99 -> 46.782966 | D100: =D96*D99 -> 34.797466 | E100: =E96*E99 -> 40.524688 | F100: =F96*F99 -> 81.454057 | G100: =G96*G99 -> 89.744441 | H100: =H96*H99 -> 96.502086 | I100: =I96*I99 -> 101.08285 | J100: =J96*J99 -> 102.21071 | ... N100: =N96*N99 -> 115.03905
B101: Entertainment% of Regional Operations | C101: =C122/C125 -> 0.042131569 | D101: =D122/D125 -> 0.04304126 | E101: =E122/E125 -> 0.054867049 | F101: =F122/F125 -> 0.060485915 | G101: =G122/G125 -> 0.059697252 | H101: =H122/H125 -> 0.06099435 | I101: =I122/I125 -> 0.062636896 | J101: =J122/J125 -> 0.061491049 | ... N101: =N122/N125 -> 0.061491049
B102: SSP Allocation to Entertainment | C102: =C96*C101 -> 21.055167 | D102: =D96*D101 -> 22.418514 | E102: =E96*E101 -> 28.718456 | F102: =F96*F101 -> 41.097458 | G102: =G96*G101 -> 43.697314 | H102: =H96*H101 -> 48.108135 | I102: =I96*I101 -> 50.391735 | J102: =J96*J101 -> 50.953992 | ... N102: =N96*N101 -> 57.349166
B104: Blend Hold% | C104: =C89/C88 -> 0.11186153 | D104: =D89/D88 -> 0.10973993 | E104: =E89/E88 -> 0.11156511 | F104: =F89/F88 -> 0.11034813 | G104: =G89/G88 -> 0.11264357 | H104: =H89/H88 -> 0.11428872 | I104: =I89/I88 -> 0.11111424 | J104: =J89/J88 -> 0.11331088 | ... N104: =N89/N88 -> 0.11331088
B105: Table Mix% | C105: =C81/C89 -> 0.25677065 | D105: =D81/D89 -> 0.24304399 | E105: =E81/E89 -> 0.27245538 | F105: =F81/F89 -> 0.24001816 | G105: =G81/G89 -> 0.23265413 | H105: =H81/H89 -> 0.22973804 | I105: =I81/I89 -> 0.23649427 | J105: =J81/J89 -> 0.27950017 | ... N105: =N81/N89 -> 0.27950017
B106: Slot Mix% | C106: =C86/C89 -> 0.74322935 | D106: =D86/D89 -> 0.75695601 | E106: =E86/E89 -> 0.72754462 | F106: =F86/F89 -> 0.75998184 | G106: =G86/G89 -> 0.76734587 | H106: =H86/H89 -> 0.77026196 | I106: =I86/I89 -> 0.76350573 | J106: =J86/J89 -> 0.72049983 | ... N106: =N86/N89 -> 0.72049983
B107: Net Monetization | C107: =C93/C89 -> 0.82765919 | D107: =D93/D89 -> 0.83935824 | E107: =E93/E89 -> 0.84715422 | F107: =F93/F89 -> 0.79966889 | G107: =G93/G89 -> 0.78903959 | H107: =H93/H89 -> 0.77853748 | I107: =I93/I89 -> 0.77221042 | J107: =J93/J89 -> 0.77662633 | ... N107: =N93/N89 -> 0.77662633
B108: Promo/SSP Rate | C108: =1-C107 -> 0.17234081 | D108: =1-D107 -> 0.16064176 | E108: =1-E107 -> 0.15284578 | F108: =1-F107 -> 0.20033111 | G108: =1-G107 -> 0.21096041 | H108: =1-H107 -> 0.22146252 | I108: =1-I107 -> 0.22778958 | J108: =1-J107 -> 0.22337367 | ... N108: =1-N107 -> 0.22337367
A110: Rooms
B111: Rooms Cash Revenue | C111: =C112-C98 -> 97.679208 | D111: =D112-D98 -> 186.02379 | E111: =E112-E98 -> 243.68831 | F111: =F112-F98 -> 241.28537 | G111: =G112-G98 -> 244.44594 | H111: =H112-H98 -> 243.56998 | I111: =I112-I98 -> 246.67274 | J111: =J112-J98 -> 255.34375 | ... N111: =N112-N98 -> 287.39164
B112: Rooms Total Revenue | C112: 130.945 | D112: 220.82 | E112: 284.213 | F112: 296.1 | G112: 304.322 | H112: 307.959 | I112: =H112*(1+I75) -> 314.11818 | J112: =I112*(1+J75) -> 323.54173 | K112: =J112*(1+K75) -> 333.24798 | L112: =K112*(1+L75) -> 343.24542 | M112: =L112*(1+M75) -> 353.54278 | N112: =M112*(1+N75) -> 364.14906
B113: Rooms Cash Revenue Growth% | C113: =(C112-316.753)/316.753 -> -0.58660218 | D113: =(D111-C111)/C111 -> 0.90443595 | E113: =(E111-D111)/D111 -> 0.30998463 | F113: =(F111-E111)/E111 -> -0.0098607123 | G113: =(G111-F111)/F111 -> 0.01309888 | H113: =(H111-G111)/G111 -> -0.0035834314 | I113: =(I111-H111)/H111 -> 0.012738672 | J113: =(J111-I111)/I111 -> 0.035151871 | K113: =(K111-J111)/J111 -> 0.03 | ... N113: =(N111-M111)/M111 -> 0.03
A115: Food and Beverage
B116: Food and Beverage Cash Revenue | C116: =C117-C100 -> 137.37003 | D116: =D117-D100 -> 186.03053 | E116: =E117-E100 -> 243.68831 | F116: =F117-F100 -> 358.54794 | G116: =G117-G100 -> 366.38456 | H116: =H117-H100 -> 365.04691 | I116: =I117-I100 -> 369.69713 | J116: =J117-J100 -> 382.69267 | ... N116: =N117-N100 -> 430.72397
...

Sheet Base MGM IS
A1: Owen Purnomo
A2: MGM
A3: NYSE: MGM
A4: Base Case Income Statement | B4: 2020 | C4: 2021 | D4: 2022 | E4: 2023 | F4: 2024 | G4: 2025 | H4: 2026 | I4: 2027 | J4: 2028 | K4: 2029 | L4: 2030 | M4: 2031
A5: Las Vegas Strip Resorts Revenue | B5: ='Base Revenue Driver'!C67 -> 2131.1673 | C5: ='Base Revenue Driver'!D67 -> 4597.9596 | D5: ='Base Revenue Driver'!E67 -> 8126.7461 | E5: ='Base Revenue Driver'!F67 -> 8767.2913 | F5: ='Base Revenue Driver'!G67 -> 8785.42 | G5: ='Base Revenue Driver'!H67 -> 8405.3474 | H5: ='Base Revenue Driver'!I67 -> 8371.5237 | I5: ='Base Revenue Driver'!J67 -> 8649.8911 | ... M5: ='Base Revenue Driver'!N67 -> 9786.3801
A6: Regional Operations Revenue | B6: ='Base Revenue Driver'!C125 -> 1967.171 | C6: ='Base Revenue Driver'!D125 -> 3305.433 | D6: ='Base Revenue Driver'!E125 -> 3670.91 | E6: ='Base Revenue Driver'!F125 -> 3670.309 | F6: ='Base Revenue Driver'!G125 -> 3720.322 | G6: ='Base Revenue Driver'!H125 -> 3772.333 | H6: ='Base Revenue Driver'!I125 -> 3746.8782 | I6: ='Base Revenue Driver'!J125 -> 3931.1999 | ... M6: ='Base Revenue Driver'!N125 -> 4424.6001
A7: MGM China Revenue | B7: ='Base Revenue Driver'!C176 -> 656.703 | C7: ='Base Revenue Driver'!D176 -> 1210.761 | D7: ='Base Revenue Driver'!E176 -> 673.593 | E7: ='Base Revenue Driver'!F176 -> 3153.609 | F7: ='Base Revenue Driver'!G176 -> 4022.384 | G7: ='Base Revenue Driver'!H176 -> 4461.743 | H7: ='Base Revenue Driver'!I176 -> 4268.2451 | I7: ='Base Revenue Driver'!J176 -> 4705.3844 | ... M7: ='Base Revenue Driver'!N176 -> 5719.4242
A8: MGM Digital Revenue | B8: ='Base Revenue Driver'!C190 -> 0 | C8: ='Base Revenue Driver'!D190 -> 0 | D8: ='Base Revenue Driver'!E190 -> 0 | E8: ='Base Revenue Driver'!F190 -> 432.146 | F8: ='Base Revenue Driver'!G190 -> 552.012 | G8: ='Base Revenue Driver'!H190 -> 654.19 | H8: ='Base Revenue Driver'!I190 -> 729.42185 | I8: ='Base Revenue Driver'!J190 -> 813.30536 | ... M8: ='Base Revenue Driver'!N190 -> 1257.0516
A9: Total Revenue | B9: =SUM(B5:B7) -> 4755.0413 | C9: =SUM(C5:C7) -> 9114.1536 | D9: =SUM(D5:D7) -> 12471.249 | E9: =SUM(E5:E7) -> 15591.209 | F9: =SUM(F5:F7) -> 16528.126 | G9: =SUM(G5:G7) -> 16639.423 | H9: =SUM(H5:H7) -> 16386.647 | I9: =SUM(I5:I7) -> 17286.475 | ... M9: =SUM(M5:M7) -> 19930.404
A10: Grotwh Rate | B10: =(B9/28590)-1 -> -0.83368166 | C10: =(C9/B9)-1 -> 0.91673491 | D10: =(D9/C9)-1 -> 0.3683387 | E10: =(E9/D9)-1 -> 0.25017223 | F10: =(F9/E9)-1 -> 0.060092622 | G10: =(G9/F9)-1 -> 0.006733821 | H10: =(H9/G9)-1 -> -0.015191414 | I10: =(I9/H9)-1 -> 0.054912291 | J10: =(J9/I9)-1 -> 0.03544585 | ... M10: =(M9/L9)-1 -> 0.0357465
A12: Las Vegas Strip EBIT | B12: ='Base Revenue Driver'!C70 -> -628.89426 | C12: ='Base Revenue Driver'!D70 -> 2141.5255 | D12: ='Base Revenue Driver'!E70 -> -349.61576 | E12: ='Base Revenue Driver'!F70 -> 1506.4587 | F12: ='Base Revenue Driver'!G70 -> 1517.5912 | G12: ='Base Revenue Driver'!H70 -> 1265.5169 | H12: ='Base Revenue Driver'!I70 -> 1381.6581 | I12: ='Base Revenue Driver'!J70 -> 1427.6006 | ... M12: ='Base Revenue Driver'!N70 -> 1615.1697
A13: Regional Operations EBIT | B13: ='Base Revenue Driver'!C128 -> -450.83079 | C13: ='Base Revenue Driver'!D128 -> 498.36023 | D13: ='Base Revenue Driver'!E128 -> 388.68688 | E13: ='Base Revenue Driver'!F128 -> 428.20055 | F13: ='Base Revenue Driver'!G128 -> 470.6898 | G13: ='Base Revenue Driver'!H128 -> 448.5751 | H13: ='Base Revenue Driver'!I128 -> 452.24382 | I13: ='Base Revenue Driver'!J128 -> 474.49123 | ... M13: ='Base Revenue Driver'!N128 -> 534.04406
A14: MGM China EBIT | B14: ='Base Revenue Driver'!C179 -> -459.16795 | C14: ='Base Revenue Driver'!D179 -> -238.16476 | D14: ='Base Revenue Driver'!E179 -> -369.37188 | E14: ='Base Revenue Driver'!F179 -> 261.14164 | F14: ='Base Revenue Driver'!G179 -> 359.62815 | G14: ='Base Revenue Driver'!H179 -> 357.93641 | H14: ='Base Revenue Driver'!I179 -> 359.1549 | I14: ='Base Revenue Driver'!J179 -> 395.93834 | ... M14: ='Base Revenue Driver'!N179 -> 481.26552
A15: MGM Digital EBIT | B15: ='Base Revenue Driver'!C193 -> 0 | C15: ='Base Revenue Driver'!D193 -> 0 | D15: ='Base Revenue Driver'!E193 -> 0 | E15: ='Base Revenue Driver'!F193 -> -115.4309 | F15: ='Base Revenue Driver'!G193 -> -177.06519 | G15: ='Base Revenue Driver'!H193 -> -214.24042 | H15: ='Base Revenue Driver'!I193 -> -109.41328 | I15: ='Base Revenue Driver'!J193 -> -73.197483 | ... M15: ='Base Revenue Driver'!N193 -> 50.282064
A16: Corporate Expense | B16: ='Base Revenue Driver'!C196 -> 896 | C16: ='Base Revenue Driver'!D196 -> -123.022 | D16: ='Base Revenue Driver'!E196 -> 1769.67 | E16: ='Base Revenue Driver'!F196 -> -189 | F16: ='Base Revenue Driver'!G196 -> -680 | G16: ='Base Revenue Driver'!H196 -> -856 | H16: ='Base Revenue Driver'!I196 -> -768 | I16: ='Base Revenue Driver'!J196 -> -768 | ... M16: ='Base Revenue Driver'!N196 -> -768
A17: Total EBIT | B17: =SUM(B12:B16) -> -642.893 | C17: =SUM(C12:C16) -> 2278.699 | D17: =SUM(D12:D16) -> 1439.3692 | E17: =SUM(E12:E16) -> 1891.37 | F17: =SUM(F12:F16) -> 1490.844 | G17: =SUM(G12:G16) -> 1001.788 | H17: =SUM(H12:H16) -> 1315.6436 | I17: =SUM(I12:I16) -> 1456.8327 | ... M17: =SUM(M12:M16) -> 1912.7614
A18: Adjusted EBIT | B18: ='Base Revenue Driver'!C200 -> -538.893 | C18: ='Base Revenue Driver'!D200 -> 784.699 | D18: ='Base Revenue Driver'!E200 -> 369.36924 | E18: ='Base Revenue Driver'!F200 -> 1492.37 | F18: ='Base Revenue Driver'!G200 -> 1490.844 | G18: ='Base Revenue Driver'!H200 -> 1373.788 | H18: ='Base Revenue Driver'!I200 -> 1315.6436 | I18: ='Base Revenue Driver'!J200 -> 1456.8327 | ... M18: ='Base Revenue Driver'!N200 -> 1912.7614
A20: Interest Expense | B20: 676.38 | C20: 799.593 | D20: 594.954 | E20: 460.293 | F20: 443.23 | G20: 419.042 | H20: =AVERAGE(E20:G20) -> 440.855 | I20: =$H$20 -> 440.855 | J20: =$H$20 -> 440.855 | K20: =$H$20 -> 440.855 | L20: =$H$20 -> 440.855 | M20: =$H$20 -> 440.855
A21: Non-operating items from unconsolidated affiliates | B21: -103.304 | C21: -83.243 | D21: -23.457 | E21: -1.032 | F21: -0.734 | G21: 1.135 | H21: 0 | I21: 0 | J21: 0 | K21: 0 | L21: 0 | M21: 0
A22: Other, net | B22: -89.361 | C22: 65.941 | D22: 82.838 | E22: 42.591 | F22: 70.573 | G22: -303.094 | H22: 0 | I22: 0 | J22: 0 | K22: 0 | L22: 0 | M22: 0
A23: Pre-Tax Income | B23: =B18-B20+B21+B22 -> -1407.938 | C23: =C18-C20+C21+C22 -> -32.196 | D23: =D18-D20+D21+D22 -> -166.20376 | E23: =E18-E20+E21+E22 -> 1073.636 | F23: =F18-F20+F21+F22 -> 1117.453 | G23: =G18-G20+G21+G22 -> 652.787 | H23: =H18-H20+H21+H22 -> 874.78856 | I23: =I18-I20+I21+I22 -> 1015.9777 | ... M23: =M18-M20+M21+M22 -> 1471.9064
A24: Tax Benefit | B24: 191.572 | C24: -253.415 | D24: -697.068 | E24: -157.839 | F24: -52.457 | G24: 240.093 | H24: =0 -> 0 | I24: =H24 -> 0 | J24: =I24 -> 0 | K24: =J24 -> 0 | L24: =K24 -> 0 | M24: =L24 -> 0
A25: Net income attributable to noncontrolling interests | B25: 287.183 | C25: 45.981 | D25: 1266.362 | E25: -172.744 | F25: -318.05 | G25: =-315.01 -> -315.01 | H25: 0 | I25: 0 | J25: 0 | K25: 0 | L25: 0 | M25: 0
A26: Adjusted Net Income | B26: =B23+B24+B25 -> -929.183 | C26: =C23+C24+C25 -> -239.63 | D26: =D23+D24+D25 -> 403.09024 | E26: =E23+E24+E25 -> 743.053 | F26: =F23+F24+F25 -> 746.946 | G26: =G23+G24+G25 -> 577.87 | H26: =H23+H24+H25 -> 874.78856 | I26: =I23+I24+I25 -> 1015.9777 | ... M26: =M23+M24+M25 -> 1471.9064
A28: Depreciation & Amort. | B28: 1210.556 | C28: 1150.61 | D28: 3482.05 | E28: 814.128 | F28: 831.097 | G28: 1017.794 | H28: =+G28*(1+H10) -> 1002.3323 | I28: =+H28*(1+I10) -> 1057.3726 | J28: =+I28*(1+J10) -> 1094.8521 | K28: =+J28*(1+K10) -> 1136.5093 | L28: =+K28*(1+L10) -> 1177.0211 | M28: =+L28*(1+M10) -> 1219.0955
A29: Adjusted EBITDA | B29: =B28+B18 -> 671.663 | C29: =C28+C18 -> 1935.309 | D29: =D28+D18 -> 3851.4192 | E29: =E28+E18 -> 2306.498 | F29: =F28+F18 -> 2321.941 | G29: =G28+G18 -> 2391.582 | H29: =H28+H18 -> 2317.9758 | I29: =I28+I18 -> 2514.2053 | ... M29: =M28+M18 -> 3131.8569
A30: EBITDA Margin | B30: =B29/B9 -> 0.14125282 | C30: =C29/C9 -> 0.21234106 | D30: =D29/D9 -> 0.30882386 | E30: =E29/E9 -> 0.1479358 | F30: =F29/F9 -> 0.14048423 | G30: =G29/G9 -> 0.14372986 | H30: =H29/H9 -> 0.14145516 | I30: =I29/I9 -> 0.14544349 | ... M30: =M29/M9 -> 0.15713965
A31: Cash Interest | B31: =B52*B49 -> 816.8655 | C31: =C52*C49 -> 804.56418 | D31: =D52*D49 -> 595.13126 | E31: =E52*E49 -> 445.97262 | F31: =F52*F49 -> 343.55621 | G31: =G52*G49 -> 373.81206 | H31: =H52*H49 -> 293.00692 | I31: =I52*I49 -> 218.0786 | ... M31: =M52*M49 -> 142.87262
A32: Capex | B32: 271 | C32: 491 | D32: 765 | E32: 932 | F32: 1200 | G32: =1100 -> 1100 | H32: =1050 -> 1050 | I32: =$H$32 -> 1050 | J32: =$H$32 -> 1050 | K32: =$H$32 -> 1050 | L32: =$H$32 -> 1050 | M32: =$H$32 -> 1050
A33: Cash Taxes | B33: =B20 -> 676.38 | C33: =C20 -> 799.593 | D33: =D20 -> 594.954 | E33: =E20 -> 460.293 | F33: =F20 -> 443.23 | G33: =G20 -> 419.042 | H33: =H20 -> 440.855 | I33: =I20 -> 440.855 | ... M33: =M20 -> 440.855
A34: FCF | B34: =B29-B31-B32-B33 -> -1092.5825 | C34: =C29-C31-C32-C33 -> -159.84818 | D34: =D29-D31-D32-D33 -> 1896.334 | E34: =E29-E31-E32-E33 -> 468.23238 | F34: =F29-F31-F32-F33 -> 335.15479 | G34: =G29-G31-G32-G33 -> 498.72794 | H34: =H29-H31-H32-H33 -> 534.11392 | I34: =I29-I31-I32-I33 -> 805.27171 | ... M34: =M29-M31-M32-M33 -> 1498.1292
A35: Maintence Capex (60%) | G35: =G32*0.6 -> 660
A36: Operating Cash before maturities | G36: =G29-G31-G35 -> 1357.7699
A38: Lease Expense | B38: 751.002 | C38: 870.779 | D38: 1986.853 | E38: 2306.64 | F38: 2300.373 | G38: =F38*(1+G10) -> 2315.8633 | H38: =G38*(1+H10) -> 2280.6821 | I38: =H38*(1+I10) -> 2405.9195 | J38: =I38*(1+J10) -> 2491.1994 | K38: =J38*(1+K10) -> 2585.9853 | L38: =K38*(1+L10) -> 2678.1647 | M38: =L38*(1+M10) -> 2773.8997
A40: Credit Matrix
A41: EBIT/Interest | B41: =B18/B20 -> -0.79673113 | C41: =C18/C20 -> 0.98137302 | D41: =D18/D20 -> 0.62083663 | E41: =E18/E20 -> 3.2422175 | F41: =F18/F20 -> 3.36359 | G41: =G18/G20 -> 3.2784017 | H41: =H18/H20 -> 2.9843 | I41: =I18/I20 -> 3.304562 | ... M41: =M18/M20 -> 4.3387539
A42: EBITDA/Interest | B42: =B29/B20 -> 0.99302611 | C42: =C29/C20 -> 2.4203676 | D42: =D29/D20 -> 6.473474 | E42: =E29/E20 -> 5.0109343 | F42: =F29/F20 -> 5.2386819 | G42: =G29/G20 -> 5.7072608 | H42: =H29/H20 -> 5.2579098 | I42: =I29/I20 -> 5.703021 | ... M42: =M29/M20 -> 7.104052
A43: (EBITDA - CAPEX)/Interest | B43: =(B29-B32)/B20 -> 0.59236376 | C43: =(C29-C32)/C20 -> 1.8063052 | D43: =(D29-D32)/D20 -> 5.1876603 | E43: =(E29-E32)/E20 -> 2.9861371 | F43: =(F29-F32)/F20 -> 2.531284 | G43: =(G29-G32)/G20 -> 3.0822256 | H43: =(H29-H32)/H20 -> 2.8761743 | I43: =(I29-I32)/I20 -> 3.3212855 | ... M43: =(M29-M32)/M20 -> 4.7223165
A44: Gross Debt/EBITDAR | B44: =B52/(B29+B38) -> 8.6996939 | C44: =C52/(C29+C38) -> 4.551126 | D44: =D52/(D29+D38) -> 1.3068743 | E44: =E52/(E29+E38) -> 1.611241 | F44: =F52/(F29+F38) -> 1.3763998 | G44: =G52/(G29+G38) -> 1.3234782 | H44: =H52/(H29+H38) -> 1.1799212 | I44: =I52/(I29+I38) -> 0.869094 | ... M44: =M52/(M29+M38) -> 0.3557661
A45: Adjusted Debt/EBITDAR | B45: =B58/(B29+B38) -> 14.597159 | C45: =C58/(C29+C38) -> 8.7571466 | D45: =D58/(D29+D38) -> 5.6145355 | E45: =E58/(E29+E38) -> 7.0581762 | F45: =F58/(F29+F38) -> 6.8014183 | G45: =G58/(G29+G38) -> 6.6262996 | H45: =H58/(H29+H38) -> 6.6283474 | I45: =I58/(I29+I38) -> 5.9566566 | ... M45: =M58/(M29+M38) -> 4.5933554
A46: FCF/ Debt | B46: =B34/B58 -> -0.052611812 | C46: =C34/C58 -> -0.0065049474 | D46: =D34/D58 -> 0.05785177 | E46: =E34/E58 -> 0.014380451 | F46: =F34/F58 -> 0.010660719 | G46: =G34/G58 -> 0.015988486 | H46: =H34/H58 -> 0.017522559 | I46: =I34/I58 -> 0.027476648 | ... M46: =M34/M58 -> 0.055226013
A48: Note 8 & 9: Debt & Leases
A49: Interest Rate | B49: 0.066 | C49: 0.063 | D49: 0.078 | E49: 0.06 | F49: 0.054 | G49: 0.06 | H49: 0.054 | I49: 0.051 | J49: 0.048 | K49: 0.061 | L49: 0.049 | M49: 0.068
A50: Long Term Notes | B50: 12376.684 | C50: 11770.797 | D50: 6343.81 | E50: 7432.817 | F50: 6362.098 | G50: 6230.141 | H50: 5426 | I50: =H50-'MGM Bond'!D6-'MGM Bond'!D7 -> 4276 | J50: =I50-'MGM Bond'!D8-'MGM Bond'!D9 -> 2851 | K50: =J50-'MGM Bond'!D10 -> 2101 | L50: =K50 -> 2101 | M50: =L50 -> 2101
A51: Short Term Debt | B51: 0 | C51: 1000 | D51: 1286 | E51: 0 | F51: 0 | G51: 0 | H51: 0 | I51: 0 | J51: 0 | K51: 0 | L51: 0 | M51: 0
A52: Total Debt | B52: =SUM(B49:B51) -> 12376.75 | C52: =SUM(C49:C51) -> 12770.86 | D52: =SUM(D49:D51) -> 7629.888 | E52: =SUM(E49:E51) -> 7432.877 | F52: =SUM(F49:F51) -> 6362.152 | G52: =SUM(G49:G51) -> 6230.201 | H52: =SUM(H49:H51) -> 5426.054 | I52: =SUM(I49:I51) -> 4276.051 | ... M52: =SUM(M49:M51) -> 2101.068
A53: Total Purchase Obligations 2025 onwards
A54: Operating Leases | B54: 8390.117 | C54: 11802.464 | D54: 25149.299 | E54: 25127.464 | F54: 25076.139 | G54: 24962.742 | H54: =AVERAGE(E54:G54) -> 25055.448 | I54: =AVERAGE(F54:H54) -> 25031.443 | J54: =AVERAGE(G54:I54) -> 25016.544 | K54: =AVERAGE(H54:J54) -> 25034.479 | L54: =AVERAGE(I54:K54) -> 25027.489 | M54: =AVERAGE(J54:L54) -> 25026.171
O55: Pension obligations are primarily multiemployer in nature and not recognized on balance sheet, limiting their relevance to leverage analysis relative to the company’s substantial lease obligations
A56: Unfunded Pensions | B56: 0 | C56: 0 | D56: 0 | E56: 0 | F56: 0 | G56: 0 | H56: 0 | I56: 0 | J56: 0 | K56: 0 | L56: 0 | M56: 0 | O56: MGM participates in multiemployer pension plans, limiting balance sheet recognition of pension liabilities, with exposure primarily reflected through ongoing contributions and contingent withdrawal risk
A58: Adjusted Leverage | B58: =B52+B54+B56 -> 20766.867 | C58: =C52+C54+C56 -> 24573.324 | D58: =D52+D54+D56 -> 32779.187 | E58: =E52+E54+E56 -> 32560.341 | F58: =F52+F54+F56 -> 31438.291 | G58: =G52+G54+G56 -> 31192.943 | H58: =H52+H54+H56 -> 30481.502 | I58: =I52+I54+I56 -> 29307.494 | ... M58: =M52+M54+M56 -> 27127.239 | O58: Lease adjusted debt/ Ebitdar

Sheet Downside Revenue Driver
A1: Owen Purnomo
A2: MGM Resorts International
A3: NYSE: MGM
A4: Segment Revenue Driver
A5: Figures in USD mm
A6: Segment | B6: Metrics | C6: 2020 | D6: 2021 | E6: 2022 | F6: 2023 | G6: 2024 | H6: 2025 | I6: 2026 | J6: 2027 | K6: 2028 | L6: 2029 | M6: 2030 | N6: 2031
A7: Las Vegas Strip Resorts | B7: Las Vegas Visitor Growth% | C7: - | D7: - | E7: - | F7: - | G7: - | H7: - | I7: -0.03 | J7: -0.015 | K7: =0 -> 0 | L7: =0 -> 0 | M7: =0 -> 0 | N7: =0 -> 0
B8: Spend per Visitor Growth % | C8: - | D8: - | E8: - | F8: - | G8: - | H8: - | I8: -0.02 | J8: -0.015 | K8: =0 -> 0 | L8: =0 -> 0 | M8: =0 -> 0 | N8: =0 -> 0
B9: Event Based Growth% | C9: - | D9: - | E9: - | F9: - | G9: - | H9: - | I9: 0 | J9: 0 | K9: 0 | L9: 0.0075 | M9: 0 | N9: 0
B10: Total Growth | C10: - | D10: - | E10: - | F10: - | G10: - | H10: - | I10: =SUM(I7:I9) -> -0.05 | J10: =SUM(J7:J9) -> -0.03 | K10: =SUM(K7:K9) -> 0 | L10: =SUM(L7:L9) -> 0.0075 | M10: =SUM(M7:M9) -> 0 | N10: =SUM(N7:N9) -> 0
A12: Casino
A13: Table Games | B13: Table Drop | C13: 2001 | D13: 3587 | E13: 5804 | F13: 6215 | G13: 6028 | H13: 6127 | I13: =H13*(1+I10) -> 5820.65 | J13: =I13*(1+J10) -> 5646.0305 | K13: =J13*(1+K10) -> 5646.0305 | L13: =K13*(1+L10) -> 5688.3757 | M13: =L13*(1+M10) -> 5688.3757 | N13: =M13*(1+N10) -> 5688.3757
B14: Table Drop Growth% | C14: =(C13-3526)/3526 -> -0.43250142 | D14: =(D13-C13)/C13 -> 0.7926037 | E14: =(E13-D13)/D13 -> 0.61806524 | F14: =(F13-E13)/E13 -> 0.070813232 | G14: =(G13-F13)/F13 -> -0.030088496 | H14: =(H13-G13)/G13 -> 0.016423358 | I14: =(I13-H13)/H13 -> -0.05 | J14: =(J13-I13)/I13 -> -0.03 | K14: =(K13-J13)/J13 -> 0 | ... N14: =(N13-M13)/M13 -> 0
B15: Table Win% | C15: 0.235 | D15: 0.246 | E15: 0.24 | F15: 0.263 | G15: 0.244 | H15: 0.252 | I15: =AVERAGE(C15:H15) -> 0.24666667 | J15: =$I$15 -> 0.24666667 | K15: =$I$15 -> 0.24666667 | L15: =$I$15 -> 0.24666667 | M15: =$I$15 -> 0.24666667 | N15: =$I$15 -> 0.24666667
B16: Table Win | C16: =C13*C15 -> 470.235 | D16: =D13*D15 -> 882.402 | E16: =E13*E15 -> 1392.96 | F16: =F13*F15 -> 1634.545 | G16: =G13*G15 -> 1470.832 | H16: =H13*H15 -> 1544.004 | I16: =I13*I15 -> 1435.7603 | J16: =J13*J15 -> 1392.6875 | ... N16: =N13*N15 -> 1403.1327
A18: Slot Games | B18: Slot Handle | C18: 6904 | D18: 15089 | E18: 22812 | F18: 23920 | G18: 23840 | H18: 24565 | I18: =H18*(1+I10) -> 23336.75 | J18: =I18*(1+J10) -> 22636.647 | K18: =J18*(1+K10) -> 22636.647 | L18: =K18*(1+L10) -> 22806.422 | M18: =L18*(1+M10) -> 22806.422 | N18: =M18*(1+N10) -> 22806.422
B19: Slot Handle Growth% | C19: =(C18-12874)/12874 -> -0.46372534 | D19: =(D18-C18)/C18 -> 1.1855446 | E19: =(E18-D18)/D18 -> 0.51182981 | F19: =(F18-E18)/E18 -> 0.048570928 | G19: =(G18-F18)/F18 -> -0.0033444816 | H19: =(H18-G18)/G18 -> 0.030411074 | I19: =(I18-H18)/H18 -> -0.05 | J19: =(J18-I18)/I18 -> -0.03 | K19: =(K18-J18)/J18 -> 0 | ... N19: =(N18-M18)/M18 -> 0
B20: Slot Win% | C20: 0.094 | D20: 0.094 | E20: 0.093 | F20: 0.093 | G20: 0.094 | H20: 0.094 | I20: =AVERAGE(C20:H20) -> 0.093666667 | J20: =$I$20 -> 0.093666667 | K20: =$I$20 -> 0.093666667 | L20: =$I$20 -> 0.093666667 | M20: =$I$20 -> 0.093666667 | N20: =$I$20 -> 0.093666667
B21: Slot Win | C21: =C18*C20 -> 648.976 | D21: =D18*D20 -> 1418.366 | E21: =E18*E20 -> 2121.516 | F21: =F18*F20 -> 2224.56 | G21: =G18*G20 -> 2240.96 | H21: =H18*H20 -> 2309.11 | I21: =I18*I20 -> 2185.8756 | J21: =J18*J20 -> 2120.2993 | ... N21: =N18*N20 -> 2136.2016
A23: Gaming Summary | B23: Total Handle | C23: =C13+C18 -> 8905 | D23: =D13+D18 -> 18676 | E23: =E13+E18 -> 28616 | F23: =F13+F18 -> 30135 | G23: =G13+G18 -> 29868 | H23: =H13+H18 -> 30692 | I23: =I13+I18 -> 29157.4 | J23: =J13+J18 -> 28282.678 | ... N23: =N13+N18 -> 28494.798
B24: Gross Gaming Win | C24: =C16+C21 -> 1119.211 | D24: =D16+D21 -> 2300.768 | E24: =E16+E21 -> 3514.476 | F24: =F16+F21 -> 3859.105 | G24: =G16+G21 -> 3711.792 | H24: =H16+H21 -> 3853.114 | I24: =I16+I21 -> 3621.6359 | J24: =J16+J21 -> 3512.9868 | ... N24: =N16+N21 -> 3539.3342
B25: Gaming Incentives (SSP Allocation) | C25: 422.421 | D25: 752 | E25: 1410 | F25: 1731 | G25: 1752 | H25: 1839 | I25: =H25*(1+I26) -> 1747.05 | J25: =I25*(1+J26) -> 1694.6385 | K25: =J25*(1+K26) -> 1694.6385 | L25: =K25*(1+L26) -> 1707.3483 | M25: =L25*(1+M26) -> 1707.3483 | N25: =M25*(1+N26) -> 1707.3483
B26: Gaming Incentives Growth% | C26: =(C25-751)/751 -> -0.43752197 | D26: =(D25-C25)/C25 -> 0.78021453 | E26: =(E25-D25)/D25 -> 0.875 | F26: =(F25-E25)/E25 -> 0.22765957 | G26: =(G25-F25)/F25 -> 0.012131716 | H26: =(H25-G25)/G25 -> 0.049657534 | I26: =I10 -> -0.05 | J26: =J10 -> -0.03 | K26: =K10 -> 0 | L26: =L10 -> 0.0075 | M26: =M10 -> 0 | N26: =N10 -> 0
B27: Gaming Incentives (% of Gross Gaming Win) | C27: =C25/C24 -> 0.37742749 | D27: =D25/D24 -> 0.32684738 | E27: =E25/E24 -> 0.40119779 | F27: =F25/F24 -> 0.4485496 | G27: =G25/G24 -> 0.47200921 | H27: =H25/H24 -> 0.4772763 | I27: =I25/I24 -> 0.4823925 | J27: =J25/J24 -> 0.4823925 | ... N27: =N25/N24 -> 0.4823925 | P27: Despite stable hold rates and mix, rising promotional reinvestment has structurally diluted revenue conversion, indicating competitive pressure rather than demand weakness
B28: Casino Revenue | C28: =C24+31-C25 -> 727.79 | D28: =D24-D25 -> 1548.768 | E28: =E24-E25 -> 2104.476 | F28: =F24-F25 -> 2128.105 | G28: =G24-G25 -> 1959.792 | H28: =H24-H25 -> 2014.114 | I28: =I24-I25 -> 1874.5859 | J28: =J24-J25 -> 1818.3483 | K28: =K24-K25 -> 1818.3483 | ... N28: =N24-N25 -> 1831.986
B29: Casino Revenue Growth% | C29: =(C28-1296)/1296 -> -0.43843364 | D29: =(D28-C28)/C28 -> 1.1280424 | E29: =(E28-D28)/D28 -> 0.35880648 | F29: =(F28-E28)/E28 -> 0.011227973 | G29: =(G28-F28)/F28 -> -0.079090552 | H29: =(H28-G28)/G28 -> 0.027718248 | I29: =(I28-H28)/H28 -> -0.069275167 | J29: =(J28-I28)/I28 -> -0.03 | K29: =(K28-J28)/J28 -> 0 | ... N29: =(N28-M28)/M28 -> 0
A31: Analytics | B31: Total SSP Allocation | C31: =C25 -> 422.421 | D31: =D25 -> 752 | E31: =E25 -> 1410 | F31: =F25 -> 1731 | G31: =G25 -> 1752 | H31: =H25 -> 1839 | I31: =I25 -> 1747.05 | J31: =J25 -> 1694.6385 | ... N31: =N25 -> 1707.3483 | P31: MGM retains only ~50% of gross gaming win as casino revenue, with the remainder reinvested into customer incentives and reallocated across non-gaming segments, materially distorting segment-level profitability.
B32: Rooms% of LVSR | C32: =C54/C67 -> 0.25778233 | D32: =D54/D67 -> 0.27516371 | E32: =E54/E67 -> 0.30261436 | F32: =F54/F67 -> 0.34174595 | G32: =G54/G67 -> 0.35634358 | H32: =H54/H67 -> 0.33850277 | I32: =I54/I67 -> 0.32380574 | J32: =J54/J67 -> 0.33490682 | ... N32: =N54/N67 -> 0.35107066
B33: SSP Allocation to Rooms | C33: =C31*C32 -> 108.89267 | D33: =D31*D32 -> 206.92311 | E33: =E31*E32 -> 426.68625 | F33: =F31*F32 -> 591.56224 | G33: =G31*G32 -> 624.31394 | H33: =H31*H32 -> 622.5066 | I33: =I31*I32 -> 565.70481 | J33: =J31*J32 -> 567.54599 | ... N33: =N31*N32 -> 599.39989
B34: F&B% of LVSR | C34: =C59/C67 -> 0.22100565 | D34: =D59/D67 -> 0.22075009 | E34: =E59/E67 -> 0.26148227 | F34: =F59/F67 -> 0.26108406 | G34: =G59/G67 -> 0.26817159 | H34: =H59/H67 -> 0.26887645 | I34: =I59/I67 -> 0.27688535 | J34: =J59/J67 -> 0.27233973 | ... N34: =N59/N67 -> 0.26572102
B35: SSP Allocation to Food and Beverage | C35: =C31*C34 -> 93.357426 | D35: =D31*D34 -> 166.00407 | E35: =E31*E34 -> 368.69 | F35: =F31*F34 -> 451.93651 | G35: =G31*G34 -> 469.83662 | H35: =H31*H34 -> 494.4638 | I35: =I31*I34 -> 483.73256 | J35: =J31*J34 -> 461.51739 | ... N35: =N31*N34 -> 453.67833
B36: Entertainmen% of LVSR | C36: =C64/C67 -> 0.17971372 | D36: =D64/D67 -> 0.1672481 | E36: =E64/E67 -> 0.17694659 | F36: =F64/F67 -> 0.15443767 | G36: =G64/G67 -> 0.15241161 | H36: =H64/H67 -> 0.15299784 | I36: =I64/I67 -> 0.15755512 | J36: =J64/J67 -> 0.15496854 | ... N36: =N64/N67 -> 0.15120232
B37: SSP Allocation to Entertainment and Other | C37: =C31*C36 -> 75.91485 | D37: =D31*D36 -> 125.77057 | E37: =E31*E36 -> 249.49469 | F37: =F31*F36 -> 267.3316 | G37: =G31*G36 -> 267.02514 | H37: =H31*H36 -> 281.36303 | I37: =I31*I36 -> 275.25667 | J37: =J31*J36 -> 262.61565 | ... N37: =N31*N36 -> 258.15502
B39: Blend Hold% | C39: =C24/C23 -> 0.12568344 | D39: =D24/D23 -> 0.12319383 | E39: =E24/E23 -> 0.12281507 | F39: =F24/F23 -> 0.12806056 | G39: =G24/G23 -> 0.1242732 | H39: =H24/H23 -> 0.12554131 | I39: =I24/I23 -> 0.12420984 | J39: =J24/J23 -> 0.12420984 | ... N39: =N24/N23 -> 0.12420984
B40: Table Mix% | C40: =C16/C24 -> 0.42014866 | D40: =D16/D24 -> 0.38352498 | E40: =E16/E24 -> 0.39634927 | F40: =F16/F24 -> 0.42355546 | G40: =G16/G24 -> 0.39625927 | H40: =H16/H24 -> 0.40071589 | I40: =I16/I24 -> 0.39643972 | J40: =J16/J24 -> 0.39643972 | ... N40: =N16/N24 -> 0.39643972
B41: Slot Mix% | C41: =C21/C24 -> 0.57985134 | D41: =D21/D24 -> 0.61647502 | E41: =E21/E24 -> 0.60365073 | F41: =F21/F24 -> 0.57644454 | G41: =G21/G24 -> 0.60374073 | H41: =H21/H24 -> 0.59928411 | I41: =I21/I24 -> 0.60356028 | J41: =J21/J24 -> 0.60356028 | ... N41: =N21/N24 -> 0.60356028
B42: Net Monetization | C42: =C28/C24 -> 0.65027059 | D42: =D28/D24 -> 0.67315262 | E42: =E28/E24 -> 0.59880221 | F42: =F28/F24 -> 0.5514504 | G42: =G28/G24 -> 0.52799079 | H42: =H28/H24 -> 0.5227237 | I42: =I28/I24 -> 0.5176075 | J42: =J28/J24 -> 0.5176075 | ... N42: =N28/N24 -> 0.5176075
B43: Promo/SSP Rate | C43: =1-C42 -> 0.34972941 | D43: =1-D42 -> 0.32684738 | E43: =1-E42 -> 0.40119779 | F43: =1-F42 -> 0.4485496 | G43: =1-G42 -> 0.47200921 | H43: =1-H42 -> 0.4772763 | I43: =1-I42 -> 0.4823925 | J43: =1-J42 -> 0.4823925 | ... N43: =1-N42 -> 0.4823925
A45: Rooms | B45: Occupancy% | C45: 0.55 | D45: 0.74 | E45: 0.89 | F45: 0.93 | G45: 0.94 | H45: 0.92 | I45: 0.8 | J45: =$I$45 -> 0.8 | K45: =$I$45 -> 0.8 | L45: =$I$45 -> 0.8 | M45: =$I$45 -> 0.8 | N45: =$I$45 -> 0.8
B46: Occupancy Growth% | C46: =(C45-91%)/91% -> -0.3956044 | D46: =(D45-C45)/C45 -> 0.34545455 | E46: =(E45-D45)/D45 -> 0.2027027 | F46: =(F45-E45)/E45 -> 0.04494382 | G46: =(G45-F45)/F45 -> 0.010752688 | H46: =(H45-G45)/G45 -> -0.021276596 | I46: =(I45-H45)/H45 -> -0.13043478 | J46: =(J45-I45)/I45 -> 0 | K46: =(K45-J45)/J45 -> 0 | ... N46: =(N45-M45)/M45 -> 0
B47: # of Rooms and Suites | C47: 31098 | D47: 36595 | E47: 37293 | F47: 37243 | G47: 37243 | H47: 37000 | I47: =AVERAGE(F47:H47) -> 37162 | J47: =$I$47 -> 37162 | K47: =$I$47 -> 37162 | L47: =$I$47 -> 37162 | M47: =$I$47 -> 37162 | N47: =$I$47 -> 37162
B48: ADR (Average Daily Rate) | C48: 161 | D48: 173 | E48: 229 | F48: 256 | G48: 260 | H48: 249 | I48: =H48*(1+I49) -> 249 | J48: =I48*(1+J49) -> 253.98 | K48: =J48*(1+K49) -> 259.0596 | L48: =K48*(1+L49) -> 264.24079 | M48: =L48*(1+M49) -> 269.52561 | N48: =M48*(1+N49) -> 274.91612
B49: ADR Growth% | C49: =(C48-167)/167 -> -0.035928144 | D49: =(D48-C48)/C48 -> 0.074534161 | E49: =(E48-D48)/D48 -> 0.32369942 | F49: =(F48-E48)/E48 -> 0.11790393 | G49: =(G48-F48)/F48 -> 0.015625 | H49: =(H48-G48)/G48 -> -0.042307692 | I49: =0% -> 0 | J49: =2% -> 0.02 | K49: =$J$49 -> 0.02 | L49: =$J$49 -> 0.02 | M49: =$J$49 -> 0.02 | N49: =$J$49 -> 0.02
B50: RevPar | C50: 88 | D50: 128 | E50: 203 | F50: 237 | G50: 245 | H50: 229 | I50: =I48*I51 -> 231.38472 | J50: =J48*J51 -> 236.01241 | K50: =K48*K51 -> 240.73266 | L50: =L48*L51 -> 245.54731 | M50: =M48*M51 -> 250.45826 | N50: =N48*N51 -> 255.46742
B51: Revpar/ADR | C51: =C50/C48 -> 0.54658385 | D51: =D50/D48 -> 0.73988439 | E51: =E50/E48 -> 0.88646288 | F51: =F50/F48 -> 0.92578125 | G51: =G50/G48 -> 0.94230769 | H51: =H50/H48 -> 0.91967871 | I51: =AVERAGE(F51:H51) -> 0.92925589 | J51: =$I$51 -> 0.92925589 | K51: =$I$51 -> 0.92925589 | L51: =$I$51 -> 0.92925589 | M51: =$I$51 -> 0.92925589 | N51: =$I$51 -> 0.92925589
B52: Rooms Promotion | C52: =C33 -> 108.89267 | D52: =D33 -> 206.92311 | E52: =E33 -> 426.68625 | F52: =F33 -> 591.56224 | G52: =G33 -> 624.31394 | H52: =H33 -> 622.5066 | I52: =I33 -> 565.70481 | J52: =J33 -> 567.54599 | ... N52: =N33 -> 599.39989
B53: Rooms Cash Revenue | C53: =C54-C52 -> 440.4846 | D53: =D54-D52 -> 1058.2685 | E53: =E54-E52 -> 2032.5838 | F53: =F54-F52 -> 2404.6241 | G53: =G54-G52 -> 2506.314 | H53: =H54-H52 -> 2222.7268 | I53: =I54-I52 -> 1945.1211 | J53: =J54-J52 -> 1993.4964 | ... N53: =N54-N52 -> 2172.7548
B54: Rooms Total Revenue | C54: =((C50*C47*365)/1000000)*C45 -> 549.37727 | D54: =((D50*D47*365)/1000000)*D45 -> 1265.1916 | E54: =((E50*E47*365)/1000000)*E45 -> 2459.2701 | F54: =((F50*F47*365)/1000000)*F45 -> 2996.1863 | G54: =((G50*G47*365)/1000000)*G45 -> 3130.628 | H54: =((H50*H47*365)/1000000)*H45 -> 2845.2334 | I54: =((I50*I47*365)/1000000)*I45 -> 2510.8259 | J54: =((J50*J47*365)/1000000)*J45 -> 2561.0424 | ... N54: =((N50*N47*365)/1000000)*N45 -> 2772.1547
B55: Rooms Total Cash Revenue Growth% | C55: =(C54-1863)/1863 -> -0.7051115 | D55: =(D53-C53)/C53 -> 1.4025097 | E55: =(E53-D53)/D53 -> 0.92066932 | F55: =(F53-E53)/E53 -> 0.18303807 | G55: =(G53-F53)/F53 -> 0.042289331 | H55: =(H53-G53)/G53 -> -0.11314912 | I55: =(I53-H53)/H53 -> -0.12489422 | J55: =(J53-I53)/I53 -> 0.024870093 | K55: =(K53-J53)/J53 -> 0.021932148 | ... N55: =(N53-M53)/M53 -> 0.021954167
A57: Food and Beverage | B57: Food and Beverage Promotional Revenue | C57: =C35 -> 93.357426 | D57: =D35 -> 166.00407 | E57: =E35 -> 368.69 | F57: =F35 -> 451.93651 | G57: =G35 -> 469.83662 | H57: =H35 -> 494.4638 | I57: =I35 -> 483.73256 | J57: =J35 -> 461.51739 | ... N57: =N35 -> 453.67833
B58: Food and Beverage Cash Revenue | C58: =C59-C57 -> 377.64257 | D58: =D59-D57 -> 848.99593 | E58: =E59-E57 -> 1756.31 | F58: =F59-F57 -> 1837.0635 | G58: =G59-G57 -> 1886.1634 | H58: =H59-H57 -> 1765.5362 | I58: =I59-I57 -> 1663.2674 | J58: =J59-J57 -> 1621.0726 | ... N58: =N59-N57 -> 1644.5311
B59: Food and Beverage Total Revenue | C59: 471 | D59: 1015 | E59: 2125 | F59: 2289 | G59: 2356 | H59: 2260 | I59: =H59*(1+I10) -> 2147 | J59: =I59*(1+J10) -> 2082.59 | K59: =J59*(1+K10) -> 2082.59 | L59: =K59*(1+L10) -> 2098.2094 | M59: =L59*(1+M10) -> 2098.2094 | N59: =M59*(1+N10) -> 2098.2094
B60: Food and Beverage Cash Revenue Growth% | C60: =(C59-1517)/1517 -> -0.68951879 | D60: =(D58-C58)/C58 -> 1.2481468 | E60: =(E58-D58)/D58 -> 1.0686907 | F60: =(F58-E58)/E58 -> 0.045979065 | G60: =(G58-F58)/F58 -> 0.026727376 | H60: =(H58-G58)/G58 -> -0.063953728 | I60: =(I58-H58)/H58 -> -0.057925044 | J60: =(J58-I58)/I58 -> -0.025368637 | K60: =(K58-J58)/J58 -> 0.0018942632 | ... N60: =(N58-M58)/M58 -> 0.0019158498
A61: Entertainment, retail and other
B62: Entertianment & other Promotional Revenue | C62: =C37 -> 75.91485 | D62: =D37 -> 125.77057 | E62: =E37 -> 249.49469 | F62: =F37 -> 267.3316 | G62: =G37 -> 267.02514 | H62: =H37 -> 281.36303 | I62: =I37 -> 275.25667 | J62: =J37 -> 262.61565 | ... N62: =N37 -> 258.15502
B63: Entertianment & other Cash Revenue | C63: =C64-C62 -> 307.08515 | D63: =D64-D62 -> 643.22943 | E63: =E64-E62 -> 1188.5053 | F63: =F64-F62 -> 1086.6684 | G63: =G64-G62 -> 1071.9749 | H63: =H64-H62 -> 1004.637 | I63: =I64-I62 -> 946.44333 | J63: =J64-J62 -> 922.43335 | ... N63: =N64-N62 -> 935.78185
B64: Entertainment, retail and other | C64: 383 | D64: 769 | E64: 1438 | F64: 1354 | G64: 1339 | H64: 1286 | I64: =H64*(1+I10) -> 1221.7 | J64: =I64*(1+J10) -> 1185.049 | K64: =J64*(1+K10) -> 1185.049 | L64: =K64*(1+L10) -> 1193.9369 | M64: =L64*(1+M10) -> 1193.9369 | N64: =M64*(1+N10) -> 1193.9369
B65: Entertainment, retail and other Cash Growth% | C65: =(C64-1153)/1153 -> -0.66782307 | D65: =(D63-C63)/C63 -> 1.0946289 | E65: =(E63-D63)/D63 -> 0.847716 | F65: =(F63-E63)/E63 -> -0.085684858 | G65: =(G63-F63)/F63 -> -0.013521643 | H65: =(H63-G63)/G63 -> -0.062816667 | I65: =(I63-H63)/H63 -> -0.057925044 | J65: =(J63-I63)/I63 -> -0.025368637 | K65: =(K63-J63)/J63 -> 0.0018942632 | ... N65: =(N63-M63)/M63 -> 0.0019158498
B67: Segment Revenue (USD mm) | C67: =C28+C54+C59+C64 -> 2131.1673 | D67: =D28+D54+D59+D64 -> 4597.9596 | E67: =E28+E54+E59+E64 -> 8126.7461 | F67: =F28+F54+F59+F64 -> 8767.2913 | G67: =G28+G54+G59+G64 -> 8785.42 | H67: =H28+H54+H59+H64 -> 8405.3474 | I67: =I28+I54+I59+I64 -> 7754.1118 | J67: =J28+J54+J59+J64 -> 7647.0297 | ... N67: =N28+N54+N59+N64 -> 7896.2869
B68: Segment of Total Revenue% | C68: =C67/C198 -> 0.44819112 | D68: =D67/D198 -> 0.50448564 | E68: =E67/E198 -> 0.6516385 | F68: =F67/F198 -> 0.54715702 | G68: =G67/G198 -> 0.5143647 | H68: =H67/H198 -> 0.48603766 | I68: =I67/I198 -> 0.48760926 | J68: =J67/J198 -> 0.47673851 | ... N68: =N67/N198 -> 0.49935427
B69: Segment EBIT Margin% | C69: =C70/C67 -> -0.2950938 | D69: =D70/D67 -> 0.46575562 | E69: =E70/E67 -> -0.043020387 | F69: =F70/F67 -> 0.17182715 | G69: =G70/G67 -> 0.17273975 | H69: =H70/H67 -> 0.15056093 | I69: =10% -> 0.1 | J69: 0.11 | K69: =12% -> 0.12 | L69: =K69 -> 0.12 | M69: =L69 -> 0.12 | N69: =M69 -> 0.12
B70: Segment EBIT (USD mm) | C70: =232.188-(1210.556*C68)-(710.683*C68) -> -628.89426 | D70: =3142.308-(1150.61*D68)-(833.158*D68) -> 2141.5255 | E70: =3190.486-(3482.05*E68)-(1950.566*E68) -> -349.61576 | F70: =3190.486-(814.128*F68)-(2263.649*F68) -> 1506.4587 | G70: =3106.543-(831.097*G68)-(2258.057*G68) -> 1517.5912 | H70: =2857.873-(1017.794*H68)-(2258.405*H68) -> 1265.5169 | I70: =I67*I69 -> 775.41118 | J70: =J67*J69 -> 841.17327 | K70: =K67*K69 -> 923.79007 | L70: =L67*L69 -> 934.63689 | M70: =M67*M69 -> 941.03171 | N70: =N67*N69 -> 947.55443
A72: Regional Operations | B72: Regional Visitor Growth% | C72: - | D72: - | E72: - | F72: - | G72: - | H72: - | I72: -0.015 | J72: 0.01 | K72: =0 -> 0 | L72: =0 -> 0 | M72: =0 -> 0 | N72: =0 -> 0
B73: Spend per Visitor Growth % | C73: - | D73: - | E73: - | F73: - | G73: - | H73: - | I73: -0.015 | J73: 0.01 | K73: 0 | L73: 0 | M73: 0 | N73: 0
B74: Event Based Growth% | C74: - | D74: - | E74: - | F74: - | G74: - | H74: - | I74: 0 | J74: 0 | K74: 0 | L74: 0 | M74: 0 | N74: 0
B75: Total Growth | C75: - | D75: - | E75: - | F75: - | G75: - | H75: - | I75: =SUM(I72:I74) -> -0.03 | J75: =SUM(J72:J74) -> 0.02 | K75: =SUM(K72:K74) -> 0 | L75: =SUM(L72:L74) -> 0 | M75: =SUM(M72:M74) -> 0 | N75: =SUM(N72:N74) -> 0
A77: Casino
A78: Table Games | B78: Table Drop | C78: 2422 | D78: 3980 | E78: 4469 | F78: 3886 | G78: 3909 | H78: 4001 | I78: =H78*(1+I75) -> 3880.97 | J78: =I78*(1+J75) -> 3958.5894 | K78: =J78*(1+K75) -> 3958.5894 | L78: =K78*(1+L75) -> 3958.5894 | M78: =L78*(1+M75) -> 3958.5894 | N78: =M78*(1+N75) -> 3958.5894
B79: Table Drop Growth% | C79: =(C78-4226)/4226 -> -0.42688121 | D79: =(D78-C78)/C78 -> 0.64327002 | E79: =(E78-D78)/D78 -> 0.12286432 | F79: =(F78-E78)/E78 -> -0.13045424 | G79: =(G78-F78)/F78 -> 0.0059186824 | H79: =(H78-G78)/G78 -> 0.023535431 | I79: =(I78-H78)/H78 -> -0.03 | J79: =(J78-I78)/I78 -> 0.02 | K79: =(K78-J78)/J78 -> 0 | ... N79: =(N78-M78)/M78 -> 0
B80: Table Win% | C80: 0.201 | D80: 0.198 | E80: 0.209 | F80: 0.21 | G80: 0.206 | H80: 0.204 | I80: =AVERAGE(C80:H80) -> 0.20466667 | J80: =$I$15 -> 0.24666667 | K80: =$I$15 -> 0.24666667 | L80: =$I$15 -> 0.24666667 | M80: =$I$15 -> 0.24666667 | N80: =$I$15 -> 0.24666667
B81: Table Win | C81: =C78*C80 -> 486.822 | D81: =D78*D80 -> 788.04 | E81: =E78*E80-1 -> 933.021 | F81: =F78*F80-2 -> 814.06 | G81: =G78*G80+2 -> 807.254 | H81: =H78*H80+2 -> 818.204 | I81: =I78*I80 -> 794.30519 | J81: =J78*J80 -> 976.45205 | K81: =K78*K80 -> 976.45205 | L81: =L78*L80 -> 976.45205 | M81: =M78*M80 -> 976.45205 | N81: =N78*N80 -> 976.45205
A83: Slot Games | B83: Slot Handle | C83: 14527 | D83: 25566 | E83: 26226 | F83: 26850 | G83: 26894 | H83: 27161 | I83: =H83*(1+I75) -> 26346.17 | J83: =I83*(1+J75) -> 26873.093 | K83: =J83*(1+K75) -> 26873.093 | L83: =K83*(1+L75) -> 26873.093 | M83: =L83*(1+M75) -> 26873.093 | N83: =M83*(1+N75) -> 26873.093
B84: Slot Handle Growth% | C84: =(C83-25031)/25031 -> -0.41963965 | D84: =(D83-C83)/C83 -> 0.75989537 | E84: =(E83-D83)/D83 -> 0.025815536 | F84: =(F83-E83)/E83 -> 0.023793182 | G84: =(G83-F83)/F83 -> 0.0016387337 | H84: =(H83-G83)/G83 -> 0.009927865 | I84: =(I83-H83)/H83 -> -0.03 | J84: =(J83-I83)/I83 -> 0.02 | K84: =(K83-J83)/J83 -> 0 | ... N84: =(N83-M83)/M83 -> 0
B85: Slot Win% | C85: 0.097 | D85: 0.096 | E85: 0.095 | F85: 0.096 | G85: 0.099 | H85: 0.101 | I85: =AVERAGE(C85:H85) -> 0.097333333 | J85: =$I$20 -> 0.093666667 | K85: =$I$20 -> 0.093666667 | L85: =$I$20 -> 0.093666667 | M85: =$I$20 -> 0.093666667 | N85: =$I$20 -> 0.093666667
B86: Slot Win | C86: =C83*C85 -> 1409.119 | D86: =D83*D85 -> 2454.336 | E86: =E83*E85 -> 2491.47 | F86: =F83*F85 -> 2577.6 | G86: =G83*G85 -> 2662.506 | H86: =H83*H85 -> 2743.261 | I86: =I83*I85 -> 2564.3605 | J86: =J83*J85 -> 2517.1131 | ... N86: =N83*N85 -> 2517.1131
A88: Gaming Summary | B88: Total Handle | C88: =C78+C83 -> 16949 | D88: =D78+D83 -> 29546 | E88: =E78+E83 -> 30695 | F88: =F78+F83 -> 30736 | G88: =G78+G83 -> 30803 | H88: =H78+H83 -> 31162 | I88: =I78+I83 -> 30227.14 | J88: =J78+J83 -> 30831.683 | ... N88: =N78+N83 -> 30831.683
B89: Gross Gaming Win | C89: =C81+C86 -> 1895.941 | D89: =D81+D86 -> 3242.376 | E89: =E81+E86 -> 3424.491 | F89: =F81+F86 -> 3391.66 | G89: =G81+G86 -> 3469.76 | H89: =H81+H86 -> 3561.465 | I89: =I81+I86 -> 3358.6657 | J89: =J81+J86 -> 3493.5651 | ... N89: =N81+N86 -> 3493.5651
B90: Gaming Incentives (SSP Allocation) | C90: =C89-C93+173 -> 499.748 | D90: =D89-D93 -> 520.861 | E90: =E89-E93 -> 523.419 | F90: =F89-F93 -> 679.455 | G90: =G89-G93 -> 731.982 | H90: =H89-H93 -> 788.731 | I90: =H90*(1+I91) -> 765.06907 | J90: =I90*(1+J91) -> 780.37045 | K90: =J90*(1+K91) -> 780.37045 | L90: =K90*(1+L91) -> 780.37045 | M90: =L90*(1+M91) -> 780.37045 | N90: =M90*(1+N91) -> 780.37045
B91: Gaming Incentives Growth% | C91: =(C90-751)/751 -> -0.33455659 | D91: =(D90-C90)/C90 -> 0.042247293 | E91: =(E90-D90)/D90 -> 0.0049110991 | F91: =(F90-E90)/E90 -> 0.29810916 | G91: =(G90-F90)/F90 -> 0.077307548 | H91: =(H90-G90)/G90 -> 0.077527863 | I91: =I75 -> -0.03 | J91: =J75 -> 0.02 | K91: =K75 -> 0 | L91: =L75 -> 0 | M91: =M75 -> 0 | N91: =N75 -> 0
B92: Gaming Incentives (% of Gross Gaming Win) | C92: =C90/C89 -> 0.26358837 | D92: =D90/D89 -> 0.16064176 | E92: =E90/E89 -> 0.15284578 | F92: =F90/F89 -> 0.20033111 | G92: =G90/G89 -> 0.21096041 | H92: =H90/H89 -> 0.22146252 | I92: =I90/I89 -> 0.22778958 | J92: =J90/J89 -> 0.22337367 | ... N92: =N90/N89 -> 0.22337367
B93: Casino Revenue | C93: 1569.193 | D93: 2721.515 | E93: 2901.072 | F93: 2712.205 | G93: 2737.778 | H93: 2772.734 | I93: =I89-I90 -> 2593.5967 | J93: =J89-J90 -> 2713.1947 | K93: =K89-K90 -> 2713.1947 | L93: =L89-L90 -> 2713.1947 | M93: =M89-M90 -> 2713.1947 | N93: =N89-N90 -> 2713.1947
B94: Casino Revenue Growth% | C94: =(C93-1296)/1296 -> 0.21079707 | D94: =(D93-C93)/C93 -> 0.73434052 | E94: =(E93-D93)/D93 -> 0.065976855 | F94: =(F93-E93)/E93 -> -0.065102486 | G94: =(G93-F93)/F93 -> 0.0094288595 | H94: =(H93-G93)/G93 -> 0.012768018 | I94: =(I93-H93)/H93 -> -0.064606749 | J94: =(J93-I93)/I93 -> 0.046112803 | K94: =(K93-J93)/J93 -> 0 | ... N94: =(N93-M93)/M93 -> 0
A96: Analytics | B96: Total SSP Allocation | C96: =C90 -> 499.748 | D96: =D90 -> 520.861 | E96: =E90 -> 523.419 | F96: =F90 -> 679.455 | G96: =G90 -> 731.982 | H96: =H90 -> 788.731 | I96: =I90 -> 765.06907 | J96: =J90 -> 780.37045 | ... N96: =N90 -> 780.37045
B97: Rooms% of Regional Operations | C97: =C112/C125 -> 0.066565133 | D97: =D112/D125 -> 0.066805166 | E97: =E112/E125 -> 0.077423037 | F97: =F112/F125 -> 0.080674406 | G97: =G112/G125 -> 0.081799909 | H97: =H112/H125 -> 0.081636218 | I97: =I112/I125 -> 0.083834639 | J97: =J112/J125 -> 0.082301011 | ... N97: =N112/N125 -> 0.082301011
B98: SSP Allocation to Rooms | C98: =C96*C97 -> 33.265792 | D98: =D96*D97 -> 34.796206 | E98: =E96*E97 -> 40.524688 | F98: =F96*F97 -> 54.814629 | G98: =G96*G97 -> 59.876061 | H98: =H96*H97 -> 64.389016 | I98: =I96*I97 -> 64.139289 | J98: =J96*J97 -> 64.225277 | ... N98: =N96*N97 -> 64.225277
B99: F&B% of Regional Operations | C99: =C117/C125 -> 0.093613112 | D99: =D117/D125 -> 0.066807586 | E99: =E117/E125 -> 0.077423037 | F99: =F117/F125 -> 0.11988146 | G99: =G117/G125 -> 0.12260471 | H99: =H117/H125 -> 0.12235108 | I99: =I117/I125 -> 0.12564593 | J99: =J117/J125 -> 0.12334742 | ... N99: =N117/N125 -> 0.12334742
B100: SSP Allocation to Food and Beverage | C100: =C96*C99 -> 46.782966 | D100: =D96*D99 -> 34.797466 | E100: =E96*E99 -> 40.524688 | F100: =F96*F99 -> 81.454057 | G100: =G96*G99 -> 89.744441 | H100: =H96*H99 -> 96.502086 | I100: =I96*I99 -> 96.127812 | J100: =J96*J99 -> 96.256685 | ... N100: =N96*N99 -> 96.256685
B101: Entertainment% of Regional Operations | C101: =C122/C125 -> 0.042131569 | D101: =D122/D125 -> 0.04304126 | E101: =E122/E125 -> 0.054867049 | F101: =F122/F125 -> 0.060485915 | G101: =G122/G125 -> 0.059697252 | H101: =H122/H125 -> 0.06099435 | I101: =I122/I125 -> 0.062636896 | J101: =J122/J125 -> 0.061491049 | ... N101: =N122/N125 -> 0.061491049
B102: SSP Allocation to Entertainment | C102: =C96*C101 -> 21.055167 | D102: =D96*D101 -> 22.418514 | E102: =E96*E101 -> 28.718456 | F102: =F96*F101 -> 41.097458 | G102: =G96*G101 -> 43.697314 | H102: =H96*H101 -> 48.108135 | I102: =I96*I101 -> 47.921552 | J102: =J96*J101 -> 47.985798 | ... N102: =N96*N101 -> 47.985798
B104: Blend Hold% | C104: =C89/C88 -> 0.11186153 | D104: =D89/D88 -> 0.10973993 | E104: =E89/E88 -> 0.11156511 | F104: =F89/F88 -> 0.11034813 | G104: =G89/G88 -> 0.11264357 | H104: =H89/H88 -> 0.11428872 | I104: =I89/I88 -> 0.11111424 | J104: =J89/J88 -> 0.11331088 | ... N104: =N89/N88 -> 0.11331088
B105: Table Mix% | C105: =C81/C89 -> 0.25677065 | D105: =D81/D89 -> 0.24304399 | E105: =E81/E89 -> 0.27245538 | F105: =F81/F89 -> 0.24001816 | G105: =G81/G89 -> 0.23265413 | H105: =H81/H89 -> 0.22973804 | I105: =I81/I89 -> 0.23649427 | J105: =J81/J89 -> 0.27950017 | ... N105: =N81/N89 -> 0.27950017
B106: Slot Mix% | C106: =C86/C89 -> 0.74322935 | D106: =D86/D89 -> 0.75695601 | E106: =E86/E89 -> 0.72754462 | F106: =F86/F89 -> 0.75998184 | G106: =G86/G89 -> 0.76734587 | H106: =H86/H89 -> 0.77026196 | I106: =I86/I89 -> 0.76350573 | J106: =J86/J89 -> 0.72049983 | ... N106: =N86/N89 -> 0.72049983
B107: Net Monetization | C107: =C93/C89 -> 0.82765919 | D107: =D93/D89 -> 0.83935824 | E107: =E93/E89 -> 0.84715422 | F107: =F93/F89 -> 0.79966889 | G107: =G93/G89 -> 0.78903959 | H107: =H93/H89 -> 0.77853748 | I107: =I93/I89 -> 0.77221042 | J107: =J93/J89 -> 0.77662633 | ... N107: =N93/N89 -> 0.77662633
B108: Promo/SSP Rate | C108: =1-C107 -> 0.17234081 | D108: =1-D107 -> 0.16064176 | E108: =1-E107 -> 0.15284578 | F108: =1-F107 -> 0.20033111 | G108: =1-G107 -> 0.21096041 | H108: =1-H107 -> 0.22146252 | I108: =1-I107 -> 0.22778958 | J108: =1-J107 -> 0.22337367 | ... N108: =1-N107 -> 0.22337367
A110: Rooms
B111: Rooms Cash Revenue | C111: =C112-C98 -> 97.679208 | D111: =D112-D98 -> 186.02379 | E111: =E112-E98 -> 243.68831 | F111: =F112-F98 -> 241.28537 | G111: =G112-G98 -> 244.44594 | H111: =H112-H98 -> 243.56998 | I111: =I112-I98 -> 234.58094 | J111: =J112-J98 -> 240.46936 | ... N111: =N112-N98 -> 240.46936
B112: Rooms Total Revenue | C112: 130.945 | D112: 220.82 | E112: 284.213 | F112: 296.1 | G112: 304.322 | H112: 307.959 | I112: =H112*(1+I75) -> 298.72023 | J112: =I112*(1+J75) -> 304.69463 | K112: =J112*(1+K75) -> 304.69463 | L112: =K112*(1+L75) -> 304.69463 | M112: =L112*(1+M75) -> 304.69463 | N112: =M112*(1+N75) -> 304.69463
B113: Rooms Cash Revenue Growth% | C113: =(C112-316.753)/316.753 -> -0.58660218 | D113: =(D111-C111)/C111 -> 0.90443595 | E113: =(E111-D111)/D111 -> 0.30998463 | F113: =(F111-E111)/E111 -> -0.0098607123 | G113: =(G111-F111)/F111 -> 0.01309888 | H113: =(H111-G111)/G111 -> -0.0035834314 | I113: =(I111-H111)/H111 -> -0.036905381 | J113: =(J111-I111)/I111 -> 0.025101852 | K113: =(K111-J111)/J111 -> 0 | ... N113: =(N111-M111)/M111 -> 0
A115: Food and Beverage
B116: Food and Beverage Cash Revenue | C116: =C117-C100 -> 137.37003 | D116: =D117-D100 -> 186.03053 | E116: =E117-E100 -> 243.68831 | F116: =F117-F100 -> 358.54794 | G116: =G117-G100 -> 366.38456 | H116: =H117-H100 -> 365.04691 | I116: =I117-I100 -> 351.57472 | J116: =J117-J100 -> 360.3999 | ... N116: =N117-N100 -> 360.3999
...

Sheet Downside MGM IS
A1: Owen Purnomo
A2: MGM
A3: NYSE: MGM
A4: Downside Case Income Statement | B4: 2020 | C4: 2021 | D4: 2022 | E4: 2023 | F4: 2024 | G4: 2025 | H4: 2026 | I4: 2027 | J4: 2028 | K4: 2029 | L4: 2030 | M4: 2031
A5: Las Vegas Strip Resorts Revenue | B5: ='Base Revenue Driver'!C67 -> 2131.1673 | C5: ='Base Revenue Driver'!D67 -> 4597.9596 | D5: ='Base Revenue Driver'!E67 -> 8126.7461 | E5: ='Base Revenue Driver'!F67 -> 8767.2913 | F5: ='Base Revenue Driver'!G67 -> 8785.42 | G5: ='Base Revenue Driver'!H67 -> 8405.3474 | H5: ='Downside Revenue Driver'!I67 -> 7754.1118 | I5: ='Downside Revenue Driver'!J67 -> 7647.0297 | J5: ='Downside Revenue Driver'!K67 -> 7698.2506 | K5: ='Downside Revenue Driver'!L67 -> 7788.6408 | L5: ='Downside Revenue Driver'!M67 -> 7841.9309 | M5: ='Downside Revenue Driver'!N67 -> 7896.2869
A6: Regional Operations Revenue | B6: ='Base Revenue Driver'!C125 -> 1967.171 | C6: ='Base Revenue Driver'!D125 -> 3305.433 | D6: ='Base Revenue Driver'!E125 -> 3670.91 | E6: ='Base Revenue Driver'!F125 -> 3670.309 | F6: ='Base Revenue Driver'!G125 -> 3720.322 | G6: ='Base Revenue Driver'!H125 -> 3772.333 | H6: ='Downside Revenue Driver'!I125 -> 3563.2077 | I6: ='Downside Revenue Driver'!J125 -> 3702.1979 | J6: ='Downside Revenue Driver'!K125 -> 3702.1979 | K6: ='Downside Revenue Driver'!L125 -> 3702.1979 | L6: ='Downside Revenue Driver'!M125 -> 3702.1979 | M6: ='Downside Revenue Driver'!N125 -> 3702.1979
A7: MGM China Revenue | B7: ='Base Revenue Driver'!C176 -> 656.703 | C7: ='Base Revenue Driver'!D176 -> 1210.761 | D7: ='Base Revenue Driver'!E176 -> 673.593 | E7: ='Base Revenue Driver'!F176 -> 3153.609 | F7: ='Base Revenue Driver'!G176 -> 4022.384 | G7: ='Base Revenue Driver'!H176 -> 4461.743 | H7: ='Downside Revenue Driver'!I176 -> 3917.7129 | I7: ='Downside Revenue Driver'!J176 -> 4010.4553 | J7: ='Downside Revenue Driver'!K176 -> 3870.0894 | K7: ='Downside Revenue Driver'!L176 -> 3734.6363 | L7: ='Downside Revenue Driver'!M176 -> 3603.924 | M7: ='Downside Revenue Driver'!N176 -> 3477.7867
A8: MGM Digital Revenue | B8: ='Base Revenue Driver'!C190 -> 0 | C8: ='Base Revenue Driver'!D190 -> 0 | D8: ='Base Revenue Driver'!E190 -> 0 | E8: ='Base Revenue Driver'!F190 -> 432.146 | F8: ='Base Revenue Driver'!G190 -> 552.012 | G8: ='Base Revenue Driver'!H190 -> 654.19 | H8: ='Downside Revenue Driver'!I190 -> 667.2738 | I8: ='Downside Revenue Driver'!J190 -> 680.61928 | J8: ='Downside Revenue Driver'!K190 -> 694.23166 | K8: ='Downside Revenue Driver'!L190 -> 708.11629 | L8: ='Downside Revenue Driver'!M190 -> 722.27862 | M8: ='Downside Revenue Driver'!N190 -> 736.72419
A9: Total Revenue | B9: =SUM(B5:B7) -> 4755.0413 | C9: =SUM(C5:C7) -> 9114.1536 | D9: =SUM(D5:D7) -> 12471.249 | E9: =SUM(E5:E7) -> 15591.209 | F9: =SUM(F5:F7) -> 16528.126 | G9: =SUM(G5:G7) -> 16639.423 | H9: =SUM(H5:H7) -> 15235.032 | I9: =SUM(I5:I7) -> 15359.683 | ... M9: =SUM(M5:M7) -> 15076.271
A10: Grotwh Rate | B10: =(B9/28590)-1 -> -0.83368166 | C10: =(C9/B9)-1 -> 0.91673491 | D10: =(D9/C9)-1 -> 0.3683387 | E10: =(E9/D9)-1 -> 0.25017223 | F10: =(F9/E9)-1 -> 0.060092622 | G10: =(G9/F9)-1 -> 0.006733821 | H10: =(H9/G9)-1 -> -0.084401421 | I10: =(I9/H9)-1 -> 0.0081818392 | J10: =(J9/I9)-1 -> -0.0058038365 | ... M10: =(M9/L9)-1 -> -0.004738653
A12: Las Vegas Strip EBIT | B12: ='Base Revenue Driver'!C70 -> -628.89426 | C12: ='Base Revenue Driver'!D70 -> 2141.5255 | D12: ='Base Revenue Driver'!E70 -> -349.61576 | E12: ='Base Revenue Driver'!F70 -> 1506.4587 | F12: ='Base Revenue Driver'!G70 -> 1517.5912 | G12: ='Base Revenue Driver'!H70 -> 1265.5169 | H12: ='Downside Revenue Driver'!I70 -> 775.41118 | I12: ='Downside Revenue Driver'!J70 -> 841.17327 | J12: ='Downside Revenue Driver'!K70 -> 923.79007 | K12: ='Downside Revenue Driver'!L70 -> 934.63689 | L12: ='Downside Revenue Driver'!M70 -> 941.03171 | M12: ='Downside Revenue Driver'!N70 -> 947.55443
A13: Regional Operations EBIT | B13: ='Base Revenue Driver'!C128 -> -450.83079 | C13: ='Base Revenue Driver'!D128 -> 498.36023 | D13: ='Base Revenue Driver'!E128 -> 388.68688 | E13: ='Base Revenue Driver'!F128 -> 428.20055 | F13: ='Base Revenue Driver'!G128 -> 470.6898 | G13: ='Base Revenue Driver'!H128 -> 448.5751 | H13: ='Downside Revenue Driver'!I128 -> 249.42454 | I13: ='Downside Revenue Driver'!J128 -> 296.17583 | J13: ='Downside Revenue Driver'!K128 -> 333.19781 | K13: ='Downside Revenue Driver'!L128 -> 333.19781 | L13: ='Downside Revenue Driver'!M128 -> 333.19781 | M13: ='Downside Revenue Driver'!N128 -> 333.19781
A14: MGM China EBIT | B14: ='Base Revenue Driver'!C179 -> -459.16795 | C14: ='Base Revenue Driver'!D179 -> -238.16476 | D14: ='Base Revenue Driver'!E179 -> -369.37188 | E14: ='Base Revenue Driver'!F179 -> 261.14164 | F14: ='Base Revenue Driver'!G179 -> 359.62815 | G14: ='Base Revenue Driver'!H179 -> 357.93641 | H14: ='Downside Revenue Driver'!I179 -> 156.70852 | I14: ='Base Revenue Driver'!J179 -> 395.93834 | J14: ='Base Revenue Driver'!K179 -> 415.73525 | K14: ='Base Revenue Driver'!L179 -> 436.52202 | L14: ='Base Revenue Driver'!M179 -> 458.34812 | M14: ='Base Revenue Driver'!N179 -> 481.26552
A15: MGM Digital EBIT | B15: ='Base Revenue Driver'!C193 -> 0 | C15: ='Base Revenue Driver'!D193 -> 0 | D15: ='Base Revenue Driver'!E193 -> 0 | E15: ='Base Revenue Driver'!F193 -> -115.4309 | F15: ='Base Revenue Driver'!G193 -> -177.06519 | G15: ='Base Revenue Driver'!H193 -> -214.24042 | H15: ='Base Revenue Driver'!I193 -> -109.41328 | I15: ='Base Revenue Driver'!J193 -> -73.197483 | ... M15: ='Base Revenue Driver'!N193 -> 50.282064
A16: Corporate Expense | B16: ='Base Revenue Driver'!C196 -> 896 | C16: ='Base Revenue Driver'!D196 -> -123.022 | D16: ='Base Revenue Driver'!E196 -> 1769.67 | E16: ='Base Revenue Driver'!F196 -> -189 | F16: ='Base Revenue Driver'!G196 -> -680 | G16: ='Base Revenue Driver'!H196 -> -856 | H16: ='Downside Revenue Driver'!I193 -> -133.45476 | I16: ='Downside Revenue Driver'!J193 -> -102.09289 | J16: ='Downside Revenue Driver'!K193 -> -48.596216 | K16: ='Downside Revenue Driver'!L193 -> 14.162326 | L16: ='Downside Revenue Driver'!M193 -> 21.668359 | M16: ='Downside Revenue Driver'!N193 -> 29.468968
A17: Total EBIT | B17: =SUM(B12:B16) -> -642.893 | C17: =SUM(C12:C16) -> 2278.699 | D17: =SUM(D12:D16) -> 1439.3692 | E17: =SUM(E12:E16) -> 1891.37 | F17: =SUM(F12:F16) -> 1490.844 | G17: =SUM(G12:G16) -> 1001.788 | H17: =SUM(H12:H16) -> 938.6762 | I17: =SUM(I12:I16) -> 1357.9971 | ... M17: =SUM(M12:M16) -> 1841.7688
A18: Adjusted EBIT | B18: ='Base Revenue Driver'!C200 -> -538.893 | C18: ='Base Revenue Driver'!D200 -> 784.699 | D18: ='Base Revenue Driver'!E200 -> 369.36924 | E18: ='Base Revenue Driver'!F200 -> 1492.37 | F18: ='Base Revenue Driver'!G200 -> 1490.844 | G18: ='Base Revenue Driver'!H200 -> 1373.788 | H18: ='Base Revenue Driver'!I200 -> 1315.6436 | I18: ='Base Revenue Driver'!J200 -> 1456.8327 | ... M18: ='Base Revenue Driver'!N200 -> 1912.7614
A20: Interest Expense | B20: 676.38 | C20: 799.593 | D20: 594.954 | E20: 460.293 | F20: 443.23 | G20: 419.042 | H20: =AVERAGE(E20:G20) -> 440.855 | I20: =$H$20 -> 440.855 | J20: =$H$20 -> 440.855 | K20: =$H$20 -> 440.855 | L20: =$H$20 -> 440.855 | M20: =$H$20 -> 440.855
A21: Non-operating items from unconsolidated affiliates | B21: -103.304 | C21: -83.243 | D21: -23.457 | E21: -1.032 | F21: -0.734 | G21: 1.135 | H21: 0 | I21: 0 | J21: 0 | K21: 0 | L21: 0 | M21: 0
A22: Other, net | B22: -89.361 | C22: 65.941 | D22: 82.838 | E22: 42.591 | F22: 70.573 | G22: -303.094 | H22: 0 | I22: 0 | J22: 0 | K22: 0 | L22: 0 | M22: 0
A23: Pre-Tax Income | B23: =B18-B20+B21+B22 -> -1407.938 | C23: =C18-C20+C21+C22 -> -32.196 | D23: =D18-D20+D21+D22 -> -166.20376 | E23: =E18-E20+E21+E22 -> 1073.636 | F23: =F18-F20+F21+F22 -> 1117.453 | G23: =G18-G20+G21+G22 -> 652.787 | H23: =H18-H20+H21+H22 -> 874.78856 | I23: =I18-I20+I21+I22 -> 1015.9777 | ... M23: =M18-M20+M21+M22 -> 1471.9064
A24: Tax Benefit | B24: 191.572 | C24: -253.415 | D24: -697.068 | E24: -157.839 | F24: -52.457 | G24: 240.093 | H24: =0 -> 0 | I24: =H24 -> 0 | J24: =I24 -> 0 | K24: =J24 -> 0 | L24: =K24 -> 0 | M24: =L24 -> 0
A25: Net income attributable to noncontrolling interests | B25: 287.183 | C25: 45.981 | D25: 1266.362 | E25: -172.744 | F25: -318.05 | G25: =-315.01 -> -315.01 | H25: 0 | I25: 0 | J25: 0 | K25: 0 | L25: 0 | M25: 0
A27: Adjusted Net Income | B27: =B23+B24+B25 -> -929.183 | C27: =C23+C24+C25 -> -239.63 | D27: =D23+D24+D25 -> 403.09024 | E27: =E23+E24+E25 -> 743.053 | F27: =F23+F24+F25 -> 746.946 | G27: =G23+G24+G25 -> 577.87 | H27: =H23+H24+H25 -> 874.78856 | I27: =I23+I24+I25 -> 1015.9777 | ... M27: =M23+M24+M25 -> 1471.9064
A29: Depreciation & Amort. | B29: 1210.556 | C29: 1150.61 | D29: 3482.05 | E29: 814.128 | F29: 831.097 | G29: 1017.794 | H29: =+G29*(1+H10) -> 931.89074 | I29: =+H29*(1+I10) -> 939.51532 | J29: =+I29*(1+J10) -> 934.06253 | K29: =+J29*(1+K10) -> 931.30613 | L29: =+K29*(1+L10) -> 926.57041 | M29: =+L29*(1+M10) -> 922.17971
A30: Adjusted EBITDA | B30: =B29+B18 -> 671.663 | C30: =C29+C18 -> 1935.309 | D30: =D29+D18 -> 3851.4192 | E30: =E29+E18 -> 2306.498 | F30: =F29+F18 -> 2321.941 | G30: =G29+G18 -> 2391.582 | H30: =H29+H18 -> 2247.5343 | I30: =I29+I18 -> 2396.348 | ... M30: =M29+M18 -> 2834.9411
A31: EBITDA Margin | B31: =B30/B9 -> 0.14125282 | C31: =C30/C9 -> 0.21234106 | D31: =D30/D9 -> 0.30882386 | E31: =E30/E9 -> 0.1479358 | F31: =F30/F9 -> 0.14048423 | G31: =G30/G9 -> 0.14372986 | H31: =H30/H9 -> 0.14752409 | I31: =I30/I9 -> 0.15601546 | ... M31: =M30/M9 -> 0.18803993
A32: Cash Interest | B32: =B53*B50 -> 816.8655 | C32: =C53*C50 -> 741.56418 | D32: =D53*D50 -> 494.82326 | E32: =E53*E50 -> 445.97262 | F32: =F53*F50 -> 343.55621 | G32: =G53*G50 -> 373.81206 | H32: =H53*H50 -> 293.00692 | I32: =I53*I50 -> 218.0786 | ... M32: =M53*M50 -> 142.87262
A33: Capex | B33: 271 | C33: 491 | D33: 765 | E33: 932 | F33: 1200 | G33: =1100 -> 1100 | H33: =1050 -> 1050 | I33: =$H$33 -> 1050 | J33: =$H$33 -> 1050 | K33: =$H$33 -> 1050 | L33: =$H$33 -> 1050 | M33: =$H$33 -> 1050
A34: Cash Taxes | B34: =B20 -> 676.38 | C34: =C20 -> 799.593 | D34: =D20 -> 594.954 | E34: =E20 -> 460.293 | F34: =F20 -> 443.23 | G34: =G20 -> 419.042 | H34: =H20 -> 440.855 | I34: =I20 -> 440.855 | ... M34: =M20 -> 440.855
A35: FCF | B35: =B30-B32-B33-B34 -> -1092.5825 | C35: =C30-C32-C33-C34 -> -96.84818 | D35: =D30-D32-D33-D34 -> 1996.642 | E35: =E30-E32-E33-E34 -> 468.23238 | F35: =F30-F32-F33-F34 -> 335.15479 | G35: =G30-G32-G33-G34 -> 498.72794 | H35: =H30-H32-H33-H34 -> 463.67239 | I35: =I30-I32-I33-I34 -> 687.4144 | ... M35: =M30-M32-M33-M34 -> 1201.2135
A36: Maintence Capex (60%)
A37: Operating Cash before maturities
A39: Lease Expense | B39: 751.002 | C39: 870.779 | D39: 1986.853 | E39: 2306.64 | F39: 2300.373 | G39: =F39*(1+G10) -> 2315.8633 | H39: =G39*(1+H10) -> 2120.4011 | I39: =H39*(1+I10) -> 2137.7499 | J39: =I39*(1+J10) -> 2125.3428 | K39: =J39*(1+K10) -> 2119.0709 | L39: =K39*(1+L10) -> 2108.2954 | M39: =L39*(1+M10) -> 2098.3049
A41: Credit Matrix
A42: EBIT/Interest | B42: =B18/B20 -> -0.79673113 | C42: =C18/C20 -> 0.98137302 | D42: =D18/D20 -> 0.62083663 | E42: =E18/E20 -> 3.2422175 | F42: =F18/F20 -> 3.36359 | G42: =G18/G20 -> 3.2784017 | H42: =H18/H20 -> 2.9843 | I42: =I18/I20 -> 3.304562 | ... M42: =M18/M20 -> 4.3387539
A43: EBITDA/Interest | B43: =B30/B20 -> 0.99302611 | C43: =C30/C20 -> 2.4203676 | D43: =D30/D20 -> 6.473474 | E43: =E30/E20 -> 5.0109343 | F43: =F30/F20 -> 5.2386819 | G43: =G30/G20 -> 5.7072608 | H43: =H30/H20 -> 5.0981259 | I43: =I30/I20 -> 5.4356829 | ... M43: =M30/M20 -> 6.4305522
A44: (EBITDA - CAPEX)/Interest | B44: =(B30-B33)/B20 -> 0.59236376 | C44: =(C30-C33)/C20 -> 1.8063052 | D44: =(D30-D33)/D20 -> 5.1876603 | E44: =(E30-E33)/E20 -> 2.9861371 | F44: =(F30-F33)/F20 -> 2.531284 | G44: =(G30-G33)/G20 -> 3.0822256 | H44: =(H30-H33)/H20 -> 2.7163904 | I44: =(I30-I33)/I20 -> 3.0539474 | ... M44: =(M30-M33)/M20 -> 4.0488167
A45: Gross Debt/EBITDAR | B45: =B53/(B30+B39) -> 8.6996939 | C45: =C53/(C30+C39) -> 4.194758 | D45: =D53/(D30+D39) -> 1.0866037 | E45: =E53/(E30+E39) -> 1.611241 | F45: =F53/(F30+F39) -> 1.3763998 | G45: =G53/(G30+G39) -> 1.3234782 | H45: =H53/(H30+H39) -> 1.2422468 | I45: =I53/(I30+I39) -> 0.94308748 | ... M45: =M53/(M30+M39) -> 0.4258997
A46: Adjusted Debt/EBITDAR | B46: =B59/(B30+B39) -> 14.597159 | C46: =C59/(C30+C39) -> 8.4007786 | D46: =D59/(D30+D39) -> 5.3942649 | E46: =E59/(E30+E39) -> 7.0581762 | F46: =F59/(F30+F39) -> 6.8014183 | G46: =G59/(G30+G39) -> 6.6262996 | H46: =H59/(H30+H39) -> 6.978469 | I46: =I59/(I30+I39) -> 6.4637982 | ... M46: =M59/(M30+M39) -> 5.4988619
A47: FCF/ Debt | B47: =B35/B59 -> -0.052611812 | C47: =C35/C59 -> -0.0041083803 | D47: =D35/D59 -> 0.063399172 | E47: =E35/E59 -> 0.014380451 | F47: =F35/F59 -> 0.010660719 | G47: =G35/G59 -> 0.015988486 | H47: =H35/H59 -> 0.015211599 | I47: =I35/I59 -> 0.023455243 | ... M47: =M35/M59 -> 0.044280712
A49: Note 8 & 9: Debt & Leases
A50: Interest Rate | B50: 0.066 | C50: 0.063 | D50: 0.078 | E50: 0.06 | F50: 0.054 | G50: 0.06 | H50: 0.054 | I50: 0.051 | J50: 0.048 | K50: 0.061 | L50: 0.049 | M50: 0.068
A51: Long Term Notes | B51: 12376.684 | C51: 11770.797 | D51: 6343.81 | E51: 7432.817 | F51: 6362.098 | G51: 6230.141 | H51: 5426 | I51: =H51-'MGM Bond'!D6-'MGM Bond'!D7 -> 4276 | J51: =I51-'MGM Bond'!D8-'MGM Bond'!D9 -> 2851 | K51: =J51-'MGM Bond'!D10 -> 2101 | L51: =K51 -> 2101 | M51: =L51 -> 2101
A52: Short Term Debt | B52: 0 | C52: 0 | D52: 0 | E52: 0 | F52: 0 | G52: 0 | H52: 0 | I52: 0 | J52: 0 | K52: 0 | L52: 0 | M52: 0
A53: Total Debt | B53: =SUM(B50:B52) -> 12376.75 | C53: =SUM(C50:C52) -> 11770.86 | D53: =SUM(D50:D52) -> 6343.888 | E53: =SUM(E50:E52) -> 7432.877 | F53: =SUM(F50:F52) -> 6362.152 | G53: =SUM(G50:G52) -> 6230.201 | H53: =SUM(H50:H52) -> 5426.054 | I53: =SUM(I50:I52) -> 4276.051 | ... M53: =SUM(M50:M52) -> 2101.068
A54: Total Purchase Obligations 2025 onwards
A55: Operating Leases | B55: 8390.117 | C55: 11802.464 | D55: 25149.299 | E55: 25127.464 | F55: 25076.139 | G55: 24962.742 | H55: =AVERAGE(E55:G55) -> 25055.448 | I55: =AVERAGE(F55:H55) -> 25031.443 | J55: =AVERAGE(G55:I55) -> 25016.544 | K55: =AVERAGE(H55:J55) -> 25034.479 | L55: =AVERAGE(I55:K55) -> 25027.489 | M55: =AVERAGE(J55:L55) -> 25026.171
A57: Unfunded Pensions | B57: 0 | C57: 0 | D57: 0 | E57: 0 | F57: 0 | G57: 0 | H57: 0 | I57: 0 | J57: 0 | K57: 0 | L57: 0 | M57: 0
A59: Adjusted Leverage | B59: =B53+B55+B57 -> 20766.867 | C59: =C53+C55+C57 -> 23573.324 | D59: =D53+D55+D57 -> 31493.187 | E59: =E53+E55+E57 -> 32560.341 | F59: =F53+F55+F57 -> 31438.291 | G59: =G53+G55+G57 -> 31192.943 | H59: =H53+H55+H57 -> 30481.502 | I59: =I53+I55+I57 -> 29307.494 | ... M59: =M53+M55+M57 -> 27127.239

Sheet MGM Bond
A1: Owen Purnomo
A2: Paramount
A3: NYSE: MGM
A5: Instrument | B5: Coupon (%) | C5: Maturity | D5: Carrying Value ($mm)
A6: Senior Notes | B6: 4 | C6: 2026 | D6: 750 | F6: MGM Resorts International 6.5% | H6: CUSIP: 552953CJ8 | J6: Ratings: B+/B1/BB-
A7: Senior Notes | B7: 3.7 | C7: 2026 | D7: 400 | F7: Coupon | G7: 0.065 | H7: Today | I7: 46115 | J7: Current Spread & Duration:
A8: Senior Notes | B8: 2.9 | C8: 2027 | D8: 675 | F8: Current Price | G8: 101.37 | H8: Maturity: | I8: 48349 | J8: =(I9-G9)*10000 -> 187.1
A9: Senior Notes | B9: 3.375 | C9: 2027 | D9: 750 | F9: 10 Year T-Yield: | G9: 0.04345 | H9: Current Yield: | I9: 0.06216 | J9: =DURATION(I7,I8,G7,G9,2,0) -> 5.0917935
A10: Senior Notes | B10: 3.7 | C10: 2028 | D10: 750 | F10: Scenario | G10: Spreads | H10: Price | I10: Coupon | J10: 1Y Total Returns
A11: Senior Notes | B11: 4.2 | C11: 2029 | D11: 850 | F11: Upside | G11: 160 | H11: =PRICE($I$7,$I$8,$G$7,($G$9+G11/10000),100,2,0) -> 102.80298 | I11: 6.5 | J11: =(H11-$G$8+I11)/$G$8 -> 0.07825769
A12: Senior Notes | B12: 7.875 | C12: 2031 | D12: 500 | F12: Base | G12: =J8 -> 187.1 | H12: =PRICE($I$7,$I$8,$G$7,($G$9+G12/10000),100,2,0) -> 101.418 | I12: 6.5 | J12: =(H12-$G$8+I12)/$G$8 -> 0.064595014
A13: Senior Notes | B13: 4.95 | C13: 2032 | D13: 750 | F13: Downside | G13: 350 | H13: =PRICE($I$7,$I$8,$G$7,($G$9+G13/10000),100,2,0) -> 93.552273 | I13: 6.5 | J13: =(H13-$G$8+I13)/$G$8 -> -0.012999182
A14: Senior Debentures | B14: 4.2 | C14: 2036 | D14: 0.552 | F14: Downside^2 | G14: 600 | H14: =PRICE($I$7,$I$8,$G$7,($G$9+G14/10000),100,2,0) -> 82.872852 | I14: 6.5 | J14: =(H14-$G$8+I14)/$G$8 -> -0.11835009
B15: 5.5
A16: Due By 2032 | D16: =SUM(D6:D13) -> 5425
A17: Total Debt | D17: =SUM(D6:D14)-30.2 -> 5395.352 | F17: Liquidity Sources | G17: Amount Outstadning | H17: Maturity
F18: Cash | G18: 1500 | H18: -
B19: 5.9 | F19: MGM China Cash | G19: 565 | H19: -
B20: 4.5 | F20: Operating Cash | G20: ='Base MGM IS'!G36 -> 1357.7699 | H20: -
B21: 4.85 | F21: MGM China Revoler | G21: 2512 | H21: -
B22: 4.375 | F22: Revolver (Undrawn) | G22: 2300 | H22: 2028
B23: 4.875 | F23: Yen Credit Facility | G23: 87 | H23: -
B24: 5.85 | F24: Total Liquidity | G24: =G18+G19+G20+G22+G23+G21 -> 8321.7699 | H24: -
B25: 5.25 | F25: Capital Structure
B26: 4.9 | F26: Senior Unsecured | G26: =SUM(D6:D14) -> 5425.552 | H26: 2026 to 2036
B27: 4.6 | F27: Equity | G27: 9440 | H27: -
B28: 4.95 | F28: Total Cushion | G28: =G27 -> 9440 | H28: -
B29: 6.25
B30: 6.375

Sheet Graphs & Tables
A1: Owen Purnomo
B4: MGM | C4: 2020 | D4: 2021 | E4: 2022 | F4: 2023 | G4: 2024 | H4: 2025 | I4: 2026 | J4: 2027 | K4: 2028 | L4: 2029 | M4: 2030 | N4: 2031
B5: Las Vegas Strip Revenue | C5: ='Base MGM IS'!B5 -> 2131.1673 | D5: ='Base MGM IS'!C5 -> 4597.9596 | E5: ='Base MGM IS'!D5 -> 8126.7461 | F5: ='Base MGM IS'!E5 -> 8767.2913 | G5: ='Base MGM IS'!F5 -> 8785.42 | H5: ='Base MGM IS'!G5 -> 8405.3474 | I5: ='Base MGM IS'!H5 -> 8371.5237 | J5: ='Base MGM IS'!I5 -> 8649.8911 | ... N5: ='Base MGM IS'!M5 -> 9786.3801
B6: Regional Operations Revenue | C6: ='Base MGM IS'!B6 -> 1967.171 | D6: ='Base MGM IS'!C6 -> 3305.433 | E6: ='Base MGM IS'!D6 -> 3670.91 | F6: ='Base MGM IS'!E6 -> 3670.309 | G6: ='Base MGM IS'!F6 -> 3720.322 | H6: ='Base MGM IS'!G6 -> 3772.333 | I6: ='Base MGM IS'!H6 -> 3746.8782 | J6: ='Base MGM IS'!I6 -> 3931.1999 | ... N6: ='Base MGM IS'!M6 -> 4424.6001
B7: MGM China Revenue | C7: ='Base MGM IS'!B7 -> 656.703 | D7: ='Base MGM IS'!C7 -> 1210.761 | E7: ='Base MGM IS'!D7 -> 673.593 | F7: ='Base MGM IS'!E7 -> 3153.609 | G7: ='Base MGM IS'!F7 -> 4022.384 | H7: ='Base MGM IS'!G7 -> 4461.743 | I7: ='Base MGM IS'!H7 -> 4268.2451 | J7: ='Base MGM IS'!I7 -> 4705.3844 | ... N7: ='Base MGM IS'!M7 -> 5719.4242
B8: MGM Digital Revenue | C8: ='Base MGM IS'!B8 -> 0 | D8: ='Base MGM IS'!C8 -> 0 | E8: ='Base MGM IS'!D8 -> 0 | F8: ='Base MGM IS'!E8 -> 432.146 | G8: ='Base MGM IS'!F8 -> 552.012 | H8: ='Base MGM IS'!G8 -> 654.19 | I8: ='Base MGM IS'!H8 -> 729.42185 | J8: ='Base MGM IS'!I8 -> 813.30536 | ... N8: ='Base MGM IS'!M8 -> 1257.0516
B9: Total Revenue | C9: =SUM(C5:C8) -> 4755.0413 | D9: =SUM(D5:D8) -> 9114.1536 | E9: =SUM(E5:E8) -> 12471.249 | F9: =SUM(F5:F8) -> 16023.355 | G9: =SUM(G5:G8) -> 17080.138 | H9: =SUM(H5:H8) -> 17293.613 | I9: =SUM(I5:I8) -> 17116.069 | J9: =SUM(J5:J8) -> 18099.781 | ... N9: =SUM(N5:N8) -> 21187.456
B10: Adjusted EBITDA | C10: ='Base MGM IS'!B29 -> 671.663 | D10: ='Base MGM IS'!C29 -> 1935.309 | E10: ='Base MGM IS'!D29 -> 3851.4192 | F10: ='Base MGM IS'!E29 -> 2306.498 | G10: ='Base MGM IS'!F29 -> 2321.941 | H10: ='Base MGM IS'!G29 -> 2391.582 | I10: ='Base MGM IS'!H29 -> 2317.9758 | J10: ='Base MGM IS'!I29 -> 2514.2053 | ... N10: ='Base MGM IS'!M29 -> 3131.8569
B11: Adjusted EBIT | C11: ='Base MGM IS'!B18 -> -538.893 | D11: ='Base MGM IS'!C18 -> 784.699 | E11: ='Base MGM IS'!D18 -> 369.36924 | F11: ='Base MGM IS'!E18 -> 1492.37 | G11: ='Base MGM IS'!F18 -> 1490.844 | H11: ='Base MGM IS'!G18 -> 1373.788 | I11: ='Base MGM IS'!H18 -> 1315.6436 | J11: ='Base MGM IS'!I18 -> 1456.8327 | ... N11: ='Base MGM IS'!M18 -> 1912.7614
B12: Net Income | C12: ='Base MGM IS'!B26 -> -929.183 | D12: ='Base MGM IS'!C26 -> -239.63 | E12: ='Base MGM IS'!D26 -> 403.09024 | F12: ='Base MGM IS'!E26 -> 743.053 | G12: ='Base MGM IS'!F26 -> 746.946 | H12: ='Base MGM IS'!G26 -> 577.87 | I12: ='Base MGM IS'!H26 -> 874.78856 | J12: ='Base MGM IS'!I26 -> 1015.9777 | ... N12: ='Base MGM IS'!M26 -> 1471.9064
B14: Percentage of Revenue | C14: 2020 | D14: 2021 | E14: 2022 | F14: 2023 | G14: 2024 | H14: 2025 | I14: 2026 | J14: 2027 | K14: 2028 | L14: 2029 | M14: 2030 | N14: 2031
B15: Las Vegas Strip | C15: =C5/C9 -> 0.44819112 | D15: =D5/D9 -> 0.50448564 | E15: =E5/E9 -> 0.6516385 | F15: =F5/F9 -> 0.54715702 | G15: =G5/G9 -> 0.5143647 | H15: =H5/H9 -> 0.48603766 | I15: =I5/I9 -> 0.48910318 | J15: =J5/J9 -> 0.47790032 | ... N15: =N5/N9 -> 0.46189501
B16: Regional Operations | C16: =C6/C9 -> 0.41370219 | D16: =D6/D9 -> 0.36267032 | E16: =E6/E9 -> 0.29434983 | F16: =F6/F9 -> 0.22905995 | G16: =G6/G9 -> 0.21781569 | H16: =H6/H9 -> 0.21813446 | I16: =I6/I9 -> 0.21890997 | J16: =J6/J9 -> 0.21719599 | ... N16: =N6/N9 -> 0.20883112
B17: MGM China | C17: =C7/C9 -> 0.13810669 | D17: =D7/D9 -> 0.13284404 | E17: =E7/E9 -> 0.054011671 | F17: =F7/F9 -> 0.19681327 | G17: =G7/G9 -> 0.23550067 | H17: =H7/H9 -> 0.25799946 | I17: =I7/I9 -> 0.24937064 | J17: =J7/J9 -> 0.25996914 | ... N17: =N7/N9 -> 0.26994389
B18: MGM Digital | C18: =C8/C9 -> 0 | D18: =D8/D9 -> 0 | E18: =E8/E9 -> 0 | F18: =F8/F9 -> 0.026969757 | G18: =G8/G9 -> 0.032318943 | H18: =H8/H9 -> 0.037828416 | I18: =I8/I9 -> 0.042616202 | J18: =J8/J9 -> 0.044934542 | ... N18: =N8/N9 -> 0.059329992
B19: EBITDA Margin | C19: =C10/C9 -> 0.14125282 | D19: =D10/D9 -> 0.21234106 | E19: =E10/E9 -> 0.30882386 | F19: =F10/F9 -> 0.14394601 | G19: =G10/G9 -> 0.13594393 | H19: =H10/H9 -> 0.13829279 | I19: =I10/I9 -> 0.13542688 | J19: =J10/J9 -> 0.13890805 | ... N19: =N10/N9 -> 0.14781656
B20: EBIT Margin | C20: =C11/C9 -> -0.11333088 | D20: =D11/D9 -> 0.086096749 | E20: =E11/E9 -> 0.029617662 | F20: =F11/F9 -> 0.093137172 | G20: =G11/G9 -> 0.087285243 | H20: =H11/H9 -> 0.079439037 | I20: =I11/I9 -> 0.076865989 | J20: =J11/J9 -> 0.080488969 | ... N20: =N11/N9 -> 0.09027801
B21: Net Income | C21: =C12/C9 -> -0.19541008 | D21: =D12/D9 -> -0.026292074 | E21: =E12/E9 -> 0.032321561 | F21: =F12/F9 -> 0.046373121 | G21: =G12/G9 -> 0.043731848 | H21: =H12/H9 -> 0.033415226 | I21: =I12/I9 -> 0.051109199 | J21: =J12/J9 -> 0.056132044 | ... N21: =N12/N9 -> 0.069470651
B23: MGM Segement | C23: 2020 | D23: 2021 | E23: 2022 | F23: 2023 | G23: 2024 | H23: 2025 | I23: 2026 | J23: 2027 | K23: 2028 | L23: 2029 | M23: 2030 | N23: 2031
B24: =B15 -> Las Vegas Strip | C24: =C15 -> 0.44819112 | D24: =D15 -> 0.50448564 | E24: =E15 -> 0.6516385 | F24: =F15 -> 0.54715702 | G24: =G15 -> 0.5143647 | H24: =H15 -> 0.48603766 | I24: =I15 -> 0.48910318 | ... N24: =N15 -> 0.46189501
B25: =B16 -> Regional Operations | C25: =C16 -> 0.41370219 | D25: =D16 -> 0.36267032 | E25: =E16 -> 0.29434983 | F25: =F16 -> 0.22905995 | G25: =G16 -> 0.21781569 | H25: =H16 -> 0.21813446 | I25: =I16 -> 0.21890997 | ... N25: =N16 -> 0.20883112
B26: =B17 -> MGM China | C26: =C17 -> 0.13810669 | D26: =D17 -> 0.13284404 | E26: =E17 -> 0.054011671 | F26: =F17 -> 0.19681327 | G26: =G17 -> 0.23550067 | H26: =H17 -> 0.25799946 | I26: =I17 -> 0.24937064 | ... N26: =N17 -> 0.26994389
B27: MGM Digital | C27: =C18 -> 0 | D27: =D18 -> 0 | E27: =E18 -> 0 | F27: =F18 -> 0.026969757 | G27: =G18 -> 0.032318943 | H27: =H18 -> 0.037828416 | I27: =I18 -> 0.042616202 | J27: =J18 -> 0.044934542 | ... N27: =N18 -> 0.059329992
B29: Margins | C29: 2020 | D29: 2021 | E29: 2022 | F29: 2023 | G29: 2024 | H29: 2025 | I29: 2026 | J29: 2027 | K29: 2028 | L29: 2029 | M29: 2030 | N29: 2031
B30: {=B19:B21} -> EBITDA Margin | C30: =C19 -> 0.14125282 | D30: =D19 -> 0.21234106 | E30: =E19 -> 0.30882386 | F30: =F19 -> 0.14394601 | G30: =G19 -> 0.13594393 | H30: =H19 -> 0.13829279 | I30: =I19 -> 0.13542688 | J30: =J19 -> 0.13890805 | ... N30: =N19 -> 0.14781656
B31: EBIT Margin | C31: =C20 -> -0.11333088 | D31: =D20 -> 0.086096749 | E31: =E20 -> 0.029617662 | F31: =F20 -> 0.093137172 | G31: =G20 -> 0.087285243 | H31: =H20 -> 0.079439037 | I31: =I20 -> 0.076865989 | J31: =J20 -> 0.080488969 | ... N31: =N20 -> 0.09027801
B32: Net Income | C32: =C21 -> -0.19541008 | D32: =D21 -> -0.026292074 | E32: =E21 -> 0.032321561 | F32: =F21 -> 0.046373121 | G32: =G21 -> 0.043731848 | H32: =H21 -> 0.033415226 | I32: =I21 -> 0.051109199 | J32: =J21 -> 0.056132044 | ... N32: =N21 -> 0.069470651
B34: Credit Metrics | C34: 2020 | D34: 2021 | E34: 2022 | F34: 2023 | G34: 2024 | H34: 2025 | I34: 2026 | J34: 2027 | K34: 2028 | L34: 2029 | M34: 2030 | N34: 2031
B35: {='Base MGM IS'!A41:A46} -> EBIT/Interest | C35: ='Base MGM IS'!B41 -> -0.79673113 | D35: ='Base MGM IS'!C41 -> 0.98137302 | E35: ='Base MGM IS'!D41 -> 0.62083663 | F35: ='Base MGM IS'!E41 -> 3.2422175 | G35: ='Base MGM IS'!F41 -> 3.36359 | H35: ='Base MGM IS'!G41 -> 3.2784017 | I35: ='Base MGM IS'!H41 -> 2.9843 | J35: ='Base MGM IS'!I41 -> 3.304562 | ... N35: ='Base MGM IS'!M41 -> 4.3387539
B36: EBITDA/Interest | C36: ='Base MGM IS'!B42 -> 0.99302611 | D36: ='Base MGM IS'!C42 -> 2.4203676 | E36: ='Base MGM IS'!D42 -> 6.473474 | F36: ='Base MGM IS'!E42 -> 5.0109343 | G36: ='Base MGM IS'!F42 -> 5.2386819 | H36: ='Base MGM IS'!G42 -> 5.7072608 | I36: ='Base MGM IS'!H42 -> 5.2579098 | J36: ='Base MGM IS'!I42 -> 5.703021 | ... N36: ='Base MGM IS'!M42 -> 7.104052
B37: (EBITDA - CAPEX)/Interest | C37: ='Base MGM IS'!B43 -> 0.59236376 | D37: ='Base MGM IS'!C43 -> 1.8063052 | E37: ='Base MGM IS'!D43 -> 5.1876603 | F37: ='Base MGM IS'!E43 -> 2.9861371 | G37: ='Base MGM IS'!F43 -> 2.531284 | H37: ='Base MGM IS'!G43 -> 3.0822256 | I37: ='Base MGM IS'!H43 -> 2.8761743 | J37: ='Base MGM IS'!I43 -> 3.3212855 | ... N37: ='Base MGM IS'!M43 -> 4.7223165
B38: Gross Debt/EBITDAR | C38: ='Base MGM IS'!B44 -> 8.6996939 | D38: ='Base MGM IS'!C44 -> 4.551126 | E38: ='Base MGM IS'!D44 -> 1.3068743 | F38: ='Base MGM IS'!E44 -> 1.611241 | G38: ='Base MGM IS'!F44 -> 1.3763998 | H38: ='Base MGM IS'!G44 -> 1.3234782 | I38: ='Base MGM IS'!H44 -> 1.1799212 | J38: ='Base MGM IS'!I44 -> 0.869094 | ... N38: ='Base MGM IS'!M44 -> 0.3557661
B39: Adjusted Debt/EBITDAR | C39: ='Base MGM IS'!B45 -> 14.597159 | D39: ='Base MGM IS'!C45 -> 8.7571466 | E39: ='Base MGM IS'!D45 -> 5.6145355 | F39: ='Base MGM IS'!E45 -> 7.0581762 | G39: ='Base MGM IS'!F45 -> 6.8014183 | H39: ='Base MGM IS'!G45 -> 6.6262996 | I39: ='Base MGM IS'!H45 -> 6.6283474 | J39: ='Base MGM IS'!I45 -> 5.9566566 | ... N39: ='Base MGM IS'!M45 -> 4.5933554
B40: FCF/ Debt | C40: ='Base MGM IS'!B46 -> -0.052611812 | D40: ='Base MGM IS'!C46 -> -0.0065049474 | E40: ='Base MGM IS'!D46 -> 0.05785177 | F40: ='Base MGM IS'!E46 -> 0.014380451 | G40: ='Base MGM IS'!F46 -> 0.010660719 | H40: ='Base MGM IS'!G46 -> 0.015988486 | I40: ='Base MGM IS'!H46 -> 0.017522559 | J40: ='Base MGM IS'!I46 -> 0.027476648 | ... N40: ='Base MGM IS'!M46 -> 0.055226013
